Workbook

Sheet quick price
A1: Quick Price
A2: RPO | B2: Price
A3: ZR1X Coupe 3LZ | B3: {=XLOOKUP(A3, modelPricing!$B:$B, modelPricing!$C:$C, "0", 0)} -> 218395
A4: R8E T0E | B4: {=XLOOKUP(A4, PriceSchedule!$B:$B, PriceSchedule!$D:$D, "0", 0)} -> 2600
A5: 3F9 | B5: {=XLOOKUP(A5, PriceSchedule!$B:$B, PriceSchedule!$D:$D, "0", 0)} -> 495
A6: NGA | B6: {=XLOOKUP(A6, PriceSchedule!$B:$B, PriceSchedule!$D:$D, "0", 0)} -> 395
A7: PEF | B7: {=XLOOKUP(A7, PriceSchedule!$B:$B, PriceSchedule!$D:$D, "0", 0)} -> 475
A8: SBT | B8: {=XLOOKUP(A8, PriceSchedule!$B:$B, PriceSchedule!$D:$D, "0", 0)} -> 2350
A9: BAZ | B9: {=XLOOKUP(A9, PriceSchedule!$B:$B, PriceSchedule!$D:$D, "0", 0)} -> 595
A10: E60 | B10: {=XLOOKUP(A10, PriceSchedule!$B:$B, PriceSchedule!$D:$D, "0", 0)} -> 2595
A11: ETV | B11: {=XLOOKUP(A11, PriceSchedule!$B:$B, PriceSchedule!$D:$D, "0", 0)} -> 995
A12: FA6 | B12: {=XLOOKUP(A12, PriceSchedule!$B:$B, PriceSchedule!$D:$D, "0", 0)} -> 4995
A13: J6E | B13: {=XLOOKUP(A13, PriceSchedule!$B:$B, PriceSchedule!$D:$D, "0", 0)} -> 695
A14: ZYC | B14: {=XLOOKUP(A14, PriceSchedule!$B:$B, PriceSchedule!$D:$D, "0", 0)} -> 195
A15: SPY | B15: {=XLOOKUP(A15, PriceSchedule!$B:$B, PriceSchedule!$D:$D, "0", 0)} -> 295
A16: SOG | B16: {=XLOOKUP(A16, PriceSchedule!$B:$B, PriceSchedule!$D:$D, "0", 0)} -> 1495
B17: {=XLOOKUP(A17, PriceSchedule!$B:$B, PriceSchedule!$D:$D, "0", 0)} -> 0
B18: {=XLOOKUP(A18, PriceSchedule!$B:$B, PriceSchedule!$D:$D, "0", 0)} -> 0
B19: {=XLOOKUP(A19, PriceSchedule!$B:$B, PriceSchedule!$D:$D, "0", 0)} -> 0
B20: {=XLOOKUP(A20, PriceSchedule!$B:$B, PriceSchedule!$D:$D, "0", 0)} -> 0
B21: {=XLOOKUP(A21, PriceSchedule!$B:$B, PriceSchedule!$D:$D, "0", 0)} -> 0
B22: {=XLOOKUP(A22, PriceSchedule!$B:$B, PriceSchedule!$D:$D, "0", 0)} -> 0
B23: {=XLOOKUP(A23, PriceSchedule!$B:$B, PriceSchedule!$D:$D, "0", 0)} -> 0
B24: {=XLOOKUP(A24, PriceSchedule!$B:$B, PriceSchedule!$D:$D, "0", 0)} -> 0
B25: {=XLOOKUP(A25, PriceSchedule!$B:$B, PriceSchedule!$D:$D, "0", 0)} -> 0
B26: {=XLOOKUP(A26, PriceSchedule!$B:$B, PriceSchedule!$D:$D, "0", 0)} -> 0
B27: {=XLOOKUP(A27, PriceSchedule!$B:$B, PriceSchedule!$D:$D, "0", 0)} -> 0
B28: {=XLOOKUP(A28, PriceSchedule!$B:$B, PriceSchedule!$D:$D, "0", 0)} -> 0
A29: MSRP: | B29: =SUM(B3:B28) -> 236570

Sheet modelPricing
A1: Model | B1: Model Description | C1: List Price | D1: MSRP(c) | E1: New DFC | F1: New List | G1: R8E | H1: LAST YEAR $$$ Incl DFC | I1: $ DIFF | J1: Diff Stingray | K1: Diff ERAY | L1: Diff Z06 | M1: Diff ZR1 | N1: Diff ZR1X
A2: 1YC07 | B2: Stingray Coupe 1LT | C2: 71995 | D2: 70000 | E2: 2495 | F2: =D2+E2 -> 72495 | G2: 0 | H2: 70195 | I2: 1800 | K2: =C2-C8 -> -38600 | L2: =C2-C14 -> -47700 | M2: =C2-C20 -> -110400 | N2: =C2-C24 -> -135400
A3: 1YC07 | B3: Stingray Coupe 2LT | C3: 79095 | D3: 77100 | E3: 2495 | F3: =D3+E3 -> 79595 | G3: 0 | H3: 77295 | I3: 1800 | K3: =C3-C9 -> -37000 | L3: =C3-C15 -> -49500
A4: 1YC07 | B4: Stingray Coupe 3LT | C4: 83745 | D4: 81750 | E4: 2495 | F4: =D4+E4 -> 84245 | G4: 0 | H4: 81945 | I4: 1800 | K4: =C4-C10 -> -37800 | L4: =C4-C16 -> -49500 | M4: =C4-C21 -> -109650 | N4: =C4-C25 -> -134650
A5: 1YC67 | B5: Stingray Convertible 1LT | C5: 78995 | D5: 77000 | E5: 2495 | F5: =D5+E5 -> 79495 | G5: 0 | H5: 77195 | I5: 1800 | K5: =C5-C11 -> -38600 | L5: =C5-C17 -> -47700 | M5: =C5-C22 -> -113400 | N5: =C5-C26 -> -138400
A6: 1YC67 | B6: Stingray Convertible 2LT | C6: 86095 | D6: 84100 | E6: 2495 | F6: =D6+E6 -> 86595 | G6: 0 | H6: 84295 | I6: 1800 | K6: =C6-C12 -> -37000 | L6: =C6-C18 -> -49500
A7: 1YC67 | B7: Stingray Convertible 3LT | C7: 90745 | D7: 88750 | E7: 2495 | F7: =D7+E7 -> 91245 | G7: 0 | H7: 88945 | I7: 1800 | K7: =C7-C13 -> -37800 | L7: =C7-C19 -> -49500 | M7: =C7-C23 -> -112650 | N7: =C7-C27 -> -137650
A8: 1YG07 | B8: E-Ray Coupe 1LZ | C8: 110595 | D8: 108600 | E8: 2495 | F8: =D8+E8 -> 111095 | G8: 0 | H8: 108795 | I8: 1800 | J8: =C8-C2 -> 38600 | L8: =C8-C14 -> -9100
A9: 1YG07 | B9: E-Ray Coupe 2LZ | C9: 116095 | D9: 114100 | E9: 2495 | F9: =D9+E9 -> 116595 | G9: 0 | H9: 114295 | I9: 1800 | J9: =C9-C3 -> 37000 | L9: =C9-C15 -> -12500
A10: 1YG07 | B10: E-Ray Coupe 3LZ | C10: 121545 | D10: 119550 | E10: 2495 | F10: =D10+E10 -> 122045 | G10: 0 | H10: 119745 | I10: 1800 | J10: =C10-C4 -> 37800 | L10: =C10-C16 -> -11700
A11: 1YG67 | B11: E-Ray Convertible 1LZ | C11: 117595 | D11: 115600 | E11: 2495 | F11: =D11+E11 -> 118095 | G11: 0 | H11: 115795 | I11: 1800 | J11: =C11-C5 -> 38600 | L11: =C11-C17 -> -9100
A12: 1YG67 | B12: E-Ray Convertible 2LZ | C12: 123095 | D12: 121100 | E12: 2495 | F12: =D12+E12 -> 123595 | G12: 0 | H12: 121295 | I12: 1800 | J12: =C12-C6 -> 37000 | L12: =C12-C18 -> -12500
A13: 1YG67 | B13: E-Ray Convertible 3LZ | C13: 128545 | D13: 126550 | E13: 2495 | F13: =D13+E13 -> 129045 | G13: 0 | H13: 126745 | I13: 1800 | J13: =C13-C7 -> 37800 | L13: =C13-C19 -> -11700
A14: 1YH07 | B14: Z06 Coupe 1LZ | C14: 119695 | D14: 117700 | E14: 2495 | F14: =D14+E14 -> 120195 | H14: 113995 | I14: 5700 | J14: =C14-C2 -> 47700 | K14: =C14-C8 -> 9100
A15: 1YH07 | B15: Z06 Coupe 2LZ | C15: 128595 | D15: 126600 | E15: 2495 | F15: =D15+E15 -> 129095 | H15: 122895 | I15: 5700 | J15: =C15-C3 -> 49500 | K15: =C15-C9 -> 12500
A16: 1YH07 | B16: Z06 Coupe 3LZ | C16: 133245 | D16: 131250 | E16: 2495 | F16: =D16+E16 -> 133745 | H16: 127545 | I16: 5700 | J16: =C16-C4 -> 49500 | K16: =C16-C10 -> 11700
A17: 1YH67 | B17: Z06 Convertible 1LZ | C17: 126695 | D17: 124700 | E17: 2495 | F17: =D17+E17 -> 127195 | H17: 120995 | I17: 5700 | J17: =C17-C5 -> 47700 | K17: =C17-C11 -> 9100
A18: 1YH67 | B18: Z06 Convertible 2LZ | C18: 135595 | D18: 133600 | E18: 2495 | F18: =D18+E18 -> 136095 | H18: 129895 | I18: 5700 | J18: =C18-C6 -> 49500 | K18: =C18-C12 -> 12500
A19: 1YH67 | B19: Z06 Convertible 3LZ | C19: 140245 | D19: 138250 | E19: 2495 | F19: =D19+E19 -> 140745 | H19: 134545 | I19: 5700 | J19: =C19-C7 -> 49500 | K19: =C19-C13 -> 11700
A20: 1YR07 | B20: ZR1 Coupe 1LZ | C20: 182395 | D20: 180400 | E20: 2495 | F20: =D20+E20 -> 182895 | H20: 175195 | I20: 7200 | J20: =C20-C2 -> 110400 | K20: =C20-C8 -> 71800
A21: 1YR07 | B21: ZR1 Coupe 3LZ | C21: 193395 | D21: 191400 | E21: 2495 | F21: =D21+E21 -> 193895 | H21: 186195 | I21: 7200 | J21: =C21-C4 -> 109650 | K21: =C21-C10 -> 71850
A22: 1YR67 | B22: ZR1 Convertible 1LZ | C22: 192395 | D22: 190400 | E22: 2495 | F22: =D22+E22 -> 192895 | H22: 185195 | I22: 7200 | J22: =C22-C5 -> 113400 | K22: =C22-C11 -> 74800
A23: 1YR67 | B23: ZR1 Convertible 3LZ | C23: 203395 | D23: 201400 | E23: 2495 | F23: =D23+E23 -> 203895 | H23: 196195 | I23: 7200 | J23: =C23-C7 -> 112650 | K23: =C23-C13 -> 74850
A24: 1YS07 | B24: ZR1X Coupe 1LZ | C24: 207395 | D24: 207100 | E24: 2495 | F24: =D24+E24 -> 209595 | J24: =C24-C2 -> 135400 | K24: =C24-C8 -> 96800
A25: 1YS07 | B25: ZR1X Coupe 3LZ | C25: 218395 | D25: 218100 | E25: 2495 | F25: =D25+E25 -> 220595 | J25: =C25-C4 -> 134650 | K25: =C25-C10 -> 96850
A26: 1YS67 | B26: ZR1X Convertible 1LZ | C26: 217395 | D26: 217100 | E26: 2495 | F26: =D26+E26 -> 219595 | J26: =C26-C5 -> 138400 | K26: =C26-C11 -> 99800
A27: 1YS67 | B27: ZR1X Convertible 3LZ | C27: 228395 | D27: 228100 | E27: 2495 | F27: =D27+E27 -> 230595 | J27: =C27-C7 -> 137650 | K27: =C27-C13 -> 99850

Sheet STINGRAY
A1: RPO Code | B1: Name | C1: Price | D1: Detail | E1: Compatibility | F1: Category | G1: Section | H1: Column 8
A2: 5DG | B2: 20-Spoke Tech Bronze Forged Aluminum Rims | C2: 3650 | D2: Comes as a Second Set of Wheels. Includes Bronze center caps, Black wheel locks and Black Lugnuts | E2: Not available w/ R8C | F2: lpo, wheels | G2: Exterior Accessories | H2: {=UNIQUE(G2:G133)} -> Exterior Accessories
A3: 5DO | B3: 15-spoke Bright polished aluminum wheels | C3: 4695 | D3: Comes as a 2nd set of wheels | E3: Not available w/ R8C | F3: lpo, wheels | G3: Exterior Accessories | H3: Carbon Fiber
A4: 5JR | B4: Visible Carbon Fiber Mirror Covers | C4: 1250 | D4: 3LT/LZ only. Adds DRG carbon flash painted mirrors (N/C) | E4: 3LT/LZ only. Available with 1LZ on ZR1. | F4: carbon_fiber, lpo | G4: Carbon Fiber | H4: Spoilers
A5: 5V5 | B5: High Wing Spoiler- Carbon Fiber Weave | C5: 7995 | D5: Not available at this time. | F5: spoilers, carbon_fiber | G5: Spoilers | H5: Wheel Accessories
A6: 5V7 | B6: Black Ground Effects | C6: 625 | D6: Includes STI and Front splitter. | E6: Requires 5V5, 5ZU, 5ZZ | F6: lpo | G6: Exterior Accessories | H6: Engine Appearance
A7: 5ZC | B7: Jake Logo wheel center caps | C7: 250 | F7: lpo, wheels | G7: Wheel Accessories | H7: Custom Delivery
A8: 5ZD | B8: Carbon Flash Center Caps w/ Crossed Flags logo | C8: 250 | F8: lpo, wheels | G8: Wheel Accessories | H8: Coupe Roof Panel
A9: 5ZU | B9: High Wing Spoiler- Body color | C9: 1350 | D9: Deletes T0A Z51 rear spoiler when ordered with Z51 Performance Package. | E9: Requires exterior color G8G Arctic White, GBA Black or GKZ Torch Red, Not available with 5V5, 5ZW, 5ZZ, TVS, | F9: spoilers, lpo | G9: Spoilers | H9: Interior Accessories
A10: 5ZW | B10: Visible carbon fiber two-stanchion spoiler, LPO | C10: 6225 | D10: Deletes T0A Z51 rear spoiler when ordered with Z51 Performance Package | E10: Not available with 5V5, 5ZU, 5ZZ, TVS | F10: spoilers, carbon_fiber | G10: Carbon Fiber | H10: Convertible Roof Panel
A11: 5ZZ | B11: High Wing Spoiler- Carbon Flash Painted | C11: 1395 | D11: Dealer Installed. Deletes T0A Z51 rear spoiler when ordered with Z51 Performance Package. | E11: Not available with 5V5, 5ZW, 5ZZ, TVS, | F11: spoilers, lpo | G11: Spoilers | H11: Stripes
A12: B6P | B12: Coupe Engine Appearance Package | C12: 1695 | D12: Includes Carbon Fiber Trim, D3V Engine Bay Lights, and SL9 Engine Specification Plaque | F12: engine_bay, carbon_fiber | G12: Engine Appearance | H12: Mechanical
A13: BC7 | B13: LT2 Engine Cover, Black | C13: 0 | D13: Standard on Coupe. Includes metal Corvette nameplate | E13: Requires ZZ3 Engine appearance package on Convertible. | F13: engine_bay | G13: Engine Appearance | H13: Accents
A14: BCP | B14: LPO, Engine Cover in Edge Red | C14: 495 | D14: Includes D3V Engine Bay Lights on Coupe. | E14: When equipped with B6P on Coupe. Requires ZZ3 Engine appearance package on Convertible. | F14: engine_bay, lpo | G14: Engine Appearance | H14: Badges
A15: BCP-s | B15: LPO, Engine Cover in Edge Red | C15: 595 | D15: Includes D3V Engine Bay Lights on Coupe. | E15: Not Equipped with B6P. Requires ZZ3 Engine appearance package on Convertible. | F15: engine_bay, lpo | G15: Engine Appearance | H15: Paint Color
A16: BCS | B16: LPO, Engine Cover in Sterling Silver | C16: 495 | D16: Silver with metal Corvette nameplate. | E16: When equipped with B6P on Coupe. Requires ZZ3 Engine appearance package on Convertible. | F16: engine_bay, lpo | G16: Engine Appearance | H16: Brake Calipers
A17: BCS-s | B17: LPO, Engine Cover in Sterling Silver | C17: 595 | D17: Includes D3V Engine Bay Lights on Coupe. | E17: Not Equipped with B6P. Requires ZZ3 Engine appearance package on Convertible. | F17: engine_bay, lpo | G17: Engine Appearance | H17: LPO Packages
A18: BV4 | B18: Plaque, personalized, custom-made with your name and VIN | C18: 295 | D18: Personalized plaque is included in museum delivery R8C, Plaque is located between the seats on the speaker grille. | F18: customdelivery | G18: Custom Delivery | H18: Wheels
A19: C2Z | B19: Visible Carbon Fiber weave w/body color border roof panel | C19: 2495 | F19: roof, carbon_fiber | G19: Coupe Roof Panel | H19: Car Covers
A20: CAV | B20: Contoured Cargo Area Liners w/ Jake logo | C20: 195 | D20: Included w/PEF. Stingray and Z06 include both cargo areas. E-Ray and ZR1 rear trunk only | F20: lpo | G20: Interior Accessories
A21: CC3 | B21: Transparent Glass roof panel | C21: 995 | F21: roof | G21: Coupe Roof Panel
A22: CF7 | B22: Body-Color Carbon Roof panel | C22: 0 | D22: Standard | F22: roof | G22: Coupe Roof Panel
A23: CF8 | B23: Electrochromic Dimming Roof Panel | C23: 3000 | D23: Electrochromic dimming, removable. | E23: Not available on 1LT, 1LZ. Not available with any Full Length Dual Racing Stripes (DPB, DPC, DPG, DPL, DPT, DSY, DSZ, DT0, DTB, DTH, DUB, DUK, DUW). | F23: roof | G23: Coupe Roof Panel
A24: CM9 | B24: Body-Color roof and nacelles | C24: 0 | D24: Standard | F24: roof | G24: Convertible Roof Panel
A25: D3V | B25: Engine Bay, Lights only | C25: 100 | D25: Coupe Only. Included with BCP, BCS, B6P, BCW. | F25: engine_bay | G25: Engine Appearance
A26: D84 | B26: Carbon Flash painted nacelles and roof | C26: 1295 | D26: Not available w/ GBA Black | E26: Not available w/ GBA Black | F26: roof | G26: Convertible Roof Panel
A27: D86 | B27: Carbon Flash painted nacelles and body color roof | C27: 1295 | D27: Not available w/ GBA Black | E27: Not available w/ GBA Black | F27: roof | G27: Convertible Roof Panel
A28: DPB | B28: Carbon Flash with Blue accent Full Length Dual Racing Stripes | C28: 1195 | D28: Not available with exterior color GJV Riptide Blue Metallic, GMO Rapid Blue, or GXL Hysteria Purple. | E28: Not available with exterior color GJV Riptide Blue Metallic, GMO Rapid Blue, or GXL Hysteria Purple. | F28: stripes | G28: Stripes
A29: DPC | B29: Carbon Flash with Yellow accent Full Length Dual Racing Stripes | C29: 1195 | D29: Not available with exterior color GBK Competition Yellow Tintcoat Metallic. | E29: Not available with exterior color GBK Competition Yellow Tintcoat Metallic. | F29: stripes | G29: Stripes
A30: DPG | B30: Carbon Flash with Orange accent Full Length Dual Racing Stripes | C30: 1195 | D30: Not available with exterior color G26 Sebring Orange Tintcoat. | E30: Not available with exterior color G26 Sebring Orange Tintcoat. | F30: stripes | G30: Stripes
A31: DPL | B31: Carbon Flash with Red accent Full Length Dual Racing Stripes | C31: 1195 | D31: Not available with exterior color GKZ Torch Red or GPH Red Mist Metallic Tintcoat. | E31: Not available with exterior color GKZ Torch Red or GPH Red Mist Metallic Tintcoat. | F31: stripes | G31: Stripes
A32: DPT | B32: Carbon Flash with Silver accent Full Length Dual Racing Stripes | C32: 1195 | F32: stripes | G32: Stripes
A33: DSY | B33: Edge Orange Full Length Dual Racing Stripe | C33: 1195 | D33: Not available with exterior color G26 Sebring Orange Tintcoat. | E33: Not available with exterior color G26 Sebring Orange Tintcoat. | F33: stripes | G33: Stripes
A34: DSZ | B34: Edge Red Full Length Dual Racing Stripe | C34: 1195 | D34: Not available with exterior color GKZ Torch Red or GPH Red Mist Metallic Tintcoat. | E34: Not available with exterior color GKZ Torch Red or GPH Red Mist Metallic Tintcoat. | F34: stripes | G34: Stripes
A35: DT0 | B35: Competition Yellow Full Length Dual Racing Stripe | C35: 1195 | D35: Not available with exterior color GBK Competition Yellow Tintcoat Metallic. | E35: Not available with exterior color GBK Competition Yellow Tintcoat Metallic. | F35: stripes | G35: Stripes
A36: DTH | B36: Carbon Flash Full Length Dual Racing Stripe | C36: 1195 | F36: stripes | G36: Stripes
A37: DUB | B37: Sterling Silver Full Length Dual Racing Stripe | C37: 1195 | F37: stripes | G37: Stripes
A38: DUK | B38: Asymmetrical Adrenaline Red/Carbon Flash Full Length Dual Racing Stripes | C38: 1195 | D38: Not available with exterior color (GKZ) Torch Red or (GPH) Red Mist Metallic Tintcoat. | E38: Not available with exterior color (GKZ) Torch Red or (GPH) Red Mist Metallic Tintcoat. | F38: stripes | G38: Stripes
A39: DUW | B39: Edge Blue Full Length Dual Racing Stripe | C39: 1195 | D39: Not available with exterior color GJV Riptide Blue Metallic, GMO Rapid Blue, or GXL Hysteria Purple. | E39: Not available with exterior color GJV Riptide Blue Metallic, GMO Rapid Blue, or GXL Hysteria Purple. | F39: stripes | G39: Stripes
A40: DZU | B40: Stinger Stripe, Carbon Flash/ Competition Yellow | C40: 500 | D40: Not available with exterior color GBK Competition Yellow Tintcoat Metallic. | E40: Not available with exterior color GBK Competition Yellow Tintcoat Metallic. | F40: stripes | G40: Stripes
A41: DZV | B41: Stinger Stripe, Carbon Flash/ Midnight Silver | C41: 500 | F41: stripes | G41: Stripes
A42: DZX | B42: Stinger Stripe, Carbon Flash/ Edge Red | C42: 500 | D42: Not available with exterior color GKZ Torch Red or GPH Red Mist Metallic Tintcoat. | E42: Not available with exterior color GKZ Torch Red or GPH Red Mist Metallic Tintcoat. | F42: stripes | G42: Stripes
A43: E60 | B43: Front lift adjustable height w/ memory | C43: 2595 | D43: 2LT/Z or 3LT/Z trim level only | E43: 2LT/Z or 3LT/Z trim level only | F43: mechanical | G43: Mechanical
A44: EFR | B44: Carbon Flash exterior accents | C44: 0 | D44: Standard Carbon Flash. Includes side vents and front/rear grille accents. Includes tonneau vent on convertible. Includes rockers on E-Ray and Z06 | F44: accents | G44: Accents
A45: EFY | B45: Body Color exterior accents | C45: 995 | D45: Includes side vents and front/rear grille accents. Includes tonneau vent on convertible. | E45: Not available with Black [GBA] | F45: accents | G45: Accents
A46: ERI | B46: Battery Protection Package | C46: 100 | D46: Battery tender used to keep the battery charged when vehicle is stored for long periods of time. | F46: mechanical | G46: Mechanical
A47: EYK | B47: Chrome Exterior Badge Package | C47: 295 | D47: Includes badges on the nose and decklid, "Corvette" script on rear, and lower rocker badge on wide-body models. | F47: badges | G47: Badges
A48: EYT | B48: Carbon Flash Exterior Badge Package | C48: 0 | D48: Standard. Includes badges on the nose and decklid, "Corvette" script on rear, and lower rocker badge on wide-body models. | F48: badges | G48: Badges
A49: FE2 | B49: Magnetic Selective Ride Control without Z51 package | C49: 1895 | D49: NON-Z51 | E49: Without Z51 | F49: mechanical | G49: Mechanical
A50: FE4 | B50: Magnetic Selective Ride Control with PTM | C50: 1895 | D50: Z51, Includes Performance Traction Management | E50: With Z51 | F50: mechanical | G50: Mechanical
A51: G26 | B51: Sebring Orange Tintcoat | C51: 995 | D51: Premium Tintcoat Color new | F51: paint | G51: Paint Color
A52: G4Z | B52: Roswell Green Metallic exterior color (extra cost) | C52: 500 | D52: new Premium Color | F52: paint | G52: Paint Color
A53: G8G | B53: Arctic White | C53: 0 | F53: paint | G53: Paint Color
A54: GBA | B54: Black | C54: 0 | F54: paint | G54: Paint Color
A55: GBK | B55: Competition Yellow Tintcoat Metallic | C55: 995 | D55: Premium Tintcoat Color new | F55: paint | G55: Paint Color
A56: GJV | B56: Riptide Blue Metallic | C56: 0 | F56: paint | G56: Paint Color
A57: GKA | B57: Blade Silver Metallic exterior color | C57: 0 | D57: new | F57: paint | G57: Paint Color
A58: GKZ | B58: Torch Red | C58: 0 | F58: paint | G58: Paint Color
A59: GPH | B59: Red Mist Metallic Tintcoat | C59: 995 | D59: Premium Tintcoat Color | F59: paint | G59: Paint Color
A60: GXL | B60: Hysteria Purple Metallic | C60: 0 | F60: paint | G60: Paint Color
A61: J6A | B61: Black Painted Calipers | C61: 0 | D61: Standard, Gloss finish. Not available with J57 | E61: Not available with J57 ceramic brakes | F61: calipers | G61: Brake Calipers
A62: J6E | B62: Velocity Yellow Painted Calipers | C62: 695 | D62: Gloss finish | F62: calipers | G62: Brake Calipers
A63: J6F | B63: Bright Red Painted Calipers | C63: 695 | D63: Gloss finish | F63: calipers | G63: Brake Calipers
A64: J6N | B64: Edge Red Painted Calipers | C64: 695 | D64: Darker shade of red, satin finish | F64: calipers | G64: Brake Calipers
A65: NGA | B65: Black Exhaust Tips | C65: 395 | D65: Requires NPP (Stingray) | E65: Requires NPP | F65: mechanical | G65: Mechanical
A66: NPP | B66: Performance Exhaust | C66: 1195 | D66: NON-Z51, Adds 5hp and 5lb/ft tq. Standard on Z51 | F66: mechanical | G66: Mechanical
A67: PCU | B67: Stingray Protection Package | C67: 1195 | D67: Includes VWE front grille screens, STI black composite rocker extensions, and VQK splash guards. Not available with 5V7 ground effects. | E67: Not available with 5V7 ground effects. | F67: lpo | G67: LPO Packages
A68: PCX | B68: Tech Bronze Accent Package | C68: 4395 | D68: Includes 5DG, SFZ, SHT, and SNG | E68: Not available with EYK, PDV, SB7 or stripes DPB, DPC, DPG, DPL, DPT, DSY, DSZ, DT0, DTH, DUB, DUW, DZU, DZV, DZX | F68: lpo, wheels, stripes, badges | G68: LPO Packages
A69: PDV | B69: Stingray R Appearance Package | C69: 750 | D69: Includes SB7 and VWD | F69: lpo, stripes | G69: LPO Packages
A70: PDY | B70: Roadside Safety Package | C70: 195 | D70: Includes First Aid Kit RYT and Highway Safety Kit S08 | F70: lpo | G70: LPO Packages
A71: PEF | B71: Contoured Liner Protection Package | C71: 475 | D71: Includes CAV and RIA. ZR1 includes rear cargo liner only | F71: lpo | G71: LPO Packages
A72: PIN | B72: Customer selectable VIN ending* | C72: 5000 | D72: This option is subject to restrictions and approval. | F72: customdelivery | G72: Custom Delivery
A73: Q99 | B73: 20 Spoke Bright Machined-face | C73: 1995 | D73: (19" x 8.5" Front / 20" x 11" Rear) Forged Aluminum Rims | F73: wheels | G73: Wheels
A74: Q9A | B74: 20 Spoke Midnight Gray w/ Red Stripe | C74: 1495 | D74: (19" x 8.5" Front / 20" x 11" Rear) Forged Aluminum Rims | F74: wheels | G74: Wheels
A75: Q9I | B75: 20 Spoke Gloss Black | C75: 995 | D75: (19" x 8.5" Front / 20" x 11" Rear) Forged Aluminum Rims | F75: wheels | G75: Wheels
A76: Q9O | B76: 5-split-spoke Satin Graphite with machined edge | C76: 995 | D76: (19" x 8.5" Front / 20" x 11" Rear) Forged Aluminum Rims | F76: wheels | G76: Wheels
A77: Q9Y | B77: 5-split spoke machined-face Sterling Silver-painted | C77: 995 | D77: (19" x 8.5" Front / 20" x 11" Rear) Forged Aluminum Rims | F77: wheels | G77: Wheels
A78: QE5 | B78: 5-split spoke Black Painted | C78: 995 | D78: (19" x 8.5" Front / 20" x 11" Rear) Forged Aluminum Rims | F78: wheels | G78: Wheels
A79: QEB | B79: 5-split-spoke Pearl Nickel forged aluminum wheels | C79: 0 | D79: Standard (19" x 8.5" Front / 20" x 11" Rear) Forged Aluminum Rims | F79: wheels | G79: Wheels
A80: R88 | B80: NEW! LPO, Illuminated crossed flags emblem | C80: 495 | D80: Not available at start of production. | E80: Not available with (SFZ) Dark Stealth crossed flags emblems, LPO, (EYK) Chrome Exterior Badge Package or any Full Length Dual Racing Stripes (DPB, DPC, DPG, DPL, DPT, DSY, DSZ, DT0, DTB, DTH, DUB, DUK, DUK, DUW). | F80: lpo | G80: Exterior Accessories
A81: R8C | B81: Corvette Museum Delivery | C81: 1495 | D81: Guided VIP tour of the Corvette Assembly Plant (when available) for customer and 3 guests, Guided VIP tour of the NCM where the owner will see their Corvette on display, Quality, detailed orientation of the car by Delivery Team Guide, Celebratory drive out of the Museum (complimentary SD card to record for those with PDR), Unique gold RSC decal placed on the inside of the driver's door jamb, Custom interior dash plaque, Individual one-year NCM membership, Commemorative wall plaque with nameplate (customer's name, date of delivery, VIN#), Opportunity to purchase exclusive apparel, bricks and build sheet, Delivery can be viewed world-wide via our live webcams, Photos of the customer with the car (shared via email) | F81: customdelivery | G81: Custom Delivery
A82: RIA | B82: All Weather floor liner w/ Jake logo | C82: 265 | D82: Included w/PEF | F82: lpo | G82: Interior Accessories
A83: RIK | B83: Rear Corvette Script, Torch Red | C83: 425 | D83: Not available with SL8, RIN | E83: Not available with SL8, RIN | F83: lpo | G83: Exterior Accessories
A84: RIN | B84: Rear Corvette Script, Arctic White | C84: 395 | D84: Not available with SL8, RIK | E84: Not available with SL8, RIK | F84: lpo | G84: Exterior Accessories
A85: RNX | B85: Premium outdoor car cover, Gray, Stingray logo, access panels | C85: 495 | D85: Not available with High Wing | E85: Not available with High Wing | F85: lpo | G85: Car Covers
A86: RWH | B86: Premium Indoor car cover, Black with crossed flags logo | C86: 495 | F86: lpo | G86: Car Covers
A87: RWJ | B87: Premium outdoor car cover, Gray w/ Crossed Flags logo & Vette Silhouette | C87: 495 | F87: lpo | G87: Car Covers
A88: RWU | B88: Cargo Area Organizer, collapsible | C88: 175 | F88: lpo | G88: Interior Accessories
A89: RXH | B89: Silver wheel center caps w/ Stingray logo & Red outline | C89: 250 | F89: lpo, wheels | G89: Wheel Accessories
A90: RXJ | B90: Black wheel center caps with Gray Stingray logo | C90: 250 | F90: lpo, wheels | G90: Wheel Accessories
A91: RYQ | B91: Visible Carbon Fiber Door Intake Trim | C91: 3995 | D91: Not available with (EFY) body-color exterior accents. | E91: Not available with (EFY) body-color exterior accents. | F91: carbon_fiber, lpo | G91: Carbon Fiber
A92: RYT | B92: First Aid Kit, Genuine Corvette Accessory | C92: 60 | D92: Included in PDY | F92: lpo | G92: Interior Accessories
A93: RZ9 | B93: Visible Carbon Fiber Grille Insert | C93: 2495 | D93: Not available at this time, Not available with EFY body-color exterior accents. | E93: Not available at this time, Not available with EFY body-color exterior accents. | F93: carbon_fiber, lpo | G93: Carbon Fiber
A94: S08 | B94: Highway Safety Kit, Genuine Corvette Accessory | C94: 150 | D94: Included in PDY | F94: lpo | G94: Interior Accessories
A95: S2L | B95: Premium Leather weekend travel bags | C95: 1695 | D95: Set of 2 | F95: lpo | G95: Interior Accessories
A96: S47 | B96: Chrome lug nuts | C96: 275 | F96: lpo, wheels | G96: Wheel Accessories
A97: SB7 | B97: Corvette Racing themed graphics w/ Jake and Stingray R logos | C97: 495 | D97: Dealer Installed | F97: stripes | G97: Stripes
A98: SC7 | B98: Roof panel storage pouch | C98: 195 | D98: Keeps roof panel protected when storing OUTSIDE of car. Can NOT store roof panel in pouch and put in rear trunk; damage can occur to the roof panel and trunk lid. | E98: Coupe only | F98: lpo | G98: Exterior Accessories
A99: SDA | B99: Black recovery hook | C99: 125 | F99: lpo | G99: Exterior Accessories
A100: SFE | B100: Wheel locks | C100: 125 | F100: lpo, wheels | G100: Wheel Accessories
...

Sheet Sheet5
A1: Body Style | B1: 6157] | C1: 6157] | D1: 6157] | E1: [if | F1: [ | G1: [/if | H1: =textjoin("",true,E1,B1,F1,C1,G1,D1) -> [if 6157][6157][/if 6157]
A2: Trim Level | B2: 6158] | C2: 6158] | D2: 6158] | E2: [if | F2: [ | G2: [/if | H2: =textjoin("",true,E2,B2,F2,C2,G2,D2) -> [if 6158][6158][/if 6158]
A3: Config Total | B3: 6164] | C3: 6164] | D3: 6164] | E3: [if | F3: [ | G3: [/if | H3: =textjoin("",true,E3,B3,F3,C3,G3,D3) -> [if 6164][6164][/if 6164]
A4: Config Total1 | B4: 6165] | C4: 6165] | D4: 6165] | E4: [if | F4: [ | G4: [/if | H4: =textjoin("",true,E4,B4,F4,C4,G4,D4) -> [if 6165][6165][/if 6165]
A5: Color | B5: 6168] | C5: 6168] | D5: 6168] | E5: [if | F5: [ | G5: [/if | H5: =textjoin("",true,E5,B5,F5,C5,G5,D5) -> [if 6168][6168][/if 6168]
A6: Wheels | B6: 6169] | C6: 6169] | D6: 6169] | E6: [if | F6: [ | G6: [/if | H6: =textjoin("",true,E6,B6,F6,C6,G6,D6) -> [if 6169][6169][/if 6169]
A7: Backup Wheels | B7: 6172] | C7: 6172] | D7: 6172] | E7: [if | F7: [ | G7: [/if | H7: =textjoin("",true,E7,B7,F7,C7,G7,D7) -> [if 6172][6172][/if 6172]
A8: Brake Calipers | B8: 6174] | C8: 6174] | D8: 6174] | E8: [if | F8: [ | G8: [/if | H8: =textjoin("",true,E8,B8,F8,C8,G8,D8) -> [if 6174][6174][/if 6174]
A9: Coupe Roof Panel | B9: 6175] | C9: 6175] | D9: 6175] | E9: [if | F9: [ | G9: [/if | H9: =textjoin("",true,E9,B9,F9,C9,G9,D9) -> [if 6175][6175][/if 6175]
A10: Convertible Roof and Nacelles | B10: 6176] | C10: 6176] | D10: 6176] | E10: [if | F10: [ | G10: [/if | H10: =textjoin("",true,E10,B10,F10,C10,G10,D10) -> [if 6176][6176][/if 6176]
A11: GBA Roof Panel | B11: 6177] | C11: 6177] | D11: 6177] | E11: [if | F11: [ | G11: [/if | H11: =textjoin("",true,E11,B11,F11,C11,G11,D11) -> [if 6177][6177][/if 6177]
A12: Badges | B12: 6178] | C12: 6178] | D12: 6178] | E12: [if | F12: [ | G12: [/if | H12: =textjoin("",true,E12,B12,F12,C12,G12,D12) -> [if 6178][6178][/if 6178]
... A131: User ID | B131: 6375] | C131: 6375] | D131: 6375] | E131: [if | F131: [ | G131: [/if | H131: =textjoin("",true,E131,B131,F131,C131,G131,D131) -> [if 6375][6375][/if 6375]

Sheet Pivot Table 2

Sheet STINGRAY_INT
A1: Section | B1: Trim | C1: Seat | D1: RPO | E1: Suede | F1: Stitching | G1: Two Tone | H1: Name | I1: Detail | J1: Price | K1: Category | L1: Codes
A2: 1LT Colors | B2: 1LT | C2: AQ9 | D2: HTA | H2: Jet Black Mulan | I2: AQ9 GT1 Seats . Interior color on seats only. Stitching will match int color. Jet Black has silver stitching. | J2: =SUM( SUMIFS( PriceRef!$D$2:$D154, PriceRef!$A$2:$A154, "Seat", PriceRef!$B$2:$B154, $B2, PriceRef!$C$2:$C154, $C2 ), SUMIFS( PriceRef!$D$2:$D154, PriceRef!$A$2:$A154, "Stitching", PriceRef!$C$2:$C154, $F2 ), SUMIFS( PriceRef!$D$2:$D154, PriceRef!$A$2:$A154, "Suede", PriceRef!$C$2:$C154, $E2 ), SUMIFS( PriceRef!$D$2:$D154, PriceRef!$A$2:$A154, "TwoTone", PriceRef!$C$2:$C154, $G2 ) ) -> 0 | K2: interior.1 | L2: =textjoin(" ",true,B2,C2,D2,F2,E2,G2) -> 1LT AQ9 HTA
A3: 1LT Colors | B3: 1LT | C3: AE4 | D3: HTJ | E3: N26 | H3: Jet Black Performance Textile | I3: AE4 Comp Seats. Adds N26 suede steering wheel. Seat back and bottom are all performance textile. Interior color on seats only. Jet Black has silver stitching. | J3: =SUM( SUMIFS( PriceRef!$D$2:$D154, PriceRef!$A$2:$A154, "Seat", PriceRef!$B$2:$B154, $B3, PriceRef!$C$2:$C154, $C3 ), SUMIFS( PriceRef!$D$2:$D154, PriceRef!$A$2:$A154, "Stitching", PriceRef!$C$2:$C154, $F3 ), SUMIFS( PriceRef!$D$2:$D154, PriceRef!$A$2:$A154, "Suede", PriceRef!$C$2:$C154, $E3 ), SUMIFS( PriceRef!$D$2:$D154, PriceRef!$A$2:$A154, "TwoTone", PriceRef!$C$2:$C154, $G3 ) ) -> 695 | K3: interior.1 | L3: =textjoin(" ",true,B3,C3,D3,F3,E3,G3) -> 1LT AE4 HTJ N26
A4: 1LT Colors | B4: 1LT | C4: AQ9 | D4: HUP | H4: Sky Cool Gray Mulan | I4: AQ9 GT1 Seats. Interior color on seats only. Stitching will match int color. | J4: =SUM( SUMIFS( PriceRef!$D$2:$D154, PriceRef!$A$2:$A154, "Seat", PriceRef!$B$2:$B154, $B4, PriceRef!$C$2:$C154, $C4 ), SUMIFS( PriceRef!$D$2:$D154, PriceRef!$A$2:$A154, "Stitching", PriceRef!$C$2:$C154, $F4 ), SUMIFS( PriceRef!$D$2:$D154, PriceRef!$A$2:$A154, "Suede", PriceRef!$C$2:$C154, $E4 ), SUMIFS( PriceRef!$D$2:$D154, PriceRef!$A$2:$A154, "TwoTone", PriceRef!$C$2:$C154, $G4 ) ) -> 0 | K4: interior.1 | L4: =textjoin(" ",true,B4,C4,D4,F4,E4,G4) -> 1LT AQ9 HUP
A5: 1LT Colors | B5: 1LT | C5: AQ9 | D5: HUQ | H5: Adrenaline Red Mulan | I5: AQ9 GT1 Seats. Interior color on seats only. Stitching will match int color. | J5: =SUM( SUMIFS( PriceRef!$D$2:$D154, PriceRef!$A$2:$A154, "Seat", PriceRef!$B$2:$B154, $B5, PriceRef!$C$2:$C154, $C5 ), SUMIFS( PriceRef!$D$2:$D154, PriceRef!$A$2:$A154, "Stitching", PriceRef!$C$2:$C154, $F5 ), SUMIFS( PriceRef!$D$2:$D154, PriceRef!$A$2:$A154, "Suede", PriceRef!$C$2:$C154, $E5 ), SUMIFS( PriceRef!$D$2:$D154, PriceRef!$A$2:$A154, "TwoTone", PriceRef!$C$2:$C154, $G5 ) ) -> 0 | K5: interior.1 | L5: =textjoin(" ",true,B5,C5,D5,F5,E5,G5) -> 1LT AQ9 HUQ
A6: 1LT Seats | B6: 1LT | C6: AE4 | D6: AE4 | H6: Competition Sport Bucket seats | I6: Performance textile seating surface. Requires N26 Suede wrapped steering wheel $695 | J6: =SUM( SUMIFS( PriceRef!$D$2:$D154, PriceRef!$A$2:$A154, "Seat", PriceRef!$B$2:$B154, $B6, PriceRef!$C$2:$C154, $C6 ), SUMIFS( PriceRef!$D$2:$D154, PriceRef!$A$2:$A154, "Stitching", PriceRef!$C$2:$C154, $F6 ), SUMIFS( PriceRef!$D$2:$D154, PriceRef!$A$2:$A154, "Suede", PriceRef!$C$2:$C154, $E6 ), SUMIFS( PriceRef!$D$2:$D154, PriceRef!$A$2:$A154, "TwoTone", PriceRef!$C$2:$C154, $G6 ) ) -> 0 | K6: interior.1s | L6: =textjoin(" ",true,B6,C6,D6,F6,E6,G6) -> 1LT AE4 AE4
A7: 1LT Seats | B7: 1LT | C7: AQ9 | D7: AQ9 | H7: GT1 Bucket seats | I7: Mulan Leather | J7: =SUM( SUMIFS( PriceRef!$D$2:$D154, PriceRef!$A$2:$A154, "Seat", PriceRef!$B$2:$B154, $B7, PriceRef!$C$2:$C154, $C7 ), SUMIFS( PriceRef!$D$2:$D154, PriceRef!$A$2:$A154, "Stitching", PriceRef!$C$2:$C154, $F7 ), SUMIFS( PriceRef!$D$2:$D154, PriceRef!$A$2:$A154, "Suede", PriceRef!$C$2:$C154, $E7 ), SUMIFS( PriceRef!$D$2:$D154, PriceRef!$A$2:$A154, "TwoTone", PriceRef!$C$2:$C154, $G7 ) ) -> 0 | K7: interior.1s | L7: =textjoin(" ",true,B7,C7,D7,F7,E7,G7) -> 1LT AQ9 AQ9
A8: 2LT Colors | B8: 2LT | C8: AQ9 | D8: H1Y | H8: Jet Black Mulan | I8: AQ9 GT1 Seats. Interior color is on seats, doors, and console trim. Jet Black has silver stitching. | J8: =SUM( SUMIFS( PriceRef!$D$2:$D154, PriceRef!$A$2:$A154, "Seat", PriceRef!$B$2:$B154, $B8, PriceRef!$C$2:$C154, $C8 ), SUMIFS( PriceRef!$D$2:$D154, PriceRef!$A$2:$A154, "Stitching", PriceRef!$C$2:$C154, $F8 ), SUMIFS( PriceRef!$D$2:$D154, PriceRef!$A$2:$A154, "Suede", PriceRef!$C$2:$C154, $E8 ), SUMIFS( PriceRef!$D$2:$D154, PriceRef!$A$2:$A154, "TwoTone", PriceRef!$C$2:$C154, $G8 ) ) -> 0 | K8: interior.2 | L8: =textjoin(" ",true,B8,C8,D8,F8,E8,G8) -> 2LT AQ9 H1Y
A9: 2LT Colors | B9: 2LT | C9: AQ9 | D9: H1Y | F9: 38S | H9: Jet Black Mulan with Red Stitching | I9: AQ9 GT1 Seats. Interior color is on seats, doors, and console trim. | J9: =SUM( SUMIFS( PriceRef!$D$2:$D154, PriceRef!$A$2:$A154, "Seat", PriceRef!$B$2:$B154, $B9, PriceRef!$C$2:$C154, $C9 ), SUMIFS( PriceRef!$D$2:$D154, PriceRef!$A$2:$A154, "Stitching", PriceRef!$C$2:$C154, $F9 ), SUMIFS( PriceRef!$D$2:$D154, PriceRef!$A$2:$A154, "Suede", PriceRef!$C$2:$C154, $E9 ), SUMIFS( PriceRef!$D$2:$D154, PriceRef!$A$2:$A154, "TwoTone", PriceRef!$C$2:$C154, $G9 ) ) -> 495 | K9: interior.2 | L9: =textjoin(" ",true,B9,C9,D9,F9,E9,G9) -> 2LT AQ9 H1Y 38S
A10: 2LT Colors | B10: 2LT | C10: AQ9 | D10: H1Y | F10: 36S | H10: Jet Black Mulan with Yellow Stitching | I10: AQ9 GT1 Seats. Interior color is on seats, doors, and console trim. | J10: =SUM( SUMIFS( PriceRef!$D$2:$D154, PriceRef!$A$2:$A154, "Seat", PriceRef!$B$2:$B154, $B10, PriceRef!$C$2:$C154, $C10 ), SUMIFS( PriceRef!$D$2:$D154, PriceRef!$A$2:$A154, "Stitching", PriceRef!$C$2:$C154, $F10 ), SUMIFS( PriceRef!$D$2:$D154, PriceRef!$A$2:$A154, "Suede", PriceRef!$C$2:$C154, $E10 ), SUMIFS( PriceRef!$D$2:$D154, PriceRef!$A$2:$A154, "TwoTone", PriceRef!$C$2:$C154, $G10 ) ) -> 495 | K10: interior.2 | L10: =textjoin(" ",true,B10,C10,D10,F10,E10,G10) -> 2LT AQ9 H1Y 36S
A11: 2LT Colors | B11: 2LT | C11: AQ9 | D11: H1Y | F11: 37S | H11: Jet Black Mulan with Blue Stitching | I11: AQ9 GT1 Seats. Interior color is on seats, doors, and console trim. | J11: =SUM( SUMIFS( PriceRef!$D$2:$D154, PriceRef!$A$2:$A154, "Seat", PriceRef!$B$2:$B154, $B11, PriceRef!$C$2:$C154, $C11 ), SUMIFS( PriceRef!$D$2:$D154, PriceRef!$A$2:$A154, "Stitching", PriceRef!$C$2:$C154, $F11 ), SUMIFS( PriceRef!$D$2:$D154, PriceRef!$A$2:$A154, "Suede", PriceRef!$C$2:$C154, $E11 ), SUMIFS( PriceRef!$D$2:$D154, PriceRef!$A$2:$A154, "TwoTone", PriceRef!$C$2:$C154, $G11 ) ) -> 495 | K11: interior.2 | L11: =textjoin(" ",true,B11,C11,D11,F11,E11,G11) -> 2LT AQ9 H1Y 37S
A12: 2LT Colors | B12: 2LT | C12: AH2 | D12: HTM | H12: Jet Black Napa | I12: AH2 GT2 seats. Interior color is on seats, doors, and console trim. Jet Black has silver stitching. | J12: =SUM( SUMIFS( PriceRef!$D$2:$D154, PriceRef!$A$2:$A154, "Seat", PriceRef!$B$2:$B154, $B12, PriceRef!$C$2:$C154, $C12 ), SUMIFS( PriceRef!$D$2:$D154, PriceRef!$A$2:$A154, "Stitching", PriceRef!$C$2:$C154, $F12 ), SUMIFS( PriceRef!$D$2:$D154, PriceRef!$A$2:$A154, "Suede", PriceRef!$C$2:$C154, $E12 ), SUMIFS( PriceRef!$D$2:$D154, PriceRef!$A$2:$A154, "TwoTone", PriceRef!$C$2:$C154, $G12 ) ) -> 1695 | K12: interior.2 | L12: =textjoin(" ",true,B12,C12,D12,F12,E12,G12) -> 2LT AH2 HTM
A13: 2LT Colors | B13: 2LT | C13: AH2 | D13: HTM | F13: 38S | H13: Jet Black Napa with Red Stitching | I13: AH2 GT2 seats. Interior color is on seats, doors, and console trim. | J13: =SUM( SUMIFS( PriceRef!$D$2:$D154, PriceRef!$A$2:$A154, "Seat", PriceRef!$B$2:$B154, $B13, PriceRef!$C$2:$C154, $C13 ), SUMIFS( PriceRef!$D$2:$D154, PriceRef!$A$2:$A154, "Stitching", PriceRef!$C$2:$C154, $F13 ), SUMIFS( PriceRef!$D$2:$D154, PriceRef!$A$2:$A154, "Suede", PriceRef!$C$2:$C154, $E13 ), SUMIFS( PriceRef!$D$2:$D154, PriceRef!$A$2:$A154, "TwoTone", PriceRef!$C$2:$C154, $G13 ) ) -> 2190 | K13: interior.2 | L13: =textjoin(" ",true,B13,C13,D13,F13,E13,G13) -> 2LT AH2 HTM 38S
A14: 2LT Colors | B14: 2LT | C14: AH2 | D14: HTM | F14: 36S | H14: Jet Black Napa with Yellow Stitching | I14: AH2 GT2 seats. Interior color is on seats, doors, and console trim. | J14: =SUM( SUMIFS( PriceRef!$D$2:$D154, PriceRef!$A$2:$A154, "Seat", PriceRef!$B$2:$B154, $B14, PriceRef!$C$2:$C154, $C14 ), SUMIFS( PriceRef!$D$2:$D154, PriceRef!$A$2:$A154, "Stitching", PriceRef!$C$2:$C154, $F14 ), SUMIFS( PriceRef!$D$2:$D154, PriceRef!$A$2:$A154, "Suede", PriceRef!$C$2:$C154, $E14 ), SUMIFS( PriceRef!$D$2:$D154, PriceRef!$A$2:$A154, "TwoTone", PriceRef!$C$2:$C154, $G14 ) ) -> 2190 | K14: interior.2 | L14: =textjoin(" ",true,B14,C14,D14,F14,E14,G14) -> 2LT AH2 HTM 36S
A15: 2LT Colors | B15: 2LT | C15: AH2 | D15: HTM | F15: 37S | H15: Jet Black Napa with Blue Stitching | I15: AH2 GT2 seats. Interior color is on seats, doors, and console trim. | J15: =SUM( SUMIFS( PriceRef!$D$2:$D154, PriceRef!$A$2:$A154, "Seat", PriceRef!$B$2:$B154, $B15, PriceRef!$C$2:$C154, $C15 ), SUMIFS( PriceRef!$D$2:$D154, PriceRef!$A$2:$A154, "Stitching", PriceRef!$C$2:$C154, $F15 ), SUMIFS( PriceRef!$D$2:$D154, PriceRef!$A$2:$A154, "Suede", PriceRef!$C$2:$C154, $E15 ), SUMIFS( PriceRef!$D$2:$D154, PriceRef!$A$2:$A154, "TwoTone", PriceRef!$C$2:$C154, $G15 ) ) -> 2190 | K15: interior.2 | L15: =textjoin(" ",true,B15,C15,D15,F15,E15,G15) -> 2LT AH2 HTM 37S
A16: 2LT Colors | B16: 2LT | C16: AE4 | D16: HTM | H16: Jet Black Napa | I16: AE4 Comp Seats. Interior color is on seats, doors, and console trim. Jet Black has silver stitching. | J16: =SUM( SUMIFS( PriceRef!$D$2:$D154, PriceRef!$A$2:$A154, "Seat", PriceRef!$B$2:$B154, $B16, PriceRef!$C$2:$C154, $C16 ), SUMIFS( PriceRef!$D$2:$D154, PriceRef!$A$2:$A154, "Stitching", PriceRef!$C$2:$C154, $F16 ), SUMIFS( PriceRef!$D$2:$D154, PriceRef!$A$2:$A154, "Suede", PriceRef!$C$2:$C154, $E16 ), SUMIFS( PriceRef!$D$2:$D154, PriceRef!$A$2:$A154, "TwoTone", PriceRef!$C$2:$C154, $G16 ) ) -> 1995 | K16: interior.2 | L16: =textjoin(" ",true,B16,C16,D16,F16,E16,G16) -> 2LT AE4 HTM
A17: 2LT Colors | B17: 2LT | C17: AE4 | D17: HTM | F17: 38S | H17: Jet Black Napa with Red Stitching | I17: AE4 Comp Seats. Interior color is on seats, doors, and console trim. | J17: =SUM( SUMIFS( PriceRef!$D$2:$D154, PriceRef!$A$2:$A154, "Seat", PriceRef!$B$2:$B154, $B17, PriceRef!$C$2:$C154, $C17 ), SUMIFS( PriceRef!$D$2:$D154, PriceRef!$A$2:$A154, "Stitching", PriceRef!$C$2:$C154, $F17 ), SUMIFS( PriceRef!$D$2:$D154, PriceRef!$A$2:$A154, "Suede", PriceRef!$C$2:$C154, $E17 ), SUMIFS( PriceRef!$D$2:$D154, PriceRef!$A$2:$A154, "TwoTone", PriceRef!$C$2:$C154, $G17 ) ) -> 2490 | K17: interior.2 | L17: =textjoin(" ",true,B17,C17,D17,F17,E17,G17) -> 2LT AE4 HTM 38S
A18: 2LT Colors | B18: 2LT | C18: AE4 | D18: HTM | F18: 36S | H18: Jet Black Napa with Yellow Stitching | I18: AE4 Comp Seats. Interior color is on seats, doors, and console trim. | J18: =SUM( SUMIFS( PriceRef!$D$2:$D154, PriceRef!$A$2:$A154, "Seat", PriceRef!$B$2:$B154, $B18, PriceRef!$C$2:$C154, $C18 ), SUMIFS( PriceRef!$D$2:$D154, PriceRef!$A$2:$A154, "Stitching", PriceRef!$C$2:$C154, $F18 ), SUMIFS( PriceRef!$D$2:$D154, PriceRef!$A$2:$A154, "Suede", PriceRef!$C$2:$C154, $E18 ), SUMIFS( PriceRef!$D$2:$D154, PriceRef!$A$2:$A154, "TwoTone", PriceRef!$C$2:$C154, $G18 ) ) -> 2490 | K18: interior.2 | L18: =textjoin(" ",true,B18,C18,D18,F18,E18,G18) -> 2LT AE4 HTM 36S
A19: 2LT Colors | B19: 2LT | C19: AE4 | D19: HTM | F19: 37S | H19: Jet Black Napa with Blue Stitching | I19: AE4 Comp Seats. Interior color is on seats, doors, and console trim. | J19: =SUM( SUMIFS( PriceRef!$D$2:$D154, PriceRef!$A$2:$A154, "Seat", PriceRef!$B$2:$B154, $B19, PriceRef!$C$2:$C154, $C19 ), SUMIFS( PriceRef!$D$2:$D154, PriceRef!$A$2:$A154, "Stitching", PriceRef!$C$2:$C154, $F19 ), SUMIFS( PriceRef!$D$2:$D154, PriceRef!$A$2:$A154, "Suede", PriceRef!$C$2:$C154, $E19 ), SUMIFS( PriceRef!$D$2:$D154, PriceRef!$A$2:$A154, "TwoTone", PriceRef!$C$2:$C154, $G19 ) ) -> 2490 | K19: interior.2 | L19: =textjoin(" ",true,B19,C19,D19,F19,E19,G19) -> 2LT AE4 HTM 37S
A20: 2LT Colors | B20: 2LT | C20: AH2 | D20: HTN | H20: Natural Napa | I20: AH2 GT2 Seats. Interior color is on seats, doors, and console trim. TU7 Two tone seats available with GT2 seats | J20: =SUM( SUMIFS( PriceRef!$D$2:$D154, PriceRef!$A$2:$A154, "Seat", PriceRef!$B$2:$B154, $B20, PriceRef!$C$2:$C154, $C20 ), SUMIFS( PriceRef!$D$2:$D154, PriceRef!$A$2:$A154, "Stitching", PriceRef!$C$2:$C154, $F20 ), SUMIFS( PriceRef!$D$2:$D154, PriceRef!$A$2:$A154, "Suede", PriceRef!$C$2:$C154, $E20 ), SUMIFS( PriceRef!$D$2:$D154, PriceRef!$A$2:$A154, "TwoTone", PriceRef!$C$2:$C154, $G20 ) ) -> 1695 | K20: interior.2 | L20: =textjoin(" ",true,B20,C20,D20,F20,E20,G20) -> 2LT AH2 HTN
A21: 2LT Colors | B21: 2LT | C21: AE4 | D21: HTN | H21: Natural Napa | I21: AE4 Comp Seats. Interior color is on seats, doors, and console trim. | J21: =SUM( SUMIFS( PriceRef!$D$2:$D154, PriceRef!$A$2:$A154, "Seat", PriceRef!$B$2:$B154, $B21, PriceRef!$C$2:$C154, $C21 ), SUMIFS( PriceRef!$D$2:$D154, PriceRef!$A$2:$A154, "Stitching", PriceRef!$C$2:$C154, $F21 ), SUMIFS( PriceRef!$D$2:$D154, PriceRef!$A$2:$A154, "Suede", PriceRef!$C$2:$C154, $E21 ), SUMIFS( PriceRef!$D$2:$D154, PriceRef!$A$2:$A154, "TwoTone", PriceRef!$C$2:$C154, $G21 ) ) -> 1995 | K21: interior.2 | L21: =textjoin(" ",true,B21,C21,D21,F21,E21,G21) -> 2LT AE4 HTN
A22: 2LT Colors | B22: 2LT | C22: AH2 | D22: HTN | G22: TU7 | H22: Natural Napa with two tone seats | I22: AH2 GT2 Seats. Interior color is on seats, doors, and console trim. TU7 Two tone adds black seat inserts and headrest. | J22: =SUM( SUMIFS( PriceRef!$D$2:$D154, PriceRef!$A$2:$A154, "Seat", PriceRef!$B$2:$B154, $B22, PriceRef!$C$2:$C154, $C22 ), SUMIFS( PriceRef!$D$2:$D154, PriceRef!$A$2:$A154, "Stitching", PriceRef!$C$2:$C154, $F22 ), SUMIFS( PriceRef!$D$2:$D154, PriceRef!$A$2:$A154, "Suede", PriceRef!$C$2:$C154, $E22 ), SUMIFS( PriceRef!$D$2:$D154, PriceRef!$A$2:$A154, "TwoTone", PriceRef!$C$2:$C154, $G22 ) ) -> 2290 | K22: interior.2 | L22: =textjoin(" ",true,B22,C22,D22,F22,E22,G22) -> 2LT AH2 HTN TU7
A23: 2LT Colors | B23: 2LT | C23: AH2 | D23: HTP | E23: N26 | H23: Jet Black Napa with sueded microfiber inserts | I23: AH2 GT2 Seats. Includes Suede Steering Wheel. Interior color is on seats, doors, and console trim. Jet Black has silver stitching. | J23: =SUM( SUMIFS( PriceRef!$D$2:$D154, PriceRef!$A$2:$A154, "Seat", PriceRef!$B$2:$B154, $B23, PriceRef!$C$2:$C154, $C23 ), SUMIFS( PriceRef!$D$2:$D154, PriceRef!$A$2:$A154, "Stitching", PriceRef!$C$2:$C154, $F23 ), SUMIFS( PriceRef!$D$2:$D154, PriceRef!$A$2:$A154, "Suede", PriceRef!$C$2:$C154, $E23 ), SUMIFS( PriceRef!$D$2:$D154, PriceRef!$A$2:$A154, "TwoTone", PriceRef!$C$2:$C154, $G23 ) ) -> 2390 | K23: interior.2 | L23: =textjoin(" ",true,B23,C23,D23,F23,E23,G23) -> 2LT AH2 HTP N26
A24: 2LT Colors | B24: 2LT | C24: AH2 | D24: HTP | E24: N26 | F24: 38S | H24: Jet Black Napa with sueded microfiber inserts and Red Stitching | I24: AH2 GT2 Seats. Includes Suede Steering Wheel. Interior color is on seats, doors, and console trim. Jet Black has silver stitching. | J24: =SUM( SUMIFS( PriceRef!$D$2:$D154, PriceRef!$A$2:$A154, "Seat", PriceRef!$B$2:$B154, $B24, PriceRef!$C$2:$C154, $C24 ), SUMIFS( PriceRef!$D$2:$D154, PriceRef!$A$2:$A154, "Stitching", PriceRef!$C$2:$C154, $F24 ), SUMIFS( PriceRef!$D$2:$D154, PriceRef!$A$2:$A154, "Suede", PriceRef!$C$2:$C154, $E24 ), SUMIFS( PriceRef!$D$2:$D154, PriceRef!$A$2:$A154, "TwoTone", PriceRef!$C$2:$C154, $G24 ) ) -> 2885 | K24: interior.2 | L24: =textjoin(" ",true,B24,C24,D24,F24,E24,G24) -> 2LT AH2 HTP 38S N26
A25: 2LT Colors | B25: 2LT | C25: AH2 | D25: HTP | E25: N26 | F25: 36S | H25: Jet Black Napa with sueded microfiber inserts and Yellow Stitching | I25: AH2 GT2 Seats. Includes Suede Steering Wheel. Interior color is on seats, doors, and console trim. Jet Black has silver stitching. | J25: =SUM( SUMIFS( PriceRef!$D$2:$D154, PriceRef!$A$2:$A154, "Seat", PriceRef!$B$2:$B154, $B25, PriceRef!$C$2:$C154, $C25 ), SUMIFS( PriceRef!$D$2:$D154, PriceRef!$A$2:$A154, "Stitching", PriceRef!$C$2:$C154, $F25 ), SUMIFS( PriceRef!$D$2:$D154, PriceRef!$A$2:$A154, "Suede", PriceRef!$C$2:$C154, $E25 ), SUMIFS( PriceRef!$D$2:$D154, PriceRef!$A$2:$A154, "TwoTone", PriceRef!$C$2:$C154, $G25 ) ) -> 2885 | K25: interior.2 | L25: =textjoin(" ",true,B25,C25,D25,F25,E25,G25) -> 2LT AH2 HTP 36S N26
A26: 2LT Colors | B26: 2LT | C26: AH2 | D26: HTP | E26: N26 | F26: 37S | H26: Jet Black Napa with sueded microfiber inserts and Blue Stitching | I26: AH2 GT2 Seats. Includes Suede Steering Wheel. Interior color is on seats, doors, and console trim. Jet Black has silver stitching. | J26: =SUM( SUMIFS( PriceRef!$D$2:$D154, PriceRef!$A$2:$A154, "Seat", PriceRef!$B$2:$B154, $B26, PriceRef!$C$2:$C154, $C26 ), SUMIFS( PriceRef!$D$2:$D154, PriceRef!$A$2:$A154, "Stitching", PriceRef!$C$2:$C154, $F26 ), SUMIFS( PriceRef!$D$2:$D154, PriceRef!$A$2:$A154, "Suede", PriceRef!$C$2:$C154, $E26 ), SUMIFS( PriceRef!$D$2:$D154, PriceRef!$A$2:$A154, "TwoTone", PriceRef!$C$2:$C154, $G26 ) ) -> 2885 | K26: interior.2 | L26: =textjoin(" ",true,B26,C26,D26,F26,E26,G26) -> 2LT AH2 HTP 37S N26
A27: 2LT Colors | B27: 2LT | C27: AE4 | D27: HTP | E27: N26 | H27: Jet Black Napa with sueded microfiber inserts | I27: AE4 Comp Seats. Includes Suede Steering Wheel. Interior color is on seats, doors, and console trim. Jet Black has silver stitching. | J27: =SUM( SUMIFS( PriceRef!$D$2:$D154, PriceRef!$A$2:$A154, "Seat", PriceRef!$B$2:$B154, $B27, PriceRef!$C$2:$C154, $C27 ), SUMIFS( PriceRef!$D$2:$D154, PriceRef!$A$2:$A154, "Stitching", PriceRef!$C$2:$C154, $F27 ), SUMIFS( PriceRef!$D$2:$D154, PriceRef!$A$2:$A154, "Suede", PriceRef!$C$2:$C154, $E27 ), SUMIFS( PriceRef!$D$2:$D154, PriceRef!$A$2:$A154, "TwoTone", PriceRef!$C$2:$C154, $G27 ) ) -> 2690 | K27: interior.2 | L27: =textjoin(" ",true,B27,C27,D27,F27,E27,G27) -> 2LT AE4 HTP N26
A28: 2LT Colors | B28: 2LT | C28: AE4 | D28: HTP | E28: N26 | F28: 38S | H28: Jet Black Napa with sueded microfiber inserts and Red Stitching | I28: AE4 Comp Seats. Includes Suede Steering Wheel. Interior color is on seats, doors, and console trim. Jet Black has silver stitching. | J28: =SUM( SUMIFS( PriceRef!$D$2:$D154, PriceRef!$A$2:$A154, "Seat", PriceRef!$B$2:$B154, $B28, PriceRef!$C$2:$C154, $C28 ), SUMIFS( PriceRef!$D$2:$D154, PriceRef!$A$2:$A154, "Stitching", PriceRef!$C$2:$C154, $F28 ), SUMIFS( PriceRef!$D$2:$D154, PriceRef!$A$2:$A154, "Suede", PriceRef!$C$2:$C154, $E28 ), SUMIFS( PriceRef!$D$2:$D154, PriceRef!$A$2:$A154, "TwoTone", PriceRef!$C$2:$C154, $G28 ) ) -> 3185 | K28: interior.2 | L28: =textjoin(" ",true,B28,C28,D28,F28,E28,G28) -> 2LT AE4 HTP 38S N26
A29: 2LT Colors | B29: 2LT | C29: AE4 | D29: HTP | E29: N26 | F29: 36S | H29: Jet Black Napa with sueded microfiber inserts and Yellow Stitching | I29: AE4 Comp Seats. Includes Suede Steering Wheel. Interior color is on seats, doors, and console trim. Jet Black has silver stitching. | J29: =SUM( SUMIFS( PriceRef!$D$2:$D154, PriceRef!$A$2:$A154, "Seat", PriceRef!$B$2:$B154, $B29, PriceRef!$C$2:$C154, $C29 ), SUMIFS( PriceRef!$D$2:$D154, PriceRef!$A$2:$A154, "Stitching", PriceRef!$C$2:$C154, $F29 ), SUMIFS( PriceRef!$D$2:$D154, PriceRef!$A$2:$A154, "Suede", PriceRef!$C$2:$C154, $E29 ), SUMIFS( PriceRef!$D$2:$D154, PriceRef!$A$2:$A154, "TwoTone", PriceRef!$C$2:$C154, $G29 ) ) -> 3185 | K29: interior.2 | L29: =textjoin(" ",true,B29,C29,D29,F29,E29,G29) -> 2LT AE4 HTP 36S N26
A30: 2LT Colors | B30: 2LT | C30: AE4 | D30: HTP | E30: N26 | F30: 37S | H30: Jet Black Napa with sueded microfiber inserts and Blue Stitching | I30: AE4 Comp Seats. Includes Suede Steering Wheel. Interior color is on seats, doors, and console trim. Jet Black has silver stitching. | J30: =SUM( SUMIFS( PriceRef!$D$2:$D154, PriceRef!$A$2:$A154, "Seat", PriceRef!$B$2:$B154, $B30, PriceRef!$C$2:$C154, $C30 ), SUMIFS( PriceRef!$D$2:$D154, PriceRef!$A$2:$A154, "Stitching", PriceRef!$C$2:$C154, $F30 ), SUMIFS( PriceRef!$D$2:$D154, PriceRef!$A$2:$A154, "Suede", PriceRef!$C$2:$C154, $E30 ), SUMIFS( PriceRef!$D$2:$D154, PriceRef!$A$2:$A154, "TwoTone", PriceRef!$C$2:$C154, $G30 ) ) -> 3185 | K30: interior.2 | L30: =textjoin(" ",true,B30,C30,D30,F30,E30,G30) -> 2LT AE4 HTP 37S N26
A31: 2LT Colors | B31: 2LT | C31: AH2 | D31: HTQ | E31: N26 | H31: Natural Napa with sueded microfiber inserts | I31: AH2 GT2 seats. Includes Suede Steering Wheel. Interior color is on seats, doors, and console trim. TU7 Two tone seats available with GT2 seats | J31: =SUM( SUMIFS( PriceRef!$D$2:$D154, PriceRef!$A$2:$A154, "Seat", PriceRef!$B$2:$B154, $B31, PriceRef!$C$2:$C154, $C31 ), SUMIFS( PriceRef!$D$2:$D154, PriceRef!$A$2:$A154, "Stitching", PriceRef!$C$2:$C154, $F31 ), SUMIFS( PriceRef!$D$2:$D154, PriceRef!$A$2:$A154, "Suede", PriceRef!$C$2:$C154, $E31 ), SUMIFS( PriceRef!$D$2:$D154, PriceRef!$A$2:$A154, "TwoTone", PriceRef!$C$2:$C154, $G31 ) ) -> 2390 | K31: interior.2 | L31: =textjoin(" ",true,B31,C31,D31,F31,E31,G31) -> 2LT AH2 HTQ N26
A32: 2LT Colors | B32: 2LT | C32: AE4 | D32: HTQ | E32: N26 | H32: Natural Napa with sueded microfiber inserts | I32: AE4 Comp Seats only. Includes Suede Steering Wheel. Interior color is on seats, doors, and console trim. | J32: =SUM( SUMIFS( PriceRef!$D$2:$D154, PriceRef!$A$2:$A154, "Seat", PriceRef!$B$2:$B154, $B32, PriceRef!$C$2:$C154, $C32 ), SUMIFS( PriceRef!$D$2:$D154, PriceRef!$A$2:$A154, "Stitching", PriceRef!$C$2:$C154, $F32 ), SUMIFS( PriceRef!$D$2:$D154, PriceRef!$A$2:$A154, "Suede", PriceRef!$C$2:$C154, $E32 ), SUMIFS( PriceRef!$D$2:$D154, PriceRef!$A$2:$A154, "TwoTone", PriceRef!$C$2:$C154, $G32 ) ) -> 2690 | K32: interior.2 | L32: =textjoin(" ",true,B32,C32,D32,F32,E32,G32) -> 2LT AE4 HTQ N26
A33: 2LT Colors | B33: 2LT | C33: AH2 | D33: HTQ | E33: N26 | G33: TU7 | H33: Natural Napa with sueded microfiber inserts and two tone seats | I33: AH2 GT2 seats. Includes Suede Steering Wheel. Interior color is on seats, doors, and console trim. TU7 Two tone adds black seat inserts and headrest. | J33: =SUM( SUMIFS( PriceRef!$D$2:$D154, PriceRef!$A$2:$A154, "Seat", PriceRef!$B$2:$B154, $B33, PriceRef!$C$2:$C154, $C33 ), SUMIFS( PriceRef!$D$2:$D154, PriceRef!$A$2:$A154, "Stitching", PriceRef!$C$2:$C154, $F33 ), SUMIFS( PriceRef!$D$2:$D154, PriceRef!$A$2:$A154, "Suede", PriceRef!$C$2:$C154, $E33 ), SUMIFS( PriceRef!$D$2:$D154, PriceRef!$A$2:$A154, "TwoTone", PriceRef!$C$2:$C154, $G33 ) ) -> 2985 | K33: interior.2 | L33: =textjoin(" ",true,B33,C33,D33,F33,E33,G33) -> 2LT AH2 HTQ N26 TU7
A34: 2LT Colors | B34: 2LT | C34: AH2 | D34: HU6 | E34: N26 | H34: Sky Cool Gray Napa with sueded microfiber inserts | I34: AH2 GT2 Seats. Includes Suede Steering Wheel. Interior color is on seats, doors, and console trim. TU7 Two tone seats available with GT2 seats | J34: =SUM( SUMIFS( PriceRef!$D$2:$D154, PriceRef!$A$2:$A154, "Seat", PriceRef!$B$2:$B154, $B34, PriceRef!$C$2:$C154, $C34 ), SUMIFS( PriceRef!$D$2:$D154, PriceRef!$A$2:$A154, "Stitching", PriceRef!$C$2:$C154, $F34 ), SUMIFS( PriceRef!$D$2:$D154, PriceRef!$A$2:$A154, "Suede", PriceRef!$C$2:$C154, $E34 ), SUMIFS( PriceRef!$D$2:$D154, PriceRef!$A$2:$A154, "TwoTone", PriceRef!$C$2:$C154, $G34 ) ) -> 2390 | K34: interior.2 | L34: =textjoin(" ",true,B34,C34,D34,F34,E34,G34) -> 2LT AH2 HU6 N26
A35: 2LT Colors | B35: 2LT | C35: AE4 | D35: HU6 | E35: N26 | H35: Sky Cool Gray Napa with sueded microfiber inserts | I35: AE4 Comp Seats are black. Includes Suede Steering Wheel. Interior color is on seats, doors, and console trim. | J35: =SUM( SUMIFS( PriceRef!$D$2:$D154, PriceRef!$A$2:$A154, "Seat", PriceRef!$B$2:$B154, $B35, PriceRef!$C$2:$C154, $C35 ), SUMIFS( PriceRef!$D$2:$D154, PriceRef!$A$2:$A154, "Stitching", PriceRef!$C$2:$C154, $F35 ), SUMIFS( PriceRef!$D$2:$D154, PriceRef!$A$2:$A154, "Suede", PriceRef!$C$2:$C154, $E35 ), SUMIFS( PriceRef!$D$2:$D154, PriceRef!$A$2:$A154, "TwoTone", PriceRef!$C$2:$C154, $G35 ) ) -> 2690 | K35: interior.2 | L35: =textjoin(" ",true,B35,C35,D35,F35,E35,G35) -> 2LT AE4 HU6 N26
A36: 2LT Colors | B36: 2LT | C36: AH2 | D36: HU6 | E36: N26 | G36: TU7 | H36: Sky Cool Gray Napa with sueded microfiber inserts and two tone seats | I36: AH2 GT2 Seats. Includes Suede Steering Wheel. Interior color is on seats, doors, and console trim. TU7 Two tone adds black seat inserts and headrest. | J36: =SUM( SUMIFS( PriceRef!$D$2:$D154, PriceRef!$A$2:$A154, "Seat", PriceRef!$B$2:$B154, $B36, PriceRef!$C$2:$C154, $C36 ), SUMIFS( PriceRef!$D$2:$D154, PriceRef!$A$2:$A154, "Stitching", PriceRef!$C$2:$C154, $F36 ), SUMIFS( PriceRef!$D$2:$D154, PriceRef!$A$2:$A154, "Suede", PriceRef!$C$2:$C154, $E36 ), SUMIFS( PriceRef!$D$2:$D154, PriceRef!$A$2:$A154, "TwoTone", PriceRef!$C$2:$C154, $G36 ) ) -> 2985 | K36: interior.2 | L36: =textjoin(" ",true,B36,C36,D36,F36,E36,G36) -> 2LT AH2 HU6 N26 TU7
A37: 2LT Colors | B37: 2LT | C37: AE4 | D37: HU7 | E37: N26 | H37: Adrenaline Red Napa with (black) sueded microfiber inserts | I37: AE4 Comp Seats , Includes Suede Steering Wheel. Interior color is on seats, doors, and console trim. | J37: =SUM( SUMIFS( PriceRef!$D$2:$D154, PriceRef!$A$2:$A154, "Seat", PriceRef!$B$2:$B154, $B37, PriceRef!$C$2:$C154, $C37 ), SUMIFS( PriceRef!$D$2:$D154, PriceRef!$A$2:$A154, "Stitching", PriceRef!$C$2:$C154, $F37 ), SUMIFS( PriceRef!$D$2:$D154, PriceRef!$A$2:$A154, "Suede", PriceRef!$C$2:$C154, $E37 ), SUMIFS( PriceRef!$D$2:$D154, PriceRef!$A$2:$A154, "TwoTone", PriceRef!$C$2:$C154, $G37 ) ) -> 2690 | K37: interior.2 | L37: =textjoin(" ",true,B37,C37,D37,F37,E37,G37) -> 2LT AE4 HU7 N26
A38: 2LT Colors | B38: 2LT | C38: AH2 | D38: HU7 | E38: N26 | G38: TU7 | H38: Adrenaline Red Napa with (black) sueded microfiber inserts and two tone seats | I38: AH2 GT2 Seats , Includes Suede Steering Wheel. Interior color is on seats, doors, and console trim. TU7 Two tone seats required | J38: =SUM( SUMIFS( PriceRef!$D$2:$D154, PriceRef!$A$2:$A154, "Seat", PriceRef!$B$2:$B154, $B38, PriceRef!$C$2:$C154, $C38 ), SUMIFS( PriceRef!$D$2:$D154, PriceRef!$A$2:$A154, "Stitching", PriceRef!$C$2:$C154, $F38 ), SUMIFS( PriceRef!$D$2:$D154, PriceRef!$A$2:$A154, "Suede", PriceRef!$C$2:$C154, $E38 ), SUMIFS( PriceRef!$D$2:$D154, PriceRef!$A$2:$A154, "TwoTone", PriceRef!$C$2:$C154, $G38 ) ) -> 2985 | K38: interior.2 | L38: =textjoin(" ",true,B38,C38,D38,F38,E38,G38) -> 2LT AH2 HU7 N26 TU7
A39: 2LT Colors | B39: 2LT | C39: AH2 | D39: HUK | H39: Sky Cool Gray Napa | I39: AH2 GT2 Seats. Interior color is on seats, doors, and console trim. TU7 Two tone seats available with GT2 seats | J39: =SUM( SUMIFS( PriceRef!$D$2:$D154, PriceRef!$A$2:$A154, "Seat", PriceRef!$B$2:$B154, $B39, PriceRef!$C$2:$C154, $C39 ), SUMIFS( PriceRef!$D$2:$D154, PriceRef!$A$2:$A154, "Stitching", PriceRef!$C$2:$C154, $F39 ), SUMIFS( PriceRef!$D$2:$D154, PriceRef!$A$2:$A154, "Suede", PriceRef!$C$2:$C154, $E39 ), SUMIFS( PriceRef!$D$2:$D154, PriceRef!$A$2:$A154, "TwoTone", PriceRef!$C$2:$C154, $G39 ) ) -> 1695 | K39: interior.2 | L39: =textjoin(" ",true,B39,C39,D39,F39,E39,G39) -> 2LT AH2 HUK
A40: 2LT Colors | B40: 2LT | C40: AE4 | D40: HUK | H40: Sky Cool Gray Napa | I40: AE4 Comp Seats are black. Interior color is on seats, doors, and console trim. | J40: =SUM( SUMIFS( PriceRef!$D$2:$D154, PriceRef!$A$2:$A154, "Seat", PriceRef!$B$2:$B154, $B40, PriceRef!$C$2:$C154, $C40 ), SUMIFS( PriceRef!$D$2:$D154, PriceRef!$A$2:$A154, "Stitching", PriceRef!$C$2:$C154, $F40 ), SUMIFS( PriceRef!$D$2:$D154, PriceRef!$A$2:$A154, "Suede", PriceRef!$C$2:$C154, $E40 ), SUMIFS( PriceRef!$D$2:$D154, PriceRef!$A$2:$A154, "TwoTone", PriceRef!$C$2:$C154, $G40 ) ) -> 1995 | K40: interior.2 | L40: =textjoin(" ",true,B40,C40,D40,F40,E40,G40) -> 2LT AE4 HUK
A41: 2LT Colors | B41: 2LT | C41: AH2 | D41: HUK | G41: TU7 | H41: Sky Cool Gray Napa with two tone seats | I41: AH2 GT2 Seats. Interior color is on seats, doors, and console trim. Two tone adds black seat inserts and headrest. | J41: =SUM( SUMIFS( PriceRef!$D$2:$D154, PriceRef!$A$2:$A154, "Seat", PriceRef!$B$2:$B154, $B41, PriceRef!$C$2:$C154, $C41 ), SUMIFS( PriceRef!$D$2:$D154, PriceRef!$A$2:$A154, "Stitching", PriceRef!$C$2:$C154, $F41 ), SUMIFS( PriceRef!$D$2:$D154, PriceRef!$A$2:$A154, "Suede", PriceRef!$C$2:$C154, $E41 ), SUMIFS( PriceRef!$D$2:$D154, PriceRef!$A$2:$A154, "TwoTone", PriceRef!$C$2:$C154, $G41 ) ) -> 2290 | K41: interior.2 | L41: =textjoin(" ",true,B41,C41,D41,F41,E41,G41) -> 2LT AH2 HUK TU7
A42: 2LT Colors | B42: 2LT | C42: AH2 | D42: HUL | H42: Adrenaline Red Napa | I42: AH2 GT2 Seats. Interior color is on seats, doors, and console trim. TU7 Two tone seats available with GT2 seats | J42: =SUM( SUMIFS( PriceRef!$D$2:$D154, PriceRef!$A$2:$A154, "Seat", PriceRef!$B$2:$B154, $B42, PriceRef!$C$2:$C154, $C42 ), SUMIFS( PriceRef!$D$2:$D154, PriceRef!$A$2:$A154, "Stitching", PriceRef!$C$2:$C154, $F42 ), SUMIFS( PriceRef!$D$2:$D154, PriceRef!$A$2:$A154, "Suede", PriceRef!$C$2:$C154, $E42 ), SUMIFS( PriceRef!$D$2:$D154, PriceRef!$A$2:$A154, "TwoTone", PriceRef!$C$2:$C154, $G42 ) ) -> 1695 | K42: interior.2 | L42: =textjoin(" ",true,B42,C42,D42,F42,E42,G42) -> 2LT AH2 HUL
A43: 2LT Colors | B43: 2LT | C43: AE4 | D43: HUL | H43: Adrenaline Red Napa | I43: AE4 Comp Seats. Interior color is on seats, doors, and console trim. | J43: =SUM( SUMIFS( PriceRef!$D$2:$D154, PriceRef!$A$2:$A154, "Seat", PriceRef!$B$2:$B154, $B43, PriceRef!$C$2:$C154, $C43 ), SUMIFS( PriceRef!$D$2:$D154, PriceRef!$A$2:$A154, "Stitching", PriceRef!$C$2:$C154, $F43 ), SUMIFS( PriceRef!$D$2:$D154, PriceRef!$A$2:$A154, "Suede", PriceRef!$C$2:$C154, $E43 ), SUMIFS( PriceRef!$D$2:$D154, PriceRef!$A$2:$A154, "TwoTone", PriceRef!$C$2:$C154, $G43 ) ) -> 1995 | K43: interior.2 | L43: =textjoin(" ",true,B43,C43,D43,F43,E43,G43) -> 2LT AE4 HUL
A44: 2LT Colors | B44: 2LT | C44: AH2 | D44: HUL | G44: TU7 | H44: Adrenaline Red Napa with two tone seats | I44: AH2 GT2 Seats. Interior color is on seats, doors, and console trim. TU7 Two tone adds black seat inserts and headrest. | J44: =SUM( SUMIFS( PriceRef!$D$2:$D154, PriceRef!$A$2:$A154, "Seat", PriceRef!$B$2:$B154, $B44, PriceRef!$C$2:$C154, $C44 ), SUMIFS( PriceRef!$D$2:$D154, PriceRef!$A$2:$A154, "Stitching", PriceRef!$C$2:$C154, $F44 ), SUMIFS( PriceRef!$D$2:$D154, PriceRef!$A$2:$A154, "Suede", PriceRef!$C$2:$C154, $E44 ), SUMIFS( PriceRef!$D$2:$D154, PriceRef!$A$2:$A154, "TwoTone", PriceRef!$C$2:$C154, $G44 ) ) -> 2290 | K44: interior.2 | L44: =textjoin(" ",true,B44,C44,D44,F44,E44,G44) -> 2LT AH2 HUL TU7
A45: 2LT Colors | B45: 2LT | C45: AQ9 | D45: HUN | H45: Sky Cool Gray Mulan | I45: AQ9 GT1 Seats. Interior color is on seats, doors, and console trim. | J45: =SUM( SUMIFS( PriceRef!$D$2:$D154, PriceRef!$A$2:$A154, "Seat", PriceRef!$B$2:$B154, $B45, PriceRef!$C$2:$C154, $C45 ), SUMIFS( PriceRef!$D$2:$D154, PriceRef!$A$2:$A154, "Stitching", PriceRef!$C$2:$C154, $F45 ), SUMIFS( PriceRef!$D$2:$D154, PriceRef!$A$2:$A154, "Suede", PriceRef!$C$2:$C154, $E45 ), SUMIFS( PriceRef!$D$2:$D154, PriceRef!$A$2:$A154, "TwoTone", PriceRef!$C$2:$C154, $G45 ) ) -> 0 | K45: interior.2 | L45: =textjoin(" ",true,B45,C45,D45,F45,E45,G45) -> 2LT AQ9 HUN
A46: 2LT Colors | B46: 2LT | C46: AQ9 | D46: HUR | H46: Adrenaline Red Mulan | I46: AQ9 GT1 Seats. Interior color is on seats, doors, and console trim. | J46: =SUM( SUMIFS( PriceRef!$D$2:$D154, PriceRef!$A$2:$A154, "Seat", PriceRef!$B$2:$B154, $B46, PriceRef!$C$2:$C154, $C46 ), SUMIFS( PriceRef!$D$2:$D154, PriceRef!$A$2:$A154, "Stitching", PriceRef!$C$2:$C154, $F46 ), SUMIFS( PriceRef!$D$2:$D154, PriceRef!$A$2:$A154, "Suede", PriceRef!$C$2:$C154, $E46 ), SUMIFS( PriceRef!$D$2:$D154, PriceRef!$A$2:$A154, "TwoTone", PriceRef!$C$2:$C154, $G46 ) ) -> 0 | K46: interior.2 | L46: =textjoin(" ",true,B46,C46,D46,F46,E46,G46) -> 2LT AQ9 HUR
A47: 2LT Colors | B47: 2LT | C47: AQ9 | D47: HUV | H47: Natural Mulan | I47: AQ9 GT1 Seats. Interior color is on seats, doors, and console trim. | J47: =SUM( SUMIFS( PriceRef!$D$2:$D154, PriceRef!$A$2:$A154, "Seat", PriceRef!$B$2:$B154, $B47, PriceRef!$C$2:$C154, $C47 ), SUMIFS( PriceRef!$D$2:$D154, PriceRef!$A$2:$A154, "Stitching", PriceRef!$C$2:$C154, $F47 ), SUMIFS( PriceRef!$D$2:$D154, PriceRef!$A$2:$A154, "Suede", PriceRef!$C$2:$C154, $E47 ), SUMIFS( PriceRef!$D$2:$D154, PriceRef!$A$2:$A154, "TwoTone", PriceRef!$C$2:$C154, $G47 ) ) -> 0 | K47: interior.2 | L47: =textjoin(" ",true,B47,C47,D47,F47,E47,G47) -> 2LT AQ9 HUV
A48: 2LT Seats | B48: 2LT | C48: AE4 | D48: AE4 | H48: Competition Sport Buckets | I48: Napa Leather and Performance Textile | J48: =SUM( SUMIFS( PriceRef!$D$2:$D154, PriceRef!$A$2:$A154, "Seat", PriceRef!$B$2:$B154, $B48, PriceRef!$C$2:$C154, $C48 ), SUMIFS( PriceRef!$D$2:$D154, PriceRef!$A$2:$A154, "Stitching", PriceRef!$C$2:$C154, $F48 ), SUMIFS( PriceRef!$D$2:$D154, PriceRef!$A$2:$A154, "Suede", PriceRef!$C$2:$C154, $E48 ), SUMIFS( PriceRef!$D$2:$D154, PriceRef!$A$2:$A154, "TwoTone", PriceRef!$C$2:$C154, $G48 ) ) -> 1995 | K48: interior.2s | L48: =textjoin(" ",true,B48,C48,D48,F48,E48,G48) -> 2LT AE4 AE4
A49: 2LT Seats | B49: 2LT | C49: AH2 | D49: AH2 | H49: GT2 Bucket seats | I49: Napa Leather | J49: =SUM( SUMIFS( PriceRef!$D$2:$D154, PriceRef!$A$2:$A154, "Seat", PriceRef!$B$2:$B154, $B49, PriceRef!$C$2:$C154, $C49 ), SUMIFS( PriceRef!$D$2:$D154, PriceRef!$A$2:$A154, "Stitching", PriceRef!$C$2:$C154, $F49 ), SUMIFS( PriceRef!$D$2:$D154, PriceRef!$A$2:$A154, "Suede", PriceRef!$C$2:$C154, $E49 ), SUMIFS( PriceRef!$D$2:$D154, PriceRef!$A$2:$A154, "TwoTone", PriceRef!$C$2:$C154, $G49 ) ) -> 1695 | K49: interior.2s | L49: =textjoin(" ",true,B49,C49,D49,F49,E49,G49) -> 2LT AH2 AH2
A50: 2LT Seats | B50: 2LT | C50: AQ9 | D50: AQ9 | H50: GT1 Bucket seats | I50: Mulan Leather | J50: =SUM( SUMIFS( PriceRef!$D$2:$D154, PriceRef!$A$2:$A154, "Seat", PriceRef!$B$2:$B154, $B50, PriceRef!$C$2:$C154, $C50 ), SUMIFS( PriceRef!$D$2:$D154, PriceRef!$A$2:$A154, "Stitching", PriceRef!$C$2:$C154, $F50 ), SUMIFS( PriceRef!$D$2:$D154, PriceRef!$A$2:$A154, "Suede", PriceRef!$C$2:$C154, $E50 ), SUMIFS( PriceRef!$D$2:$D154, PriceRef!$A$2:$A154, "TwoTone", PriceRef!$C$2:$C154, $G50 ) ) -> 0 | K50: interior.2s | L50: =textjoin(" ",true,B50,C50,D50,F50,E50,G50) -> 2LT AQ9 AQ9
A51: 3LT Colors | B51: 3LT | C51: AH2 | D51: HNK | H51: Adrenaline Red Dipped Napa | I51: AH2 GT2 Seats. Includes Torch Red Seatbelt. Dipped interior is full color interior, instrument panel, doors, and carpet. Custom Stitching is on headliner of Coupe only. All Napa. | J51: =SUM( SUMIFS( PriceRef!$D$2:$D154, PriceRef!$A$2:$A154, "Seat", PriceRef!$B$2:$B154, $B51, PriceRef!$C$2:$C154, $C51 ), SUMIFS( PriceRef!$D$2:$D154, PriceRef!$A$2:$A154, "Stitching", PriceRef!$C$2:$C154, $F51 ), SUMIFS( PriceRef!$D$2:$D154, PriceRef!$A$2:$A154, "Suede", PriceRef!$C$2:$C154, $E51 ), SUMIFS( PriceRef!$D$2:$D154, PriceRef!$A$2:$A154, "TwoTone", PriceRef!$C$2:$C154, $G51 ) ) -> 0 | K51: interior.3 | L51: =textjoin(" ",true,B51,C51,D51,F51,E51,G51) -> 3LT AH2 HNK
A52: 3LT Colors | B52: 3LT | C52: AE4 | D52: HNK | H52: Adrenaline Red Dipped Napa | I52: AE4 Comp Seats. Includes Torch Red Seatbelt. Dipped interior is full color interior, instrument panel, doors, and carpet. Custom Stitching is on headliner of Coupe only. All Napa. | J52: =SUM( SUMIFS( PriceRef!$D$2:$D154, PriceRef!$A$2:$A154, "Seat", PriceRef!$B$2:$B154, $B52, PriceRef!$C$2:$C154, $C52 ), SUMIFS( PriceRef!$D$2:$D154, PriceRef!$A$2:$A154, "Stitching", PriceRef!$C$2:$C154, $F52 ), SUMIFS( PriceRef!$D$2:$D154, PriceRef!$A$2:$A154, "Suede", PriceRef!$C$2:$C154, $E52 ), SUMIFS( PriceRef!$D$2:$D154, PriceRef!$A$2:$A154, "TwoTone", PriceRef!$C$2:$C154, $G52 ) ) -> 500 | K52: interior.3 | L52: =textjoin(" ",true,B52,C52,D52,F52,E52,G52) -> 3LT AE4 HNK
A53: 3LT Colors | B53: 3LT | C53: AH2 | D53: HVZ | H53: Asymmetrical Adrenaline Red / Jet Black | I53: Driver side Adrenaline red. Passenger side Jet Black with red stitching. | J53: =SUM( SUMIFS( PriceRef!$D$2:$D154, PriceRef!$A$2:$A154, "Seat", PriceRef!$B$2:$B154, $B53, PriceRef!$C$2:$C154, $C53 ), SUMIFS( PriceRef!$D$2:$D154, PriceRef!$A$2:$A154, "Stitching", PriceRef!$C$2:$C154, $F53 ), SUMIFS( PriceRef!$D$2:$D154, PriceRef!$A$2:$A154, "Suede", PriceRef!$C$2:$C154, $E53 ), SUMIFS( PriceRef!$D$2:$D154, PriceRef!$A$2:$A154, "TwoTone", PriceRef!$C$2:$C154, $G53 ) ) -> 0 | K53: interior.3 | L53: =textjoin(" ",true,B53,C53,D53,F53,E53,G53) -> 3LT AH2 HVZ
A54: 3LT Colors | B54: 3LT | C54: AE4 | D54: HVZ | H54: Asymmetrical Adrenaline Red / Jet Black | I54: Driver side Adrenaline red. Passenger side Jet Black with red stitching. | J54: =SUM( SUMIFS( PriceRef!$D$2:$D154, PriceRef!$A$2:$A154, "Seat", PriceRef!$B$2:$B154, $B54, PriceRef!$C$2:$C154, $C54 ), SUMIFS( PriceRef!$D$2:$D154, PriceRef!$A$2:$A154, "Stitching", PriceRef!$C$2:$C154, $F54 ), SUMIFS( PriceRef!$D$2:$D154, PriceRef!$A$2:$A154, "Suede", PriceRef!$C$2:$C154, $E54 ), SUMIFS( PriceRef!$D$2:$D154, PriceRef!$A$2:$A154, "TwoTone", PriceRef!$C$2:$C154, $G54 ) ) -> 500 | K54: interior.3 | L54: =textjoin(" ",true,B54,C54,D54,F54,E54,G54) -> 3LT AE4 HVZ
A55: 3LT Colors | B55: 3LT | C55: AUP | D55: HVZ | H55: Asymmetrical Adrenaline Red / Jet Black | I55: Driver seat Adrenaline red Competition sport bucket. Passenger seat Jet Black with red stitching GT2 Bucket. | J55: =SUM( SUMIFS( PriceRef!$D$2:$D154, PriceRef!$A$2:$A154, "Seat", PriceRef!$B$2:$B154, $B55, PriceRef!$C$2:$C154, $C55 ), SUMIFS( PriceRef!$D$2:$D154, PriceRef!$A$2:$A154, "Stitching", PriceRef!$C$2:$C154, $F55 ), SUMIFS( PriceRef!$D$2:$D154, PriceRef!$A$2:$A154, "Suede", PriceRef!$C$2:$C154, $E55 ), SUMIFS( PriceRef!$D$2:$D154, PriceRef!$A$2:$A154, "TwoTone", PriceRef!$C$2:$C154, $G55 ) ) -> 250 | K55: interior.3 | L55: =textjoin(" ",true,B55,C55,D55,F55,E55,G55) -> 3LT AUP HVZ
A56: 3LT Colors | B56: 3LT | C56: AH2 | D56: HTE | H56: Jet Black Napa | I56: AH2 GT2 Seats. Jet black has silver contrast stitching. Custom Stitching is on headliner of Coupe only. All Napa. | J56: =SUM( SUMIFS( PriceRef!$D$2:$D154, PriceRef!$A$2:$A154, "Seat", PriceRef!$B$2:$B154, $B56, PriceRef!$C$2:$C154, $C56 ), SUMIFS( PriceRef!$D$2:$D154, PriceRef!$A$2:$A154, "Stitching", PriceRef!$C$2:$C154, $F56 ), SUMIFS( PriceRef!$D$2:$D154, PriceRef!$A$2:$A154, "Suede", PriceRef!$C$2:$C154, $E56 ), SUMIFS( PriceRef!$D$2:$D154, PriceRef!$A$2:$A154, "TwoTone", PriceRef!$C$2:$C154, $G56 ) ) -> 0 | K56: interior.3 | L56: =textjoin(" ",true,B56,C56,D56,F56,E56,G56) -> 3LT AH2 HTE
A57: 3LT Colors | B57: 3LT | C57: AH2 | D57: HTE | F57: 36S | H57: Jet Black Napa with Yellow Custom Stitching | I57: AH2 GT2 Seats. Interior color is on seats, doors, console, and knee areas. Custom Stitching is on headliner of Coupe only. All Napa. | J57: =SUM( SUMIFS( PriceRef!$D$2:$D154, PriceRef!$A$2:$A154, "Seat", PriceRef!$B$2:$B154, $B57, PriceRef!$C$2:$C154, $C57 ), SUMIFS( PriceRef!$D$2:$D154, PriceRef!$A$2:$A154, "Stitching", PriceRef!$C$2:$C154, $F57 ), SUMIFS( PriceRef!$D$2:$D154, PriceRef!$A$2:$A154, "Suede", PriceRef!$C$2:$C154, $E57 ), SUMIFS( PriceRef!$D$2:$D154, PriceRef!$A$2:$A154, "TwoTone", PriceRef!$C$2:$C154, $G57 ) ) -> 495 | K57: interior.3 | L57: =textjoin(" ",true,B57,C57,D57,F57,E57,G57) -> 3LT AH2 HTE 36S
A58: 3LT Colors | B58: 3LT | C58: AH2 | D58: HTE | F58: 38S | H58: Jet Black Napa with Red Custom Stitching | I58: AH2 GT2 Seats. Custom Stitching is on headliner of Coupe only. All Napa. | J58: =SUM( SUMIFS( PriceRef!$D$2:$D154, PriceRef!$A$2:$A154, "Seat", PriceRef!$B$2:$B154, $B58, PriceRef!$C$2:$C154, $C58 ), SUMIFS( PriceRef!$D$2:$D154, PriceRef!$A$2:$A154, "Stitching", PriceRef!$C$2:$C154, $F58 ), SUMIFS( PriceRef!$D$2:$D154, PriceRef!$A$2:$A154, "Suede", PriceRef!$C$2:$C154, $E58 ), SUMIFS( PriceRef!$D$2:$D154, PriceRef!$A$2:$A154, "TwoTone", PriceRef!$C$2:$C154, $G58 ) ) -> 495 | K58: interior.3 | L58: =textjoin(" ",true,B58,C58,D58,F58,E58,G58) -> 3LT AH2 HTE 38S
A59: 3LT Colors | B59: 3LT | C59: AH2 | D59: HTE | F59: 37S | H59: Jet Black Napa with Blue Custom Stitching | I59: AH2 GT2 Seats. Custom Stitching is on headliner of Coupe only. All Napa. | J59: =SUM( SUMIFS( PriceRef!$D$2:$D154, PriceRef!$A$2:$A154, "Seat", PriceRef!$B$2:$B154, $B59, PriceRef!$C$2:$C154, $C59 ), SUMIFS( PriceRef!$D$2:$D154, PriceRef!$A$2:$A154, "Stitching", PriceRef!$C$2:$C154, $F59 ), SUMIFS( PriceRef!$D$2:$D154, PriceRef!$A$2:$A154, "Suede", PriceRef!$C$2:$C154, $E59 ), SUMIFS( PriceRef!$D$2:$D154, PriceRef!$A$2:$A154, "TwoTone", PriceRef!$C$2:$C154, $G59 ) ) -> 495 | K59: interior.3 | L59: =textjoin(" ",true,B59,C59,D59,F59,E59,G59) -> 3LT AH2 HTE 37S
A60: 3LT Colors | B60: 3LT | C60: AE4 | D60: HTE | H60: Jet Black Napa | I60: AE4 Comp Seats. Interior color is on seats, doors, console, and knee areas. Custom Stitching is on headliner of Coupe only. All Napa. | J60: =SUM( SUMIFS( PriceRef!$D$2:$D154, PriceRef!$A$2:$A154, "Seat", PriceRef!$B$2:$B154, $B60, PriceRef!$C$2:$C154, $C60 ), SUMIFS( PriceRef!$D$2:$D154, PriceRef!$A$2:$A154, "Stitching", PriceRef!$C$2:$C154, $F60 ), SUMIFS( PriceRef!$D$2:$D154, PriceRef!$A$2:$A154, "Suede", PriceRef!$C$2:$C154, $E60 ), SUMIFS( PriceRef!$D$2:$D154, PriceRef!$A$2:$A154, "TwoTone", PriceRef!$C$2:$C154, $G60 ) ) -> 500 | K60: interior.3 | L60: =textjoin(" ",true,B60,C60,D60,F60,E60,G60) -> 3LT AE4 HTE
A61: 3LT Colors | B61: 3LT | C61: AE4 | D61: HTE | F61: 36S | H61: Jet Black Napa with Yellow Custom Stitching | I61: AE4 Comp Seats. Interior color is on seats, doors, console, and knee areas. Custom Stitching is on headliner of Coupe only. All Napa. | J61: =SUM( SUMIFS( PriceRef!$D$2:$D154, PriceRef!$A$2:$A154, "Seat", PriceRef!$B$2:$B154, $B61, PriceRef!$C$2:$C154, $C61 ), SUMIFS( PriceRef!$D$2:$D154, PriceRef!$A$2:$A154, "Stitching", PriceRef!$C$2:$C154, $F61 ), SUMIFS( PriceRef!$D$2:$D154, PriceRef!$A$2:$A154, "Suede", PriceRef!$C$2:$C154, $E61 ), SUMIFS( PriceRef!$D$2:$D154, PriceRef!$A$2:$A154, "TwoTone", PriceRef!$C$2:$C154, $G61 ) ) -> 995 | K61: interior.3 | L61: =textjoin(" ",true,B61,C61,D61,F61,E61,G61) -> 3LT AE4 HTE 36S
A62: 3LT Colors | B62: 3LT | C62: AE4 | D62: HTE | F62: 37S | H62: Jet Black Napa with Blue Custom Stitching | I62: AE4 Comp Seats. Custom Stitching is on headliner of Coupe only. All Napa. | J62: =SUM( SUMIFS( PriceRef!$D$2:$D154, PriceRef!$A$2:$A154, "Seat", PriceRef!$B$2:$B154, $B62, PriceRef!$C$2:$C154, $C62 ), SUMIFS( PriceRef!$D$2:$D154, PriceRef!$A$2:$A154, "Stitching", PriceRef!$C$2:$C154, $F62 ), SUMIFS( PriceRef!$D$2:$D154, PriceRef!$A$2:$A154, "Suede", PriceRef!$C$2:$C154, $E62 ), SUMIFS( PriceRef!$D$2:$D154, PriceRef!$A$2:$A154, "TwoTone", PriceRef!$C$2:$C154, $G62 ) ) -> 995 | K62: interior.3 | L62: =textjoin(" ",true,B62,C62,D62,F62,E62,G62) -> 3LT AE4 HTE 37S
A63: 3LT Colors | B63: 3LT | C63: AE4 | D63: HTE | F63: 38S | H63: Jet Black Napa with Red Custom Stitching | I63: AE4 Comp Seats. Custom Stitching is on headliner of Coupe only. All Napa. | J63: =SUM( SUMIFS( PriceRef!$D$2:$D154, PriceRef!$A$2:$A154, "Seat", PriceRef!$B$2:$B154, $B63, PriceRef!$C$2:$C154, $C63 ), SUMIFS( PriceRef!$D$2:$D154, PriceRef!$A$2:$A154, "Stitching", PriceRef!$C$2:$C154, $F63 ), SUMIFS( PriceRef!$D$2:$D154, PriceRef!$A$2:$A154, "Suede", PriceRef!$C$2:$C154, $E63 ), SUMIFS( PriceRef!$D$2:$D154, PriceRef!$A$2:$A154, "TwoTone", PriceRef!$C$2:$C154, $G63 ) ) -> 995 | K63: interior.3 | L63: =textjoin(" ",true,B63,C63,D63,F63,E63,G63) -> 3LT AE4 HTE 38S
A64: 3LT Colors | B64: 3LT | C64: AH2 | D64: HTG | E64: N26 | H64: Natural Napa with sueded microfiber inserts | I64: AH2 GT2 Seats. Includes Suede Steering Wheel. Interior color is on seats, doors, console, and knee areas. Custom Stitching is on headliner of Coupe only. All Napa. TU7 Two tone seats available with GT2 seats | J64: =SUM( SUMIFS( PriceRef!$D$2:$D154, PriceRef!$A$2:$A154, "Seat", PriceRef!$B$2:$B154, $B64, PriceRef!$C$2:$C154, $C64 ), SUMIFS( PriceRef!$D$2:$D154, PriceRef!$A$2:$A154, "Stitching", PriceRef!$C$2:$C154, $F64 ), SUMIFS( PriceRef!$D$2:$D154, PriceRef!$A$2:$A154, "Suede", PriceRef!$C$2:$C154, $E64 ), SUMIFS( PriceRef!$D$2:$D154, PriceRef!$A$2:$A154, "TwoTone", PriceRef!$C$2:$C154, $G64 ) ) -> 695 | K64: interior.3 | L64: =textjoin(" ",true,B64,C64,D64,F64,E64,G64) -> 3LT AH2 HTG N26
A65: 3LT Colors | B65: 3LT | C65: AE4 | D65: HTG | E65: N26 | H65: Natural Napa with sueded microfiber inserts | I65: AE4 Comp Seats. Includes Suede Steering Wheel. Interior color is on seats, doors, console, and knee areas. Custom Stitching is on headliner of Coupe only. All Napa. | J65: =SUM( SUMIFS( PriceRef!$D$2:$D154, PriceRef!$A$2:$A154, "Seat", PriceRef!$B$2:$B154, $B65, PriceRef!$C$2:$C154, $C65 ), SUMIFS( PriceRef!$D$2:$D154, PriceRef!$A$2:$A154, "Stitching", PriceRef!$C$2:$C154, $F65 ), SUMIFS( PriceRef!$D$2:$D154, PriceRef!$A$2:$A154, "Suede", PriceRef!$C$2:$C154, $E65 ), SUMIFS( PriceRef!$D$2:$D154, PriceRef!$A$2:$A154, "TwoTone", PriceRef!$C$2:$C154, $G65 ) ) -> 1195 | K65: interior.3 | L65: =textjoin(" ",true,B65,C65,D65,F65,E65,G65) -> 3LT AE4 HTG N26
A66: 3LT Colors | B66: 3LT | C66: AH2 | D66: HTG | E66: N26 | G66: TU7 | H66: Natural Napa with sueded microfiber inserts and two tone seats | I66: AH2 GT2 Seats. Includes Suede Steering Wheel. Interior color is on seats, doors, console, and knee areas. Custom Stitching is on headliner of Coupe only. All Napa. TU7 Two tone adds black seat inserts and headrest. | J66: =SUM( SUMIFS( PriceRef!$D$2:$D154, PriceRef!$A$2:$A154, "Seat", PriceRef!$B$2:$B154, $B66, PriceRef!$C$2:$C154, $C66 ), SUMIFS( PriceRef!$D$2:$D154, PriceRef!$A$2:$A154, "Stitching", PriceRef!$C$2:$C154, $F66 ), SUMIFS( PriceRef!$D$2:$D154, PriceRef!$A$2:$A154, "Suede", PriceRef!$C$2:$C154, $E66 ), SUMIFS( PriceRef!$D$2:$D154, PriceRef!$A$2:$A154, "TwoTone", PriceRef!$C$2:$C154, $G66 ) ) -> 1290 | K66: interior.3 | L66: =textjoin(" ",true,B66,C66,D66,F66,E66,G66) -> 3LT AH2 HTG N26 TU7
A67: 3LT Colors | B67: 3LT | C67: AH2 | D67: H8T | H67: Santorini Blue Napa | I67: AH2 GT2 Seats. Includes Blue Seatbelt. | J67: =SUM( SUMIFS( PriceRef!$D$2:$D154, PriceRef!$A$2:$A154, "Seat", PriceRef!$B$2:$B154, $B67, PriceRef!$C$2:$C154, $C67 ), SUMIFS( PriceRef!$D$2:$D154, PriceRef!$A$2:$A154, "Stitching", PriceRef!$C$2:$C154, $F67 ), SUMIFS( PriceRef!$D$2:$D154, PriceRef!$A$2:$A154, "Suede", PriceRef!$C$2:$C154, $E67 ), SUMIFS( PriceRef!$D$2:$D154, PriceRef!$A$2:$A154, "TwoTone", PriceRef!$C$2:$C154, $G67 ) ) -> 0 | K67: interior.3 | L67: =textjoin(" ",true,B67,C67,D67,F67,E67,G67) -> 3LT AH2 H8T
A68: 3LT Colors | B68: 3LT | C68: AE4 | D68: H8T | H68: Santorini Blue Napa | I68: AE4 Comp Seats. Includes Blue Seatbelt. | J68: =SUM( SUMIFS( PriceRef!$D$2:$D154, PriceRef!$A$2:$A154, "Seat", PriceRef!$B$2:$B154, $B68, PriceRef!$C$2:$C154, $C68 ), SUMIFS( PriceRef!$D$2:$D154, PriceRef!$A$2:$A154, "Stitching", PriceRef!$C$2:$C154, $F68 ), SUMIFS( PriceRef!$D$2:$D154, PriceRef!$A$2:$A154, "Suede", PriceRef!$C$2:$C154, $E68 ), SUMIFS( PriceRef!$D$2:$D154, PriceRef!$A$2:$A154, "TwoTone", PriceRef!$C$2:$C154, $G68 ) ) -> 500 | K68: interior.3 | L68: =textjoin(" ",true,B68,C68,D68,F68,E68,G68) -> 3LT AE4 H8T
A69: 3LT Colors | B69: 3LT | C69: AH2 | D69: HTT | E69: N26 | F69: 36S | H69: Jet Black Napa with Yellow Custom Stitching & Suede Inserts | I69: AH2 GT2 Seats. Includes Suede Steering Wheel. Custom Stitching is on headliner of Coupe only. All Napa. Doors and console are also suede. | J69: =SUM( SUMIFS( PriceRef!$D$2:$D154, PriceRef!$A$2:$A154, "Seat", PriceRef!$B$2:$B154, $B69, PriceRef!$C$2:$C154, $C69 ), SUMIFS( PriceRef!$D$2:$D154, PriceRef!$A$2:$A154, "Stitching", PriceRef!$C$2:$C154, $F69 ), SUMIFS( PriceRef!$D$2:$D154, PriceRef!$A$2:$A154, "Suede", PriceRef!$C$2:$C154, $E69 ), SUMIFS( PriceRef!$D$2:$D154, PriceRef!$A$2:$A154, "TwoTone", PriceRef!$C$2:$C154, $G69 ) ) -> 1190 | K69: interior.3 | L69: =textjoin(" ",true,B69,C69,D69,F69,E69,G69) -> 3LT AH2 HTT 36S N26
A70: 3LT Colors | B70: 3LT | C70: AE4 | D70: HTT | E70: N26 | F70: 36S | H70: Jet Black Napa with Yellow Custom Stitching & Suede Inserts | I70: AE4 Comp Seats. Includes Suede Steering Wheel. Custom Stitching is on headliner of Coupe only. All Napa. Doors and console are also suede. | J70: =SUM( SUMIFS( PriceRef!$D$2:$D154, PriceRef!$A$2:$A154, "Seat", PriceRef!$B$2:$B154, $B70, PriceRef!$C$2:$C154, $C70 ), SUMIFS( PriceRef!$D$2:$D154, PriceRef!$A$2:$A154, "Stitching", PriceRef!$C$2:$C154, $F70 ), SUMIFS( PriceRef!$D$2:$D154, PriceRef!$A$2:$A154, "Suede", PriceRef!$C$2:$C154, $E70 ), SUMIFS( PriceRef!$D$2:$D154, PriceRef!$A$2:$A154, "TwoTone", PriceRef!$C$2:$C154, $G70 ) ) -> 1690 | K70: interior.3 | L70: =textjoin(" ",true,B70,C70,D70,F70,E70,G70) -> 3LT AE4 HTT 36S N26
A71: 3LT Colors | B71: 3LT | C71: AH2 | D71: HTT | E71: N26 | F71: 37S | H71: Jet Black Napa with Blue Custom Stitching and Suede Inserts | I71: AH2 GT2 Seats. Includes Suede Steering Wheel. Custom Stitching is on headliner of Coupe only. All Napa. Door and console trim are also suede. | J71: =SUM( SUMIFS( PriceRef!$D$2:$D154, PriceRef!$A$2:$A154, "Seat", PriceRef!$B$2:$B154, $B71, PriceRef!$C$2:$C154, $C71 ), SUMIFS( PriceRef!$D$2:$D154, PriceRef!$A$2:$A154, "Stitching", PriceRef!$C$2:$C154, $F71 ), SUMIFS( PriceRef!$D$2:$D154, PriceRef!$A$2:$A154, "Suede", PriceRef!$C$2:$C154, $E71 ), SUMIFS( PriceRef!$D$2:$D154, PriceRef!$A$2:$A154, "TwoTone", PriceRef!$C$2:$C154, $G71 ) ) -> 1190 | K71: interior.3 | L71: =textjoin(" ",true,B71,C71,D71,F71,E71,G71) -> 3LT AH2 HTT 37S N26
A72: 3LT Colors | B72: 3LT | C72: AE4 | D72: HTT | E72: N26 | F72: 37S | H72: Jet Black Napa with Blue Custom Stitching and Suede Inserts | I72: AE4 Comp Seats. Includes Suede Steering Wheel. Custom Stitching is on headliner of Coupe only. All Napa. Door and console trim are also suede. | J72: =SUM( SUMIFS( PriceRef!$D$2:$D154, PriceRef!$A$2:$A154, "Seat", PriceRef!$B$2:$B154, $B72, PriceRef!$C$2:$C154, $C72 ), SUMIFS( PriceRef!$D$2:$D154, PriceRef!$A$2:$A154, "Stitching", PriceRef!$C$2:$C154, $F72 ), SUMIFS( PriceRef!$D$2:$D154, PriceRef!$A$2:$A154, "Suede", PriceRef!$C$2:$C154, $E72 ), SUMIFS( PriceRef!$D$2:$D154, PriceRef!$A$2:$A154, "TwoTone", PriceRef!$C$2:$C154, $G72 ) ) -> 1690 | K72: interior.3 | L72: =textjoin(" ",true,B72,C72,D72,F72,E72,G72) -> 3LT AE4 HTT 37S N26
A73: 3LT Colors | B73: 3LT | C73: AH2 | D73: HTT | E73: N26 | F73: 38S | H73: Jet Black Napa with Red Custom Stitching and Suede Inserts | I73: AH2 GT2 Seats. Includes Suede Steering Wheel. Custom Stitching is on headliner of Coupe only. All Napa. Doors and console are also suede. | J73: =SUM( SUMIFS( PriceRef!$D$2:$D154, PriceRef!$A$2:$A154, "Seat", PriceRef!$B$2:$B154, $B73, PriceRef!$C$2:$C154, $C73 ), SUMIFS( PriceRef!$D$2:$D154, PriceRef!$A$2:$A154, "Stitching", PriceRef!$C$2:$C154, $F73 ), SUMIFS( PriceRef!$D$2:$D154, PriceRef!$A$2:$A154, "Suede", PriceRef!$C$2:$C154, $E73 ), SUMIFS( PriceRef!$D$2:$D154, PriceRef!$A$2:$A154, "TwoTone", PriceRef!$C$2:$C154, $G73 ) ) -> 1190 | K73: interior.3 | L73: =textjoin(" ",true,B73,C73,D73,F73,E73,G73) -> 3LT AH2 HTT 38S N26
A74: 3LT Colors | B74: 3LT | C74: AE4 | D74: HTT | E74: N26 | F74: 38S | H74: Jet Black Napa with Red Custom Stitching and Suede Inserts | I74: AE4 Comp Seats. Includes Suede Steering Wheel. Custom Stitching is on headliner of Coupe only. All Napa. Doors and console are also suede. | J74: =SUM( SUMIFS( PriceRef!$D$2:$D154, PriceRef!$A$2:$A154, "Seat", PriceRef!$B$2:$B154, $B74, PriceRef!$C$2:$C154, $C74 ), SUMIFS( PriceRef!$D$2:$D154, PriceRef!$A$2:$A154, "Stitching", PriceRef!$C$2:$C154, $F74 ), SUMIFS( PriceRef!$D$2:$D154, PriceRef!$A$2:$A154, "Suede", PriceRef!$C$2:$C154, $E74 ), SUMIFS( PriceRef!$D$2:$D154, PriceRef!$A$2:$A154, "TwoTone", PriceRef!$C$2:$C154, $G74 ) ) -> 1690 | K74: interior.3 | L74: =textjoin(" ",true,B74,C74,D74,F74,E74,G74) -> 3LT AE4 HTT 38S N26
A75: 3LT Colors | B75: 3LT | C75: AH2 | D75: HTT | E75: N26 | H75: Jet Black Napa with sueded microfiber inserts | I75: AH2 GT2 Seats. Custom Stitching is on headliner of Coupe only. All Napa. | J75: =SUM( SUMIFS( PriceRef!$D$2:$D154, PriceRef!$A$2:$A154, "Seat", PriceRef!$B$2:$B154, $B75, PriceRef!$C$2:$C154, $C75 ), SUMIFS( PriceRef!$D$2:$D154, PriceRef!$A$2:$A154, "Stitching", PriceRef!$C$2:$C154, $F75 ), SUMIFS( PriceRef!$D$2:$D154, PriceRef!$A$2:$A154, "Suede", PriceRef!$C$2:$C154, $E75 ), SUMIFS( PriceRef!$D$2:$D154, PriceRef!$A$2:$A154, "TwoTone", PriceRef!$C$2:$C154, $G75 ) ) -> 695 | K75: interior.3 | L75: =textjoin(" ",true,B75,C75,D75,F75,E75,G75) -> 3LT AH2 HTT N26
A76: 3LT Colors | B76: 3LT | C76: AE4 | D76: HTT | E76: N26 | H76: Jet Black Napa with sueded microfiber inserts | I76: AE4 Comp Seats. Custom Stitching is on headliner of Coupe only. All Napa. | J76: =SUM( SUMIFS( PriceRef!$D$2:$D154, PriceRef!$A$2:$A154, "Seat", PriceRef!$B$2:$B154, $B76, PriceRef!$C$2:$C154, $C76 ), SUMIFS( PriceRef!$D$2:$D154, PriceRef!$A$2:$A154, "Stitching", PriceRef!$C$2:$C154, $F76 ), SUMIFS( PriceRef!$D$2:$D154, PriceRef!$A$2:$A154, "Suede", PriceRef!$C$2:$C154, $E76 ), SUMIFS( PriceRef!$D$2:$D154, PriceRef!$A$2:$A154, "TwoTone", PriceRef!$C$2:$C154, $G76 ) ) -> 1195 | K76: interior.3 | L76: =textjoin(" ",true,B76,C76,D76,F76,E76,G76) -> 3LT AE4 HTT N26
A77: 3LT Colors | B77: 3LT | C77: AH2 | D77: HUC | H77: Ultimate Suede Jet Black Napa | I77: AH2 GT2 Seats. Suede is on trim and dash. | J77: =SUM( SUMIFS( PriceRef!$D$2:$D154, PriceRef!$A$2:$A154, "Seat", PriceRef!$B$2:$B154, $B77, PriceRef!$C$2:$C154, $C77 ), SUMIFS( PriceRef!$D$2:$D154, PriceRef!$A$2:$A154, "Stitching", PriceRef!$C$2:$C154, $F77 ), SUMIFS( PriceRef!$D$2:$D154, PriceRef!$A$2:$A154, "Suede", PriceRef!$C$2:$C154, $E77 ), SUMIFS( PriceRef!$D$2:$D154, PriceRef!$A$2:$A154, "TwoTone", PriceRef!$C$2:$C154, $G77 ) ) -> 0 | K77: interior.3 | L77: =textjoin(" ",true,B77,C77,D77,F77,E77,G77) -> 3LT AH2 HUC
A78: 3LT Colors | B78: 3LT | C78: AH2 | D78: HUC | F78: 36S | H78: Ultimate Suede Jet Black Napa with Yellow Stitching | I78: AH2 GT2 Seats. Suede is on trim and dash. | J78: =SUM( SUMIFS( PriceRef!$D$2:$D154, PriceRef!$A$2:$A154, "Seat", PriceRef!$B$2:$B154, $B78, PriceRef!$C$2:$C154, $C78 ), SUMIFS( PriceRef!$D$2:$D154, PriceRef!$A$2:$A154, "Stitching", PriceRef!$C$2:$C154, $F78 ), SUMIFS( PriceRef!$D$2:$D154, PriceRef!$A$2:$A154, "Suede", PriceRef!$C$2:$C154, $E78 ), SUMIFS( PriceRef!$D$2:$D154, PriceRef!$A$2:$A154, "TwoTone", PriceRef!$C$2:$C154, $G78 ) ) -> 495 | K78: interior.3 | L78: =textjoin(" ",true,B78,C78,D78,F78,E78,G78) -> 3LT AH2 HUC 36S
A79: 3LT Colors | B79: 3LT | C79: AH2 | D79: HUC | F79: 37S | H79: Ultimate Suede Jet Black Napa with Blue Stitching | I79: AH2 GT2 Seats. Suede is on trim and dash. | J79: =SUM( SUMIFS( PriceRef!$D$2:$D154, PriceRef!$A$2:$A154, "Seat", PriceRef!$B$2:$B154, $B79, PriceRef!$C$2:$C154, $C79 ), SUMIFS( PriceRef!$D$2:$D154, PriceRef!$A$2:$A154, "Stitching", PriceRef!$C$2:$C154, $F79 ), SUMIFS( PriceRef!$D$2:$D154, PriceRef!$A$2:$A154, "Suede", PriceRef!$C$2:$C154, $E79 ), SUMIFS( PriceRef!$D$2:$D154, PriceRef!$A$2:$A154, "TwoTone", PriceRef!$C$2:$C154, $G79 ) ) -> 495 | K79: interior.3 | L79: =textjoin(" ",true,B79,C79,D79,F79,E79,G79) -> 3LT AH2 HUC 37S
A80: 3LT Colors | B80: 3LT | C80: AH2 | D80: HUC | F80: 38S | H80: Ultimate Suede Jet Black Napa with Red Stitching | I80: AH2 GT2 Seats. Suede is on trim and dash. | J80: =SUM( SUMIFS( PriceRef!$D$2:$D154, PriceRef!$A$2:$A154, "Seat", PriceRef!$B$2:$B154, $B80, PriceRef!$C$2:$C154, $C80 ), SUMIFS( PriceRef!$D$2:$D154, PriceRef!$A$2:$A154, "Stitching", PriceRef!$C$2:$C154, $F80 ), SUMIFS( PriceRef!$D$2:$D154, PriceRef!$A$2:$A154, "Suede", PriceRef!$C$2:$C154, $E80 ), SUMIFS( PriceRef!$D$2:$D154, PriceRef!$A$2:$A154, "TwoTone", PriceRef!$C$2:$C154, $G80 ) ) -> 495 | K80: interior.3 | L80: =textjoin(" ",true,B80,C80,D80,F80,E80,G80) -> 3LT AH2 HUC 38S
A81: 3LT Colors | B81: 3LT | C81: AE4 | D81: HUC | H81: Ultimate Suede Jet Black Napa | I81: AE4 Competition Seats. Suede is on trim and dash. | J81: =SUM( SUMIFS( PriceRef!$D$2:$D154, PriceRef!$A$2:$A154, "Seat", PriceRef!$B$2:$B154, $B81, PriceRef!$C$2:$C154, $C81 ), SUMIFS( PriceRef!$D$2:$D154, PriceRef!$A$2:$A154, "Stitching", PriceRef!$C$2:$C154, $F81 ), SUMIFS( PriceRef!$D$2:$D154, PriceRef!$A$2:$A154, "Suede", PriceRef!$C$2:$C154, $E81 ), SUMIFS( PriceRef!$D$2:$D154, PriceRef!$A$2:$A154, "TwoTone", PriceRef!$C$2:$C154, $G81 ) ) -> 500 | K81: interior.3 | L81: =textjoin(" ",true,B81,C81,D81,F81,E81,G81) -> 3LT AE4 HUC
A82: 3LT Colors | B82: 3LT | C82: AE4 | D82: HUC | F82: 36S | H82: Ultimate Suede Jet Black Napa with Yellow Stitching | I82: AE4 Competition Seats. Suede is on trim and dash. | J82: =SUM( SUMIFS( PriceRef!$D$2:$D154, PriceRef!$A$2:$A154, "Seat", PriceRef!$B$2:$B154, $B82, PriceRef!$C$2:$C154, $C82 ), SUMIFS( PriceRef!$D$2:$D154, PriceRef!$A$2:$A154, "Stitching", PriceRef!$C$2:$C154, $F82 ), SUMIFS( PriceRef!$D$2:$D154, PriceRef!$A$2:$A154, "Suede", PriceRef!$C$2:$C154, $E82 ), SUMIFS( PriceRef!$D$2:$D154, PriceRef!$A$2:$A154, "TwoTone", PriceRef!$C$2:$C154, $G82 ) ) -> 995 | K82: interior.3 | L82: =textjoin(" ",true,B82,C82,D82,F82,E82,G82) -> 3LT AE4 HUC 36S
A83: 3LT Colors | B83: 3LT | C83: AE4 | D83: HUC | F83: 37S | H83: Ultimate Suede Jet Black Napa with Blue Stitching | I83: AE4 Competition Seats. Suede is on trim and dash. | J83: =SUM( SUMIFS( PriceRef!$D$2:$D154, PriceRef!$A$2:$A154, "Seat", PriceRef!$B$2:$B154, $B83, PriceRef!$C$2:$C154, $C83 ), SUMIFS( PriceRef!$D$2:$D154, PriceRef!$A$2:$A154, "Stitching", PriceRef!$C$2:$C154, $F83 ), SUMIFS( PriceRef!$D$2:$D154, PriceRef!$A$2:$A154, "Suede", PriceRef!$C$2:$C154, $E83 ), SUMIFS( PriceRef!$D$2:$D154, PriceRef!$A$2:$A154, "TwoTone", PriceRef!$C$2:$C154, $G83 ) ) -> 995 | K83: interior.3 | L83: =textjoin(" ",true,B83,C83,D83,F83,E83,G83) -> 3LT AE4 HUC 37S
A84: 3LT Colors | B84: 3LT | C84: AE4 | D84: HUC | F84: 38S | H84: Ultimate Suede Jet Black Napa with Red Stitching | I84: AE4 Competition Seats. Suede is on trim and dash. | J84: =SUM( SUMIFS( PriceRef!$D$2:$D154, PriceRef!$A$2:$A154, "Seat", PriceRef!$B$2:$B154, $B84, PriceRef!$C$2:$C154, $C84 ), SUMIFS( PriceRef!$D$2:$D154, PriceRef!$A$2:$A154, "Stitching", PriceRef!$C$2:$C154, $F84 ), SUMIFS( PriceRef!$D$2:$D154, PriceRef!$A$2:$A154, "Suede", PriceRef!$C$2:$C154, $E84 ), SUMIFS( PriceRef!$D$2:$D154, PriceRef!$A$2:$A154, "TwoTone", PriceRef!$C$2:$C154, $G84 ) ) -> 995 | K84: interior.3 | L84: =textjoin(" ",true,B84,C84,D84,F84,E84,G84) -> 3LT AE4 HUC 38S
A85: 3LT Colors | B85: 3LT | C85: AH2 | D85: HUB | H85: Ultimate Suede Jet Black Napa with sueded microfiber inserts | I85: AH2 GT2 Seats. Suede is on trim and dash. | J85: =SUM( SUMIFS( PriceRef!$D$2:$D154, PriceRef!$A$2:$A154, "Seat", PriceRef!$B$2:$B154, $B85, PriceRef!$C$2:$C154, $C85 ), SUMIFS( PriceRef!$D$2:$D154, PriceRef!$A$2:$A154, "Stitching", PriceRef!$C$2:$C154, $F85 ), SUMIFS( PriceRef!$D$2:$D154, PriceRef!$A$2:$A154, "Suede", PriceRef!$C$2:$C154, $E85 ), SUMIFS( PriceRef!$D$2:$D154, PriceRef!$A$2:$A154, "TwoTone", PriceRef!$C$2:$C154, $G85 ) ) -> 0 | K85: interior.3 | L85: =textjoin(" ",true,B85,C85,D85,F85,E85,G85) -> 3LT AH2 HUB
A86: 3LT Colors | B86: 3LT | C86: AH2 | D86: HUB | E86: N26 | F86: 36S | H86: Ultimate Suede Jet Black Napa with sueded microfiber inserts and Yellow Stitching | I86: AH2 GT2 Seats. Suede is on trim and dash. | J86: =SUM( SUMIFS( PriceRef!$D$2:$D154, PriceRef!$A$2:$A154, "Seat", PriceRef!$B$2:$B154, $B86, PriceRef!$C$2:$C154, $C86 ), SUMIFS( PriceRef!$D$2:$D154, PriceRef!$A$2:$A154, "Stitching", PriceRef!$C$2:$C154, $F86 ), SUMIFS( PriceRef!$D$2:$D154, PriceRef!$A$2:$A154, "Suede", PriceRef!$C$2:$C154, $E86 ), SUMIFS( PriceRef!$D$2:$D154, PriceRef!$A$2:$A154, "TwoTone", PriceRef!$C$2:$C154, $G86 ) ) -> 1190 | K86: interior.3 | L86: =textjoin(" ",true,B86,C86,D86,F86,E86,G86) -> 3LT AH2 HUB 36S N26
A87: 3LT Colors | B87: 3LT | C87: AH2 | D87: HUB | E87: N26 | F87: 37S | H87: Ultimate Suede Jet Black Napa with sueded microfiber inserts and Blue Stitching | I87: AH2 GT2 Seats. Suede is on trim and dash. | J87: =SUM( SUMIFS( PriceRef!$D$2:$D154, PriceRef!$A$2:$A154, "Seat", PriceRef!$B$2:$B154, $B87, PriceRef!$C$2:$C154, $C87 ), SUMIFS( PriceRef!$D$2:$D154, PriceRef!$A$2:$A154, "Stitching", PriceRef!$C$2:$C154, $F87 ), SUMIFS( PriceRef!$D$2:$D154, PriceRef!$A$2:$A154, "Suede", PriceRef!$C$2:$C154, $E87 ), SUMIFS( PriceRef!$D$2:$D154, PriceRef!$A$2:$A154, "TwoTone", PriceRef!$C$2:$C154, $G87 ) ) -> 1190 | K87: interior.3 | L87: =textjoin(" ",true,B87,C87,D87,F87,E87,G87) -> 3LT AH2 HUB 37S N26
A88: 3LT Colors | B88: 3LT | C88: AH2 | D88: HUB | E88: N26 | F88: 38S | H88: Ultimate Suede Jet Black Napa with sueded microfiber inserts and Red Stitching | I88: AH2 GT2 Seats. Suede is on trim and dash. | J88: =SUM( SUMIFS( PriceRef!$D$2:$D154, PriceRef!$A$2:$A154, "Seat", PriceRef!$B$2:$B154, $B88, PriceRef!$C$2:$C154, $C88 ), SUMIFS( PriceRef!$D$2:$D154, PriceRef!$A$2:$A154, "Stitching", PriceRef!$C$2:$C154, $F88 ), SUMIFS( PriceRef!$D$2:$D154, PriceRef!$A$2:$A154, "Suede", PriceRef!$C$2:$C154, $E88 ), SUMIFS( PriceRef!$D$2:$D154, PriceRef!$A$2:$A154, "TwoTone", PriceRef!$C$2:$C154, $G88 ) ) -> 1190 | K88: interior.3 | L88: =textjoin(" ",true,B88,C88,D88,F88,E88,G88) -> 3LT AH2 HUB 38S N26
A89: 3LT Colors | B89: 3LT | C89: AE4 | D89: HUB | E89: N26 | H89: Ultimate Suede Jet Black Napa with sueded microfiber inserts | I89: AE4 Competition Seats. Suede is on trim and dash. | J89: =SUM( SUMIFS( PriceRef!$D$2:$D154, PriceRef!$A$2:$A154, "Seat", PriceRef!$B$2:$B154, $B89, PriceRef!$C$2:$C154, $C89 ), SUMIFS( PriceRef!$D$2:$D154, PriceRef!$A$2:$A154, "Stitching", PriceRef!$C$2:$C154, $F89 ), SUMIFS( PriceRef!$D$2:$D154, PriceRef!$A$2:$A154, "Suede", PriceRef!$C$2:$C154, $E89 ), SUMIFS( PriceRef!$D$2:$D154, PriceRef!$A$2:$A154, "TwoTone", PriceRef!$C$2:$C154, $G89 ) ) -> 1195 | K89: interior.3 | L89: =textjoin(" ",true,B89,C89,D89,F89,E89,G89) -> 3LT AE4 HUB N26
A90: 3LT Colors | B90: 3LT | C90: AE4 | D90: HUB | E90: N26 | F90: 36S | H90: Ultimate Suede Jet Black Napa with sueded microfiber inserts and Yellow Stitching | I90: AE4 Competition Seats. Suede is on trim and dash. | J90: =SUM( SUMIFS( PriceRef!$D$2:$D154, PriceRef!$A$2:$A154, "Seat", PriceRef!$B$2:$B154, $B90, PriceRef!$C$2:$C154, $C90 ), SUMIFS( PriceRef!$D$2:$D154, PriceRef!$A$2:$A154, "Stitching", PriceRef!$C$2:$C154, $F90 ), SUMIFS( PriceRef!$D$2:$D154, PriceRef!$A$2:$A154, "Suede", PriceRef!$C$2:$C154, $E90 ), SUMIFS( PriceRef!$D$2:$D154, PriceRef!$A$2:$A154, "TwoTone", PriceRef!$C$2:$C154, $G90 ) ) -> 1690 | K90: interior.3 | L90: =textjoin(" ",true,B90,C90,D90,F90,E90,G90) -> 3LT AE4 HUB 36S N26
A91: 3LT Colors | B91: 3LT | C91: AE4 | D91: HUB | E91: N26 | F91: 37S | H91: Ultimate Suede Jet Black Napa with sueded microfiber inserts and Blue Stitching | I91: AE4 Competition Seats. Suede is on trim and dash. | J91: =SUM( SUMIFS( PriceRef!$D$2:$D154, PriceRef!$A$2:$A154, "Seat", PriceRef!$B$2:$B154, $B91, PriceRef!$C$2:$C154, $C91 ), SUMIFS( PriceRef!$D$2:$D154, PriceRef!$A$2:$A154, "Stitching", PriceRef!$C$2:$C154, $F91 ), SUMIFS( PriceRef!$D$2:$D154, PriceRef!$A$2:$A154, "Suede", PriceRef!$C$2:$C154, $E91 ), SUMIFS( PriceRef!$D$2:$D154, PriceRef!$A$2:$A154, "TwoTone", PriceRef!$C$2:$C154, $G91 ) ) -> 1690 | K91: interior.3 | L91: =textjoin(" ",true,B91,C91,D91,F91,E91,G91) -> 3LT AE4 HUB 37S N26
A92: 3LT Colors | B92: 3LT | C92: AE4 | D92: HUB | E92: N26 | F92: 38S | H92: Ultimate Suede Jet Black Napa with sueded microfiber inserts and Red Stitching | I92: AE4 Competition Seats. Suede is on trim and dash. | J92: =SUM( SUMIFS( PriceRef!$D$2:$D154, PriceRef!$A$2:$A154, "Seat", PriceRef!$B$2:$B154, $B92, PriceRef!$C$2:$C154, $C92 ), SUMIFS( PriceRef!$D$2:$D154, PriceRef!$A$2:$A154, "Stitching", PriceRef!$C$2:$C154, $F92 ), SUMIFS( PriceRef!$D$2:$D154, PriceRef!$A$2:$A154, "Suede", PriceRef!$C$2:$C154, $E92 ), SUMIFS( PriceRef!$D$2:$D154, PriceRef!$A$2:$A154, "TwoTone", PriceRef!$C$2:$C154, $G92 ) ) -> 1690 | K92: interior.3 | L92: =textjoin(" ",true,B92,C92,D92,F92,E92,G92) -> 3LT AE4 HUB 38S N26
A93: 3LT Colors | B93: 3LT | C93: AH2 | D93: HU1 | H93: Sky Cool Gray Napa | I93: AH2 GT2 Seats. Interior color is on seats, doors, console, and knee areas. Custom Stitching is on headliner of Coupe only. All Napa. TU7 Two tone seats available with GT2 seats. Upper Interior is sky cool gray suede. | J93: =SUM( SUMIFS( PriceRef!$D$2:$D154, PriceRef!$A$2:$A154, "Seat", PriceRef!$B$2:$B154, $B93, PriceRef!$C$2:$C154, $C93 ), SUMIFS( PriceRef!$D$2:$D154, PriceRef!$A$2:$A154, "Stitching", PriceRef!$C$2:$C154, $F93 ), SUMIFS( PriceRef!$D$2:$D154, PriceRef!$A$2:$A154, "Suede", PriceRef!$C$2:$C154, $E93 ), SUMIFS( PriceRef!$D$2:$D154, PriceRef!$A$2:$A154, "TwoTone", PriceRef!$C$2:$C154, $G93 ) ) -> 0 | K93: interior.3 | L93: =textjoin(" ",true,B93,C93,D93,F93,E93,G93) -> 3LT AH2 HU1
A94: 3LT Colors | B94: 3LT | C94: AE4 | D94: HU1 | H94: Sky Cool Gray Napa | I94: AE4 Comp Seats are black. Interior color is on seats, doors, console, and knee areas. Custom Stitching is on headliner of Coupe only. All Napa. Upper interior is Sky Cool Gray suede. | J94: =SUM( SUMIFS( PriceRef!$D$2:$D154, PriceRef!$A$2:$A154, "Seat", PriceRef!$B$2:$B154, $B94, PriceRef!$C$2:$C154, $C94 ), SUMIFS( PriceRef!$D$2:$D154, PriceRef!$A$2:$A154, "Stitching", PriceRef!$C$2:$C154, $F94 ), SUMIFS( PriceRef!$D$2:$D154, PriceRef!$A$2:$A154, "Suede", PriceRef!$C$2:$C154, $E94 ), SUMIFS( PriceRef!$D$2:$D154, PriceRef!$A$2:$A154, "TwoTone", PriceRef!$C$2:$C154, $G94 ) ) -> 500 | K94: interior.3 | L94: =textjoin(" ",true,B94,C94,D94,F94,E94,G94) -> 3LT AE4 HU1
A95: 3LT Colors | B95: 3LT | C95: AH2 | D95: HU1 | G95: TU7 | H95: Sky Cool Gray Napa with two tone seats | I95: AH2 GT2 Seats. Interior color is on seats, doors, console, and knee areas. Custom Stitching is on headliner of Coupe only. All Napa. TU7 Two tone adds black seat inserts and headrest. Upper Interior is sky cool gray suede. | J95: =SUM( SUMIFS( PriceRef!$D$2:$D154, PriceRef!$A$2:$A154, "Seat", PriceRef!$B$2:$B154, $B95, PriceRef!$C$2:$C154, $C95 ), SUMIFS( PriceRef!$D$2:$D154, PriceRef!$A$2:$A154, "Stitching", PriceRef!$C$2:$C154, $F95 ), SUMIFS( PriceRef!$D$2:$D154, PriceRef!$A$2:$A154, "Suede", PriceRef!$C$2:$C154, $E95 ), SUMIFS( PriceRef!$D$2:$D154, PriceRef!$A$2:$A154, "TwoTone", PriceRef!$C$2:$C154, $G95 ) ) -> 595 | K95: interior.3 | L95: =textjoin(" ",true,B95,C95,D95,F95,E95,G95) -> 3LT AH2 HU1 TU7
A96: 3LT Colors | B96: 3LT | C96: AH2 | D96: HU2 | H96: Adrenaline Red Napa | I96: AH2 GT2 Seats. Interior color is on seats, doors, console, and knee areas. Custom Stitching is on headliner of Coupe only. All Napa. TU7 Two tone seats available with GT2 seats | J96: =SUM( SUMIFS( PriceRef!$D$2:$D154, PriceRef!$A$2:$A154, "Seat", PriceRef!$B$2:$B154, $B96, PriceRef!$C$2:$C154, $C96 ), SUMIFS( PriceRef!$D$2:$D154, PriceRef!$A$2:$A154, "Stitching", PriceRef!$C$2:$C154, $F96 ), SUMIFS( PriceRef!$D$2:$D154, PriceRef!$A$2:$A154, "Suede", PriceRef!$C$2:$C154, $E96 ), SUMIFS( PriceRef!$D$2:$D154, PriceRef!$A$2:$A154, "TwoTone", PriceRef!$C$2:$C154, $G96 ) ) -> 0 | K96: interior.3 | L96: =textjoin(" ",true,B96,C96,D96,F96,E96,G96) -> 3LT AH2 HU2
A97: 3LT Colors | B97: 3LT | C97: AE4 | D97: HU2 | H97: Adrenaline Red Napa | I97: AE4 Comp Seats. Interior color is on seats, doors, console, and knee areas. Custom Stitching is on headliner of Coupe only. All Napa. | J97: =SUM( SUMIFS( PriceRef!$D$2:$D154, PriceRef!$A$2:$A154, "Seat", PriceRef!$B$2:$B154, $B97, PriceRef!$C$2:$C154, $C97 ), SUMIFS( PriceRef!$D$2:$D154, PriceRef!$A$2:$A154, "Stitching", PriceRef!$C$2:$C154, $F97 ), SUMIFS( PriceRef!$D$2:$D154, PriceRef!$A$2:$A154, "Suede", PriceRef!$C$2:$C154, $E97 ), SUMIFS( PriceRef!$D$2:$D154, PriceRef!$A$2:$A154, "TwoTone", PriceRef!$C$2:$C154, $G97 ) ) -> 500 | K97: interior.3 | L97: =textjoin(" ",true,B97,C97,D97,F97,E97,G97) -> 3LT AE4 HU2
A98: 3LT Colors | B98: 3LT | C98: AH2 | D98: HU2 | G98: TU7 | H98: Adrenaline Red Napa with two tone seats | I98: AH2 GT2 Seats. Interior color is on seats, doors, console, and knee areas. Custom Stitching is on headliner of Coupe only. All Napa. TU7 Two tone adds black seat inserts and headrest. | J98: =SUM( SUMIFS( PriceRef!$D$2:$D154, PriceRef!$A$2:$A154, "Seat", PriceRef!$B$2:$B154, $B98, PriceRef!$C$2:$C154, $C98 ), SUMIFS( PriceRef!$D$2:$D154, PriceRef!$A$2:$A154, "Stitching", PriceRef!$C$2:$C154, $F98 ), SUMIFS( PriceRef!$D$2:$D154, PriceRef!$A$2:$A154, "Suede", PriceRef!$C$2:$C154, $E98 ), SUMIFS( PriceRef!$D$2:$D154, PriceRef!$A$2:$A154, "TwoTone", PriceRef!$C$2:$C154, $G98 ) ) -> 595 | K98: interior.3 | L98: =textjoin(" ",true,B98,C98,D98,F98,E98,G98) -> 3LT AH2 HU2 TU7
A99: 3LT Colors | B99: 3LT | C99: AH2 | D99: HU9 | E99: N26 | H99: Sky Cool Gray Napa with sueded microfiber inserts | I99: AH2 GT2 Seats. Includes Suede Steering Wheel. Interior color is on seats, doors, console, and knee areas. Custom Stitching is on headliner of Coupe only. All Napa. TU7 Two tone seats available with GT2 seats. Upper Interior is sky cool gray suede. | J99: =SUM( SUMIFS( PriceRef!$D$2:$D154, PriceRef!$A$2:$A154, "Seat", PriceRef!$B$2:$B154, $B99, PriceRef!$C$2:$C154, $C99 ), SUMIFS( PriceRef!$D$2:$D154, PriceRef!$A$2:$A154, "Stitching", PriceRef!$C$2:$C154, $F99 ), SUMIFS( PriceRef!$D$2:$D154, PriceRef!$A$2:$A154, "Suede", PriceRef!$C$2:$C154, $E99 ), SUMIFS( PriceRef!$D$2:$D154, PriceRef!$A$2:$A154, "TwoTone", PriceRef!$C$2:$C154, $G99 ) ) -> 695 | K99: interior.3 | L99: =textjoin(" ",true,B99,C99,D99,F99,E99,G99) -> 3LT AH2 HU9 N26
A100: 3LT Colors | B100: 3LT | C100: AE4 | D100: HU9 | E100: N26 | H100: Sky Cool Gray Napa with sueded microfiber inserts | I100: AE4 Comp Seats are black. Includes Suede Steering Wheel. Interior color is on seats, doors, console, and knee areas. Custom Stitching is on headliner of Coupe only. All Napa. Upper Interior is sky cool gray suede. | J100: =SUM( SUMIFS( PriceRef!$D$2:$D154, PriceRef!$A$2:$A154, "Seat", PriceRef!$B$2:$B154, $B100, PriceRef!$C$2:$C154, $C100 ), SUMIFS( PriceRef!$D$2:$D154, PriceRef!$A$2:$A154, "Stitching", PriceRef!$C$2:$C154, $F100 ), SUMIFS( PriceRef!$D$2:$D154, PriceRef!$A$2:$A154, "Suede", PriceRef!$C$2:$C154, $E100 ), SUMIFS( PriceRef!$D$2:$D154, PriceRef!$A$2:$A154, "TwoTone", PriceRef!$C$2:$C154, $G100 ) ) -> 1195 | K100: interior.3 | L100: =textjoin(" ",true,B100,C100,D100,F100,E100,G100) -> 3LT AE4 HU9 N26
...

Sheet All_S
A1: RPO | B1: Description | C1: MISSING IN STINGRAY | E1: 1LT | F1: 2LT | G1: 3LT | H1: OTHER
A2: 36S | B2: Competition Yellow custom leather stitch | C2: =IFERROR(__xludf.DUMMYFUNCTION("IFERROR( FILTER( A2:B235, ( COUNTIF(STINGRAY!$A$2:$A$133, A2:A235) + COUNTIF(STINGRAY_INT!$D$2:$G$154, A2:A235) ) = 0 ), ""All codes accounted for"" )"),"A2X") -> A2X | D2: =IFERROR(__xludf.DUMMYFUNCTION("""COMPUTED_VALUE"""),"Seat adjuster, driver 8-way power") -> Seat adjuster, driver 8-way power | E2: 1LT | F2: 2LT | G2: 3LT
A3: 379 | B3: Seat belt color, Orange | C3: =IFERROR(__xludf.DUMMYFUNCTION("""COMPUTED_VALUE"""),"A7K") -> A7K | D3: =IFERROR(__xludf.DUMMYFUNCTION("""COMPUTED_VALUE"""),"Seat adjuster, passenger 8-way power") -> Seat adjuster, passenger 8-way power | E3: 1LT | F3: 2LT | G3: 3LT
A4: 37S | B4: Santorini Blue custom leather stitch | C4: =IFERROR(__xludf.DUMMYFUNCTION("""COMPUTED_VALUE"""),"AHE") -> AHE | D4: =IFERROR(__xludf.DUMMYFUNCTION("""COMPUTED_VALUE"""),"Seat adjuster, driver power bolster") -> Seat adjuster, driver power bolster | F4: 2LT | G4: 3LT
A5: 38S | B5: Adrenaline Red custom leather stitch | C5: =IFERROR(__xludf.DUMMYFUNCTION("""COMPUTED_VALUE"""),"AHH") -> AHH | D5: =IFERROR(__xludf.DUMMYFUNCTION("""COMPUTED_VALUE"""),"Seat adjuster, passenger power bolster") -> Seat adjuster, passenger power bolster | G5: 3LT
A6: 3A9 | B6: Seat belt color, Santorini Blue | C6: =IFERROR(__xludf.DUMMYFUNCTION("""COMPUTED_VALUE"""),"AJ7") -> AJ7 | D6: =IFERROR(__xludf.DUMMYFUNCTION("""COMPUTED_VALUE"""),"Airbags, frontal and side-impact, driver and passenger") -> Airbags, frontal and side-impact, driver and passenger | E6: 1LT | F6: 2LT | G6: 3LT
A7: 3F9 | B7: Seat belt color, Torch Red | C7: =IFERROR(__xludf.DUMMYFUNCTION("""COMPUTED_VALUE"""),"AL9") -> AL9 | D7: =IFERROR(__xludf.DUMMYFUNCTION("""COMPUTED_VALUE"""),"Seat adjuster, power driver lumbar control") -> Seat adjuster, power driver lumbar control | F7: 2LT | G7: 3LT
A8: 3M9 | B8: Seat belt color, Yellow | C8: =IFERROR(__xludf.DUMMYFUNCTION("""COMPUTED_VALUE"""),"AP9") -> AP9 | D8: =IFERROR(__xludf.DUMMYFUNCTION("""COMPUTED_VALUE"""),"Cargo nets") -> Cargo nets | F8: 2LT | G8: 3LT
A9: 3N9 | B9: Seat belt color, Natural | C9: =IFERROR(__xludf.DUMMYFUNCTION("""COMPUTED_VALUE"""),"AQA") -> AQA | D9: =IFERROR(__xludf.DUMMYFUNCTION("""COMPUTED_VALUE"""),"Memory Driver and Passenger Convenience Package") -> Memory Driver and Passenger Convenience Package | F9: 2LT | G9: 3LT
A10: 5DG | B10: LPO, 19" x 8.5" (48.3 cm x 21.6 cm) front and 20" x 11" (50.8 cm x 25.4 cm) rear 20-spoke Tech Bronze aluminum wheels | C10: =IFERROR(__xludf.DUMMYFUNCTION("""COMPUTED_VALUE"""),"AT9") -> AT9 | D10: =IFERROR(__xludf.DUMMYFUNCTION("""COMPUTED_VALUE"""),"Seat adjuster, power passenger lumbar control") -> Seat adjuster, power passenger lumbar control | F10: 2LT | G10: 3LT
A11: 5DO | B11: LPO, 19" x 8.5" (48.3 cm x 21.6 cm) front and 20" x 11" (50.8 cm x 25.4 cm) rear 15-spoke bright polished aluminum wheels | C11: =IFERROR(__xludf.DUMMYFUNCTION("""COMPUTED_VALUE"""),"B4Z") -> B4Z | D11: =IFERROR(__xludf.DUMMYFUNCTION("""COMPUTED_VALUE"""),"Performance Traction Management") -> Performance Traction Management | H11: FE4
A12: 5JR | B12: LPO, Outside mirror covers in visible Carbon Fiber | C12: =IFERROR(__xludf.DUMMYFUNCTION("""COMPUTED_VALUE"""),"CFX") -> CFX | D12: =IFERROR(__xludf.DUMMYFUNCTION("""COMPUTED_VALUE"""),"Plaque, personalized with Corvette Museum logo") -> Plaque, personalized with Corvette Museum logo | H12: R8C
A13: 5V7 | B13: LPO, Black Ground Effects | C13: =IFERROR(__xludf.DUMMYFUNCTION("""COMPUTED_VALUE"""),"CJ2") -> CJ2 | D13: =IFERROR(__xludf.DUMMYFUNCTION("""COMPUTED_VALUE"""),"Air conditioning, dual-zone automatic climate control") -> Air conditioning, dual-zone automatic climate control | E13: 1LT | F13: 2LT | G13: 3LT
A14: 5ZC | B14: LPO, Jake logo wheel center caps | C14: =IFERROR(__xludf.DUMMYFUNCTION("""COMPUTED_VALUE"""),"DRG") -> DRG | D14: =IFERROR(__xludf.DUMMYFUNCTION("""COMPUTED_VALUE"""),"Mirrors, outside, Carbon Flash Metallic-painted") -> Mirrors, outside, Carbon Flash Metallic-painted | H14: ZYC, 5JR
A15: 5ZD | B15: LPO, Carbon Flash wheel center caps with crossed flags logo | C15: =IFERROR(__xludf.DUMMYFUNCTION("""COMPUTED_VALUE"""),"DRZ") -> DRZ | D15: =IFERROR(__xludf.DUMMYFUNCTION("""COMPUTED_VALUE"""),"Rear Camera Mirror") -> Rear Camera Mirror | E15: 1 | F15: 2 | G15: 3
A16: 5ZU | B16: LPO, High wing spoiler | C16: =IFERROR(__xludf.DUMMYFUNCTION("""COMPUTED_VALUE"""),"DWK") -> DWK | D16: =IFERROR(__xludf.DUMMYFUNCTION("""COMPUTED_VALUE"""),"Mirrors, outside heated, power-adjustable") -> Mirrors, outside heated, power-adjustable | E16: 1
A17: 5ZW | B17: LPO, Two-Stanchion spoiler, Visible Carbon Fiber | C17: =IFERROR(__xludf.DUMMYFUNCTION("""COMPUTED_VALUE"""),"DYX") -> DYX | D17: =IFERROR(__xludf.DUMMYFUNCTION("""COMPUTED_VALUE"""),"Mirrors, outside heated, power-adjustable") -> Mirrors, outside heated, power-adjustable | F17: 2 | G17: 3
A18: 5ZZ | B18: LPO, High wing spoiler, Carbon Flash Metallic-painted | C18: =IFERROR(__xludf.DUMMYFUNCTION("""COMPUTED_VALUE"""),"FE1") -> FE1 | D18: =IFERROR(__xludf.DUMMYFUNCTION("""COMPUTED_VALUE"""),"Suspension, Corvette standard") -> Suspension, Corvette standard
A19: 719 | B19: Seat belt color, Black | C19: =IFERROR(__xludf.DUMMYFUNCTION("""COMPUTED_VALUE"""),"FE3") -> FE3 | D19: =IFERROR(__xludf.DUMMYFUNCTION("""COMPUTED_VALUE"""),"Suspension, Z51 performance") -> Suspension, Z51 performance
A20: A2X | B20: Seat adjuster, driver 8-way power | C20: =IFERROR(__xludf.DUMMYFUNCTION("""COMPUTED_VALUE"""),"FE9") -> FE9 | D20: =IFERROR(__xludf.DUMMYFUNCTION("""COMPUTED_VALUE"""),"Emissions, Federal requirements") -> Emissions, Federal requirements
A21: A7K | B21: Seat adjuster, passenger 8-way power | C21: =IFERROR(__xludf.DUMMYFUNCTION("""COMPUTED_VALUE"""),"G0J") -> G0J | D21: =IFERROR(__xludf.DUMMYFUNCTION("""COMPUTED_VALUE"""),"Differential, mechanical limited-slip") -> Differential, mechanical limited-slip
A22: AE4 | B22: Seats, Competition Sport bucket | C22: =IFERROR(__xludf.DUMMYFUNCTION("""COMPUTED_VALUE"""),"G96") -> G96 | D22: =IFERROR(__xludf.DUMMYFUNCTION("""COMPUTED_VALUE"""),"Differential, electronic limited-slip") -> Differential, electronic limited-slip
A23: AH2 | B23: Seats, GT2 bucket | C23: =IFERROR(__xludf.DUMMYFUNCTION("""COMPUTED_VALUE"""),"GM7") -> GM7 | D23: =IFERROR(__xludf.DUMMYFUNCTION("""COMPUTED_VALUE"""),"Rear axle, performance ratio") -> Rear axle, performance ratio
A24: AHE | B24: Seat adjuster, driver power bolster | C24: =IFERROR(__xludf.DUMMYFUNCTION("""COMPUTED_VALUE"""),"IVE") -> IVE | D24: =IFERROR(__xludf.DUMMYFUNCTION("""COMPUTED_VALUE"""),"NEW! Infotainment system with Google Built-In") -> NEW! Infotainment system with Google Built-In
A25: AHH | B25: Seat adjuster, passenger power bolster | C25: =IFERROR(__xludf.DUMMYFUNCTION("""COMPUTED_VALUE"""),"IWE") -> IWE | D25: =IFERROR(__xludf.DUMMYFUNCTION("""COMPUTED_VALUE"""),"Sueded Microfiber-Wrapped Upper Interior Trim Package") -> Sueded Microfiber-Wrapped Upper Interior Trim Package
A26: AJ7 | B26: Airbags, frontal and side-impact, driver and passenger | C26: =IFERROR(__xludf.DUMMYFUNCTION("""COMPUTED_VALUE"""),"J55") -> J55 | D26: =IFERROR(__xludf.DUMMYFUNCTION("""COMPUTED_VALUE"""),"Brakes, Z51 performance") -> Brakes, Z51 performance
A27: AL9 | B27: Seat adjuster, power driver lumbar control | C27: =IFERROR(__xludf.DUMMYFUNCTION("""COMPUTED_VALUE"""),"JL9") -> JL9 | D27: =IFERROR(__xludf.DUMMYFUNCTION("""COMPUTED_VALUE"""),"Brakes, 4-wheel antilock, 4-wheel disc") -> Brakes, 4-wheel antilock, 4-wheel disc
A28: AP9 | B28: Cargo nets | C28: =IFERROR(__xludf.DUMMYFUNCTION("""COMPUTED_VALUE"""),"K7A") -> K7A | D28: =IFERROR(__xludf.DUMMYFUNCTION("""COMPUTED_VALUE"""),"NEW! Wireless Phone Charging") -> NEW! Wireless Phone Charging
A29: AQ9 | B29: Seats, GT1 bucket | C29: =IFERROR(__xludf.DUMMYFUNCTION("""COMPUTED_VALUE"""),"K7B") -> K7B | D29: =IFERROR(__xludf.DUMMYFUNCTION("""COMPUTED_VALUE"""),"NEW! Wireless Phone Charging") -> NEW! Wireless Phone Charging
A30: AQA | B30: Memory Driver and Passenger Convenience Package | C30: =IFERROR(__xludf.DUMMYFUNCTION("""COMPUTED_VALUE"""),"KI3") -> KI3 | D30: =IFERROR(__xludf.DUMMYFUNCTION("""COMPUTED_VALUE"""),"Steering wheel, heated") -> Steering wheel, heated
A31: AT9 | B31: Seat adjuster, power passenger lumbar control | C31: =IFERROR(__xludf.DUMMYFUNCTION("""COMPUTED_VALUE"""),"KQV") -> KQV | D31: =IFERROR(__xludf.DUMMYFUNCTION("""COMPUTED_VALUE"""),"Seats, heated and vented driver and passenger") -> Seats, heated and vented driver and passenger
A32: AUP | B32: NEW! Seats, mixed, driver Competition Sport bucket, passenger GT2 bucket | C32: =IFERROR(__xludf.DUMMYFUNCTION("""COMPUTED_VALUE"""),"LT2") -> LT2 | D32: =IFERROR(__xludf.DUMMYFUNCTION("""COMPUTED_VALUE"""),"Engine, 6.2L V8 DI") -> Engine, 6.2L V8 DI
A33: B4Z | B33: Performance Traction Management | C33: =IFERROR(__xludf.DUMMYFUNCTION("""COMPUTED_VALUE"""),"M1L") -> M1L | D33: =IFERROR(__xludf.DUMMYFUNCTION("""COMPUTED_VALUE"""),"Transmission, 8-speed dual clutch") -> Transmission, 8-speed dual clutch
A34: B6P | B34: Coupe Engine Appearance Package | C34: =IFERROR(__xludf.DUMMYFUNCTION("""COMPUTED_VALUE"""),"N38") -> N38 | D34: =IFERROR(__xludf.DUMMYFUNCTION("""COMPUTED_VALUE"""),"Steering column, power tilt and telescopic") -> Steering column, power tilt and telescopic
A35: BAZ | B35: Stealth Interior Trim Package | C35: =IFERROR(__xludf.DUMMYFUNCTION("""COMPUTED_VALUE"""),"NB8") -> NB8 | D35: =IFERROR(__xludf.DUMMYFUNCTION("""COMPUTED_VALUE"""),"Emissions override, California ") -> Emissions override, California
A36: BC7 | B36: LT2 engine cover | C36: =IFERROR(__xludf.DUMMYFUNCTION("""COMPUTED_VALUE"""),"NB9") -> NB9 | D36: =IFERROR(__xludf.DUMMYFUNCTION("""COMPUTED_VALUE"""),"Emissions override, state-specific") -> Emissions override, state-specific
A37: BCP | B37: LT2 engine cover | C37: =IFERROR(__xludf.DUMMYFUNCTION("""COMPUTED_VALUE"""),"NC7") -> NC7 | D37: =IFERROR(__xludf.DUMMYFUNCTION("""COMPUTED_VALUE"""),"Emissions override, Federal") -> Emissions override, Federal
A38: BCS | B38: LT2 engine cover | C38: =IFERROR(__xludf.DUMMYFUNCTION("""COMPUTED_VALUE"""),"NE1") -> NE1 | D38: =IFERROR(__xludf.DUMMYFUNCTION("""COMPUTED_VALUE"""),"Emissions") -> Emissions
A39: BV4 | B39: Plaque, personalized | C39: =IFERROR(__xludf.DUMMYFUNCTION("""COMPUTED_VALUE"""),"NK4") -> NK4 | D39: =IFERROR(__xludf.DUMMYFUNCTION("""COMPUTED_VALUE"""),"Steering wheel, leather-wrapped") -> Steering wheel, leather-wrapped
A40: C2Z | B40: Roof panel, visible carbon fiber with body-color surround | C40: =IFERROR(__xludf.DUMMYFUNCTION("""COMPUTED_VALUE"""),"P0H") -> P0H | D40: =IFERROR(__xludf.DUMMYFUNCTION("""COMPUTED_VALUE"""),"12 Months OnStar Connect Plus") -> 12 Months OnStar Connect Plus
A41: CAV | B41: LPO, Contoured cargo area liners with Jake logo | C41: =IFERROR(__xludf.DUMMYFUNCTION("""COMPUTED_VALUE"""),"P0I") -> P0I | D41: =IFERROR(__xludf.DUMMYFUNCTION("""COMPUTED_VALUE"""),"24 Months OnStar Connect Plus") -> 24 Months OnStar Connect Plus
A42: CC3 | B42: Roof panel, transparent, removable | C42: =IFERROR(__xludf.DUMMYFUNCTION("""COMPUTED_VALUE"""),"P0J") -> P0J | D42: =IFERROR(__xludf.DUMMYFUNCTION("""COMPUTED_VALUE"""),"24 Months OnStar Protect") -> 24 Months OnStar Protect
A43: CF7 | B43: Roof panel, body-color, removable | C43: =IFERROR(__xludf.DUMMYFUNCTION("""COMPUTED_VALUE"""),"P0K") -> P0K | D43: =IFERROR(__xludf.DUMMYFUNCTION("""COMPUTED_VALUE"""),"36 Months OnStar Protect") -> 36 Months OnStar Protect
A44: CF8 | B44: NEW! Roof panel, electrochromic dimming | C44: =IFERROR(__xludf.DUMMYFUNCTION("""COMPUTED_VALUE"""),"P0L") -> P0L | D44: =IFERROR(__xludf.DUMMYFUNCTION("""COMPUTED_VALUE"""),"48 Months OnStar Protect") -> 48 Months OnStar Protect
A45: CFX | B45: Plaque, personalized with Corvette Museum logo | C45: =IFERROR(__xludf.DUMMYFUNCTION("""COMPUTED_VALUE"""),"P0Q") -> P0Q | D45: =IFERROR(__xludf.DUMMYFUNCTION("""COMPUTED_VALUE"""),"60 Months OnStar Protect") -> 60 Months OnStar Protect
A46: CJ2 | B46: Air conditioning, dual-zone automatic climate control | C46: =IFERROR(__xludf.DUMMYFUNCTION("""COMPUTED_VALUE"""),"P0U") -> P0U | D46: =IFERROR(__xludf.DUMMYFUNCTION("""COMPUTED_VALUE"""),"12 Months OnStar Protect") -> 12 Months OnStar Protect
A47: CM9 | B47: Convertible top, retractable | C47: =IFERROR(__xludf.DUMMYFUNCTION("""COMPUTED_VALUE"""),"P0V") -> P0V | D47: =IFERROR(__xludf.DUMMYFUNCTION("""COMPUTED_VALUE"""),"12 Months OnStar Telematics") -> 12 Months OnStar Telematics
A48: D30 | B48: Color Combination Override | C48: =IFERROR(__xludf.DUMMYFUNCTION("""COMPUTED_VALUE"""),"P0W") -> P0W | D48: =IFERROR(__xludf.DUMMYFUNCTION("""COMPUTED_VALUE"""),"24 Months OnStar Telematics ") -> 24 Months OnStar Telematics
A49: D3V | B49: Engine lighting | C49: =IFERROR(__xludf.DUMMYFUNCTION("""COMPUTED_VALUE"""),"P0X") -> P0X | D49: =IFERROR(__xludf.DUMMYFUNCTION("""COMPUTED_VALUE"""),"36 Months OnStar Telematics") -> 36 Months OnStar Telematics
A50: D84 | B50: Convertible top, Carbon Flash-painted nacelles and roof | C50: =IFERROR(__xludf.DUMMYFUNCTION("""COMPUTED_VALUE"""),"P0Y") -> P0Y | D50: =IFERROR(__xludf.DUMMYFUNCTION("""COMPUTED_VALUE"""),"48 Months OnStar Telematics") -> 48 Months OnStar Telematics
A51: D86 | B51: Convertible top, Carbon Flash-painted nacelles and body-color roof | C51: =IFERROR(__xludf.DUMMYFUNCTION("""COMPUTED_VALUE"""),"P0Z") -> P0Z | D51: =IFERROR(__xludf.DUMMYFUNCTION("""COMPUTED_VALUE"""),"60 Months OnStar Telematics") -> 60 Months OnStar Telematics
A52: DPB | B52: Carbon Flash with Blue accent Full Length Dual Racing Stripes | C52: =IFERROR(__xludf.DUMMYFUNCTION("""COMPUTED_VALUE"""),"PPW") -> PPW | D52: =IFERROR(__xludf.DUMMYFUNCTION("""COMPUTED_VALUE"""),"Wireless Apple CarPlay/Wireless Android Auto") -> Wireless Apple CarPlay/Wireless Android Auto
A53: DPC | B53: Carbon Flash with Yellow accent Full Length Dual Racing Stripes | C53: =IFERROR(__xludf.DUMMYFUNCTION("""COMPUTED_VALUE"""),"PQG") -> PQG | D53: =IFERROR(__xludf.DUMMYFUNCTION("""COMPUTED_VALUE"""),"36 Months OnStar Connect Plus") -> 36 Months OnStar Connect Plus
A54: DPG | B54: Carbon Flash with Orange accent Full Length Dual Racing Stripes | C54: =IFERROR(__xludf.DUMMYFUNCTION("""COMPUTED_VALUE"""),"PQH") -> PQH | D54: =IFERROR(__xludf.DUMMYFUNCTION("""COMPUTED_VALUE"""),"48 Months OnStar Connect Plus") -> 48 Months OnStar Connect Plus
A55: DPL | B55: Carbon Flash with Red accent Full Length Dual Racing Stripes | C55: =IFERROR(__xludf.DUMMYFUNCTION("""COMPUTED_VALUE"""),"PQI") -> PQI | D55: =IFERROR(__xludf.DUMMYFUNCTION("""COMPUTED_VALUE"""),"60 Months OnStar Connect Plus") -> 60 Months OnStar Connect Plus
A56: DPT | B56: Carbon Flash with Silver accent Full Length Dual Racing Stripes | C56: =IFERROR(__xludf.DUMMYFUNCTION("""COMPUTED_VALUE"""),"PRB") -> PRB | D56: =IFERROR(__xludf.DUMMYFUNCTION("""COMPUTED_VALUE"""),"3 Years OnStar One") -> 3 Years OnStar One
A57: DRG | B57: Mirrors, outside, Carbon Flash Metallic-painted | C57: =IFERROR(__xludf.DUMMYFUNCTION("""COMPUTED_VALUE"""),"QUD") -> QUD | D57: =IFERROR(__xludf.DUMMYFUNCTION("""COMPUTED_VALUE"""),"Tires, 245/35ZR19 front and 305/30ZR20 rear, blackwall, high performance") -> Tires, 245/35ZR19 front and 305/30ZR20 rear, blackwall, high performance
A58: DRZ | B58: Rear Camera Mirror | C58: =IFERROR(__xludf.DUMMYFUNCTION("""COMPUTED_VALUE"""),"R6P") -> R6P | D58: =IFERROR(__xludf.DUMMYFUNCTION("""COMPUTED_VALUE"""),"3 Years SiriusXM") -> 3 Years SiriusXM
A59: DSY | B59: Edge Orange Full Length Dual Racing Stripes | C59: =IFERROR(__xludf.DUMMYFUNCTION("""COMPUTED_VALUE"""),"R6X") -> R6X | D59: =IFERROR(__xludf.DUMMYFUNCTION("""COMPUTED_VALUE"""),"Custom Interior Trim and Seat Combination") -> Custom Interior Trim and Seat Combination
A60: DSZ | B60: Edge Red Full Length Dual Racing Stripes | C60: =IFERROR(__xludf.DUMMYFUNCTION("""COMPUTED_VALUE"""),"R8G") -> R8G | D60: =IFERROR(__xludf.DUMMYFUNCTION("""COMPUTED_VALUE"""),"12 Months OnStar One Fleet") -> 12 Months OnStar One Fleet
A61: DT0 | B61: Competition Yellow Full Length Dual Racing Stripes | C61: =IFERROR(__xludf.DUMMYFUNCTION("""COMPUTED_VALUE"""),"R8P") -> R8P | D61: =IFERROR(__xludf.DUMMYFUNCTION("""COMPUTED_VALUE"""),"36 Months OnStar One Fleet") -> 36 Months OnStar One Fleet
A62: DTH | B62: Carbon Flash Metallic Full Length Dual Racing Stripes | C62: =IFERROR(__xludf.DUMMYFUNCTION("""COMPUTED_VALUE"""),"R8W") -> R8W | D62: =IFERROR(__xludf.DUMMYFUNCTION("""COMPUTED_VALUE"""),"60 Months OnStar One Fleet") -> 60 Months OnStar One Fleet
A63: DUB | B63: Sterling Silver Full Length Dual Racing Stripes | C63: =IFERROR(__xludf.DUMMYFUNCTION("""COMPUTED_VALUE"""),"R8Z") -> R8Z | D63: =IFERROR(__xludf.DUMMYFUNCTION("""COMPUTED_VALUE"""),"48 Months OnStar One Fleet") -> 48 Months OnStar One Fleet
A64: DUK | B64: NEW! Asymmetrical Adrenaline Red/Carbon Flash Full Length Dual Racing Stripes | C64: =IFERROR(__xludf.DUMMYFUNCTION("""COMPUTED_VALUE"""),"R9L") -> R9L | D64: =IFERROR(__xludf.DUMMYFUNCTION("""COMPUTED_VALUE"""),"Removes OnStar Basics (OnStar Fleet Basics for Fleet)") -> Removes OnStar Basics (OnStar Fleet Basics for Fleet)
A65: DUW | B65: Edge Blue Full Length Dual Racing Stripes | C65: =IFERROR(__xludf.DUMMYFUNCTION("""COMPUTED_VALUE"""),"R9V") -> R9V | D65: =IFERROR(__xludf.DUMMYFUNCTION("""COMPUTED_VALUE"""),"Mobile Service Plus") -> Mobile Service Plus
A66: DWK | B66: Mirrors, outside heated, power-adjustable | C66: =IFERROR(__xludf.DUMMYFUNCTION("""COMPUTED_VALUE"""),"R9W") -> R9W | D66: =IFERROR(__xludf.DUMMYFUNCTION("""COMPUTED_VALUE"""),"Deleted Mobile Service Plus") -> Deleted Mobile Service Plus
A67: DYX | B67: Mirrors, outside heated, power-adjustable | C67: =IFERROR(__xludf.DUMMYFUNCTION("""COMPUTED_VALUE"""),"R9Y") -> R9Y | D67: =IFERROR(__xludf.DUMMYFUNCTION("""COMPUTED_VALUE"""),"Mobile Service Plus") -> Mobile Service Plus
A68: DZU | B68: Carbon Flash/Competition Yellow Stinger Stripe | C68: =IFERROR(__xludf.DUMMYFUNCTION("""COMPUTED_VALUE"""),"RFH") -> RFH | D68: =IFERROR(__xludf.DUMMYFUNCTION("""COMPUTED_VALUE"""),"24 Months OnStar One Fleet") -> 24 Months OnStar One Fleet
A69: DZV | B69: Carbon Flash/Midnight Silver Stinger Stripe | C69: =IFERROR(__xludf.DUMMYFUNCTION("""COMPUTED_VALUE"""),"T4L") -> T4L | D69: =IFERROR(__xludf.DUMMYFUNCTION("""COMPUTED_VALUE"""),"Headlamps, LED") -> Headlamps, LED
A70: DZX | B70: Carbon Flash/Edge Red Stinger Stripe | C70: =IFERROR(__xludf.DUMMYFUNCTION("""COMPUTED_VALUE"""),"TDM") -> TDM | D70: =IFERROR(__xludf.DUMMYFUNCTION("""COMPUTED_VALUE"""),"Teen Driver") -> Teen Driver
A71: E60 | B71: Front lift adjustable height | C71: =IFERROR(__xludf.DUMMYFUNCTION("""COMPUTED_VALUE"""),"TQ5") -> TQ5 | D71: =IFERROR(__xludf.DUMMYFUNCTION("""COMPUTED_VALUE"""),"IntelliBeam") -> IntelliBeam
A72: EFR | B72: Exterior accents, Carbon Flash | C72: =IFERROR(__xludf.DUMMYFUNCTION("""COMPUTED_VALUE"""),"TR7") -> TR7 | D72: =IFERROR(__xludf.DUMMYFUNCTION("""COMPUTED_VALUE"""),"Headlamp control, automatic leveling system") -> Headlamp control, automatic leveling system
A73: EFY | B73: Exterior accents, body-color | C73: =IFERROR(__xludf.DUMMYFUNCTION("""COMPUTED_VALUE"""),"U2K") -> U2K | D73: =IFERROR(__xludf.DUMMYFUNCTION("""COMPUTED_VALUE"""),"SiriusXM with 360L") -> SiriusXM with 360L
A74: ERI | B74: Battery Protection Package | C74: =IFERROR(__xludf.DUMMYFUNCTION("""COMPUTED_VALUE"""),"U5G") -> U5G | D74: =IFERROR(__xludf.DUMMYFUNCTION("""COMPUTED_VALUE"""),"NEW! 5G vehicle connectivity") -> NEW! 5G vehicle connectivity
A75: EYK | B75: Chrome Exterior Badge Package | C75: =IFERROR(__xludf.DUMMYFUNCTION("""COMPUTED_VALUE"""),"U80") -> U80 | D75: =IFERROR(__xludf.DUMMYFUNCTION("""COMPUTED_VALUE"""),"Compass, digital") -> Compass, digital
A76: EYT | B76: Carbon Flash Exterior Badge Package | C76: =IFERROR(__xludf.DUMMYFUNCTION("""COMPUTED_VALUE"""),"UD7") -> UD7 | D76: =IFERROR(__xludf.DUMMYFUNCTION("""COMPUTED_VALUE"""),"Rear Park Assist") -> Rear Park Assist
A77: FA5 | B77: Trim, interior | C77: =IFERROR(__xludf.DUMMYFUNCTION("""COMPUTED_VALUE"""),"UE1") -> UE1 | D77: =IFERROR(__xludf.DUMMYFUNCTION("""COMPUTED_VALUE"""),"OnStar services capable") -> OnStar services capable
A78: FE1 | B78: Suspension, Corvette standard | C78: =IFERROR(__xludf.DUMMYFUNCTION("""COMPUTED_VALUE"""),"UEU") -> UEU | D78: =IFERROR(__xludf.DUMMYFUNCTION("""COMPUTED_VALUE"""),"Forward Collision Alert") -> Forward Collision Alert
A79: FE2 | B79: Suspension, Magnetic Selective Ride Control | C79: =IFERROR(__xludf.DUMMYFUNCTION("""COMPUTED_VALUE"""),"UFG") -> UFG | D79: =IFERROR(__xludf.DUMMYFUNCTION("""COMPUTED_VALUE"""),"Rear Cross Traffic Alert") -> Rear Cross Traffic Alert
A80: FE3 | B80: Suspension, Z51 performance | C80: =IFERROR(__xludf.DUMMYFUNCTION("""COMPUTED_VALUE"""),"UFT") -> UFT | D80: =IFERROR(__xludf.DUMMYFUNCTION("""COMPUTED_VALUE"""),"Side Blind Zone Alert") -> Side Blind Zone Alert
A81: FE4 | B81: Suspension, Z51 performance with Magnetic Selective Ride Control | C81: =IFERROR(__xludf.DUMMYFUNCTION("""COMPUTED_VALUE"""),"UG1") -> UG1 | D81: =IFERROR(__xludf.DUMMYFUNCTION("""COMPUTED_VALUE"""),"Universal Home Remote") -> Universal Home Remote
A82: FE9 | B82: Emissions, Federal requirements | C82: =IFERROR(__xludf.DUMMYFUNCTION("""COMPUTED_VALUE"""),"UHX") -> UHX | D82: =IFERROR(__xludf.DUMMYFUNCTION("""COMPUTED_VALUE"""),"Lane Keep Assist with Lane Departure Warning") -> Lane Keep Assist with Lane Departure Warning
A83: G0J | B83: Differential, mechanical limited-slip | C83: =IFERROR(__xludf.DUMMYFUNCTION("""COMPUTED_VALUE"""),"UHY") -> UHY | D83: =IFERROR(__xludf.DUMMYFUNCTION("""COMPUTED_VALUE"""),"Automatic Emergency Braking") -> Automatic Emergency Braking
A84: G96 | B84: Differential, electronic limited-slip | C84: =IFERROR(__xludf.DUMMYFUNCTION("""COMPUTED_VALUE"""),"UKT") -> UKT | D84: =IFERROR(__xludf.DUMMYFUNCTION("""COMPUTED_VALUE"""),"Front Pedestrian and Bicyclist Braking") -> Front Pedestrian and Bicyclist Braking
A85: GM7 | B85: Rear axle, performance ratio | C85: =IFERROR(__xludf.DUMMYFUNCTION("""COMPUTED_VALUE"""),"UQH") -> UQH | D85: =IFERROR(__xludf.DUMMYFUNCTION("""COMPUTED_VALUE"""),"Audio system feature, Bose Performance Series Sound System") -> Audio system feature, Bose Performance Series Sound System
A86: IVE | B86: NEW! Infotainment system with Google Built-In | C86: =IFERROR(__xludf.DUMMYFUNCTION("""COMPUTED_VALUE"""),"UQS") -> UQS | D86: =IFERROR(__xludf.DUMMYFUNCTION("""COMPUTED_VALUE"""),"Audio system feature, Bose Premium 10-speaker system") -> Audio system feature, Bose Premium 10-speaker system
A87: IWE | B87: Sueded Microfiber-Wrapped Upper Interior Trim Package | C87: =IFERROR(__xludf.DUMMYFUNCTION("""COMPUTED_VALUE"""),"UTJ") -> UTJ | D87: =IFERROR(__xludf.DUMMYFUNCTION("""COMPUTED_VALUE"""),"Theft-deterrent system") -> Theft-deterrent system
A88: J55 | B88: Brakes, Z51 performance | C88: =IFERROR(__xludf.DUMMYFUNCTION("""COMPUTED_VALUE"""),"UTU") -> UTU | D88: =IFERROR(__xludf.DUMMYFUNCTION("""COMPUTED_VALUE"""),"Theft deterrent sensor, vehicle inclination") -> Theft deterrent sensor, vehicle inclination
A89: J6A | B89: Calipers, Black | C89: =IFERROR(__xludf.DUMMYFUNCTION("""COMPUTED_VALUE"""),"UTV") -> UTV | D89: =IFERROR(__xludf.DUMMYFUNCTION("""COMPUTED_VALUE"""),"Theft deterrent sensor, vehicle interior movement") -> Theft deterrent sensor, vehicle interior movement
A90: J6E | B90: Calipers, Velocity Yellow | C90: =IFERROR(__xludf.DUMMYFUNCTION("""COMPUTED_VALUE"""),"UV6") -> UV6 | D90: =IFERROR(__xludf.DUMMYFUNCTION("""COMPUTED_VALUE"""),"Head-Up Display") -> Head-Up Display
A91: J6F | B91: Calipers, Bright Red | C91: =IFERROR(__xludf.DUMMYFUNCTION("""COMPUTED_VALUE"""),"UVA") -> UVA | D91: =IFERROR(__xludf.DUMMYFUNCTION("""COMPUTED_VALUE"""),"HD Front and Rear Vision Cameras") -> HD Front and Rear Vision Cameras
A92: J6N | B92: Calipers, Edge Red | C92: =IFERROR(__xludf.DUMMYFUNCTION("""COMPUTED_VALUE"""),"UVB") -> UVB | D92: =IFERROR(__xludf.DUMMYFUNCTION("""COMPUTED_VALUE"""),"HD Rear Vision Camera") -> HD Rear Vision Camera
A93: JL9 | B93: Brakes, 4-wheel antilock, 4-wheel disc | C93: =IFERROR(__xludf.DUMMYFUNCTION("""COMPUTED_VALUE"""),"V08") -> V08 | D93: =IFERROR(__xludf.DUMMYFUNCTION("""COMPUTED_VALUE"""),"Cooling system, heavy-duty") -> Cooling system, heavy-duty
A94: K7A | B94: NEW! Wireless Phone Charging | C94: =IFERROR(__xludf.DUMMYFUNCTION("""COMPUTED_VALUE"""),"VHM") -> VHM | D94: =IFERROR(__xludf.DUMMYFUNCTION("""COMPUTED_VALUE"""),"Vehicle health management") -> Vehicle health management
A95: K7B | B95: NEW! Wireless Phone Charging | C95: =IFERROR(__xludf.DUMMYFUNCTION("""COMPUTED_VALUE"""),"VV4") -> VV4 | D95: =IFERROR(__xludf.DUMMYFUNCTION("""COMPUTED_VALUE"""),"Wi-Fi Hotspot capable") -> Wi-Fi Hotspot capable
A96: KI3 | B96: Steering wheel, heated | C96: =IFERROR(__xludf.DUMMYFUNCTION("""COMPUTED_VALUE"""),"XFN") -> XFN | D96: =IFERROR(__xludf.DUMMYFUNCTION("""COMPUTED_VALUE"""),"Tires, 245/35ZR19 front and 305/30ZR20 rear, blackwall, all-season, performance") -> Tires, 245/35ZR19 front and 305/30ZR20 rear, blackwall, all-season, performance
A97: KQV | B97: Seats, heated and vented driver and passenger | C97: =IFERROR(__xludf.DUMMYFUNCTION("""COMPUTED_VALUE"""),"YF5") -> YF5 | D97: =IFERROR(__xludf.DUMMYFUNCTION("""COMPUTED_VALUE"""),"Emissions, California state requirements") -> Emissions, California state requirements
A98: LT2 | B98: Engine, 6.2L V8 DI
A99: M1L | B99: Transmission, 8-speed dual clutch
A100: N26 | B100: Steering wheel, sueded microfiber-wrapped
...

Sheet ERAY
A1: RPO Code | B1: Name | C1: Price | D1: Detail | E1: Compatibility | F1: Category | G1: Section
A2: EFR | B2: Carbon Flash exterior accents | C2: 0 | D2: Standard Carbon Flash. Includes side vents and front/rear grille accents. Includes tonneau vent on convertible. Includes rockers on E-Ray and Z06 | F2: accents | G2: Accents
A3: EFY-e | B3: Body Color exterior accents | C3: 0 | D3: Standard. Includes side vents, rockers, and front/rear grille accents. Includes tonneau vent on convertible. | F3: accents | G3: Accents
A4: EYK | B4: Chrome Exterior Badge Package | C4: 295 | D4: Includes badges on the nose and decklid, "Corvette" script on rear, and lower rocker badge on wide-body models. | F4: badges | G4: Badges
A5: EYT | B5: Carbon Flash Exterior Badge Package | C5: 0 | D5: Standard. Includes badges on the nose and decklid, "Corvette" script on rear, and lower rocker badge on wide-body models. | F5: badges | G5: Badges
A6: J6B | B6: Blue Painted Calipers | C6: 695 | D6: Requires J57 Ceramic brakes | E6: Requires J57 Ceramic brakes | F6: calipers | G6: Brake Calipers
A7: J6D | B7: Dark Gray metallic Painted Calipers | C7: 0 | D7: Standard with J57, Requires J57 Ceramic brakes | E7: Requires J57 Ceramic brakes | F7: calipers | G7: Brake Calipers
A8: J6E | B8: Velocity Yellow Painted Calipers | C8: 695 | D8: Gloss finish | F8: calipers | G8: Brake Calipers
A9: J6F | B9: Bright Red Painted Calipers | C9: 695 | D9: Gloss finish | F9: calipers | G9: Brake Calipers
A10: J6L | B10: Orange Painted Calipers | C10: 695 | D10: Requires J57 Ceramic brakes | E10: Requires J57 Ceramic brakes | F10: calipers | G10: Brake Calipers
A11: J6N | B11: Edge Red Painted Calipers | C11: 695 | D11: Darker shade of red, satin finish | F11: calipers | G11: Brake Calipers
A12: RWH | B12: Premium Indoor car cover, Black with crossed flags logo | C12: 495 | F12: lpo | G12: Car Covers
A13: RWJ | B13: LPO, Premium outdoor car cover, Gray with crossed flags logo and Corvette silhouette | C13: 495 | F13: lpo | G13: Car Covers
A14: WKR | B14: NEW! LPO, Premium indoor car cover, GT3.R, fully rendered | C14: 495 | F14: lpo | G14: Car Covers
A15: 5JR | B15: Visible Carbon Fiber Mirror Covers | C15: 1250 | D15: 3LT/LZ only. Adds DRG carbon flash painted mirrors (N/C) | E15: 3LT/LZ only. Available with 1LZ on ZR1. | F15: carbon_fiber, lpo | G15: Carbon Fiber
A16: CFV | B16: Carbon Fiber Ground Effects- Visible Carbon weave | C16: 3995 | D16: Included with T0G | F16: carbon_fiber, lpo | G16: Carbon Fiber
A17: CFZ | B17: Carbon Fiber Ground Effects- Carbon Flash metallic Painted | C17: 2995 | D17: Included with T0F | F17: carbon_fiber, lpo | G17: Carbon Fiber
A18: SLN | B18: Visible Carbon Fiber Engine Cross Brace w/ Jake Logo | C18: 2895 | D18: Not available with RXI | E18: Not available with RXI | F18: carbon_fiber, engine_bay, lpo | G18: Carbon Fiber
A19: V8X | B19: Visible Carbon Fiber Sill Plates | C19: 1995 | D19: Corvette Script and sillhouette logo | F19: carbon_fiber, lpo | G19: Carbon Fiber
A20: CM9 | B20: Body-Color roof and nacelles | C20: 0 | D20: Standard | F20: roof | G20: Convertible Roof Panel
A21: D84 | B21: Carbon Flash painted nacelles and roof | C21: 1295 | D21: Not available w/ GBA Black | E21: Not available w/ GBA Black | F21: roof | G21: Convertible Roof Panel
A22: D86 | B22: Carbon Flash painted nacelles and body color roof | C22: 1295 | D22: Not available w/ GBA Black | E22: Not available w/ GBA Black | F22: roof | G22: Convertible Roof Panel
A23: C2Z | B23: Visible Carbon Fiber weave w/body color border roof panel | C23: 2495 | F23: roof, carbon_fiber | G23: Coupe Roof Panel
A24: CC3 | B24: Transparent Glass roof panel | C24: 995 | F24: roof | G24: Coupe Roof Panel
A25: CF7 | B25: Body-Color Carbon Roof panel | C25: 0 | D25: Standard | F25: roof | G25: Coupe Roof Panel
A26: CF8 | B26: Electrochromic Dimming Roof Panel | C26: 3000 | D26: Electrochromic dimming, removable. | E26: Not available on 1LT, 1LZ. Not available with any Full Length Dual Racing Stripes (DPB, DPC, DPG, DPL, DPT, DSY, DSZ, DT0, DTB, DTH, DUB, DUK, DUW). | F26: roof | G26: Coupe Roof Panel
A27: SBT | B27: LPO, Dual Roof, adds clear roof and storage bag. | C27: 2350 | D27: Adds Transparent glass panel CC3 and Roof panel storage bag SC7 | F27: roof, lpo | G27: Coupe Roof Panel
A28: BV4 | B28: Plaque, personalized, custom-made with your name and VIN | C28: 295 | D28: Personalized plaque is included in museum delivery R8C, Plaque is located between the seats on the speaker grille. | F28: customdelivery | G28: Custom Delivery
A29: PIN | B29: Customer selectable VIN ending* | C29: 5000 | D29: This option is subject to restrictions and approval. | F29: customdelivery | G29: Custom Delivery
A30: R8C | B30: Corvette Museum Delivery | C30: 1495 | D30: Guided VIP tour of the Corvette Assembly Plant (when available) for customer and 3 guests, Guided VIP tour of the NCM where the owner will see their Corvette on display, Quality, detailed orientation of the car by Delivery Team Guide, Celebratory drive out of the Museum (complimentary SD card to record for those with PDR), Unique gold RSC decal placed on the inside of the driver's door jamb, Custom interior dash plaque, Individual one-year NCM membership, Commemorative wall plaque with nameplate (customer's name, date of delivery, VIN#), Opportunity to purchase exclusive apparel, bricks and build sheet, Delivery can be viewed world-wide via our live webcams, Photos of the customer with the car (shared via email) | F30: customdelivery | G30: Custom Delivery
A31: B6P | B31: Coupe Engine Appearance Package | C31: 1695 | D31: Includes Carbon Fiber Trim, D3V Engine Bay Lights, and SL9 Engine Specification Plaque | F31: engine_bay, carbon_fiber | G31: Engine Appearance
A32: BC7 | B32: LT2 Engine Cover, Black | C32: 0 | D32: Standard on Coupe. Includes metal Corvette nameplate | E32: Requires ZZ3 Engine appearance package on Convertible. | F32: engine_bay | G32: Engine Appearance
A33: BCP | B33: LPO, Engine Cover in Edge Red | C33: 495 | E33: When equipped with B6P on Coupe. Requires ZZ3 Engine appearance package on Convertible. | F33: engine_bay, lpo | G33: Engine Appearance
A34: BCP-s | B34: LPO, Engine Cover in Edge Red | C34: 595 | D34: Includes D3V Engine Bay Lights on Coupe. | E34: Not Equipped with B6P. Requires ZZ3 Engine appearance package on Convertible. | F34: engine_bay, lpo | G34: Engine Appearance
A35: BCS | B35: LPO, Engine Cover in Sterling Silver | C35: 495 | D35: Silver with metal Corvette nameplate. | E35: When equipped with B6P on Coupe. Requires ZZ3 Engine appearance package on Convertible. | F35: engine_bay, lpo | G35: Engine Appearance
A36: BCS-s | B36: LPO, Engine Cover in Sterling Silver | C36: 595 | D36: Includes D3V Engine Bay Lights on Coupe. | E36: Not Equipped with B6P. Requires ZZ3 Engine appearance package on Convertible. | F36: engine_bay, lpo | G36: Engine Appearance
A37: D3V | B37: Engine Bay, Lights only | C37: 100 | D37: Coupe Only. Included with BCP, BCS, B6P, BCW. | F37: engine_bay | G37: Engine Appearance
A38: SL9 | B38: Engine Specification Plaque | C38: 95 | D38: Included with B6P/ZZ3 Engine Appearance Package new | F38: engine_bay | G38: Engine Appearance
A39: SLK | B39: Red Strut Bracket | C39: 1995 | D39: Coupe only. LPO | F39: engine_bay, lpo | G39: Engine Appearance
A40: VUP | B40: Engine Bay Closeout Graphics | C40: 570 | D40: Coupe only. LPO | F40: lpo, engine_bay | G40: Engine Appearance
A41: ZZ3 | B41: Convertible Engine Appearance Package | C41: 1095 | D41: Includes window under tonneau cover, Black engine cover and (SL9) engine specification plaque. | F41: engine_bay, carbon_fiber | G41: Engine Appearance
A42: R88 | B42: NEW! LPO, Illuminated crossed flags emblem | C42: 475 | D42: Not available at the start of production | E42: Not available with (SFZ) Dark Stealth crossed flags emblems, LPO, (EYK) Chrome Exterior Badge Package or any Full Length Dual Racing Stripes (DPB, DPC, DPG, DPL, DPT, DSY, DSZ, DT0, DTB, DTH, DUB, DUK, DUK, DUW). | F42: lpo | G42: Exterior Accessories
A43: RIK | B43: Rear Corvette Script, Torch Red | C43: 425 | D43: Not available with SL8, RIN | E43: Not available with SL8, RIN | F43: lpo | G43: Exterior Accessories
A44: RIN | B44: Rear Corvette Script, Arctic White | C44: 395 | D44: Not available with SL8, RIK | E44: Not available with SL8, RIK | F44: lpo | G44: Exterior Accessories
A45: SC7 | B45: Roof panel storage pouch | C45: 195 | D45: Included with SBT. Coupe Only. Keeps roof panel protected when storing OUTSIDE of car. Can NOT store roof panel in pouch and put in rear trunk; damage can occur to the roof panel and trunk lid. | F45: lpo | G45: Exterior Accessories
A46: SDA | B46: Black recovery hook | C46: 125 | F46: lpo | G46: Exterior Accessories
A47: SFZ | B47: Dark Stealth crossed flags emblem | C47: 275 | D47: Not available with EYK Chrome Exterior Badge Package or any Full Length Dual Racing Stripes DPB, DPC, DPG, DPL, DPT, DSY, DSZ, DT0, DTB, DTH, DUB, DUW, Included with PCX/PCZ Tech Bronze Accent Package, LPO. | E47: Not available with EYK Chrome Exterior Badge Package or any Full Length Dual Racing Stripes DPB, DPC, DPG, DPL, DPT, DSY, DSZ, DT0, DTB, DTH, DUB, DUW, Included with PCX/PCZ Tech Bronze Accent Package, LPO. | F47: lpo | G47: Exterior Accessories
A48: SIG | B48: LPO, Spoiler Extension, clear smoked center bridge w/ Jake Logo | C48: 425 | D48: Requires T0E rear spoiler (Standard spoiler) | E48: Requires T0E rear spoiler (Standard spoiler) | F48: spoilers, lpo | G48: Exterior Accessories
A49: SL8 | B49: Rear Corvette Script, Edge Red | C49: 395 | D49: Not available with RIK, RIN | E49: Not available with RIK, RIN | F49: lpo | G49: Exterior Accessories
A50: SUF | B50: Eray Badge in Blue | C50: 275 | F50: lpo | G50: Exterior Accessories
A51: VK3 | B51: License Plate Bracket, Front | C51: 40 | D51: (Auto Shipped to Required States) | F51: lpo | G51: Exterior Accessories
A52: VWE-z | B52: Front radiator grille guards | C52: 650 | F52: lpo | G52: Exterior Accessories
A53: CAV | B53: Contoured Cargo Area Liners w/ Jake logo | C53: 195 | D53: Included w/PEF. Stingray and Z06 include both cargo areas. E-Ray and ZR1 rear trunk only | F53: lpo | G53: Interior Accessories
A54: RIA | B54: All Weather floor liner w/ Jake logo | C54: 265 | D54: Included w/PEF | F54: lpo | G54: Interior Accessories
A55: RWU | B55: Cargo Area Organizer, collapsible | C55: 175 | F55: lpo | G55: Interior Accessories
A56: RYT | B56: First Aid Kit, Genuine Corvette Accessory | C56: 60 | D56: Included in PDY | F56: lpo | G56: Interior Accessories
A57: S08 | B57: Highway Safety Kit, Genuine Corvette Accessory | C57: 150 | D57: Included in PDY | F57: lpo | G57: Interior Accessories
A58: S2L | B58: Premium Leather weekend travel bags | C58: 1695 | D58: Set of 2 | F58: lpo | G58: Interior Accessories
A59: VTB | B59: Rear Fascia/roof storage protector Black w/ Crossed flags logo | C59: 150 | F59: lpo | G59: Interior Accessories
A60: VYW | B60: Premium Floor mats, carpeted w/ Car silhouette logo | C60: 298 | D60: Z06 has Z06 logo instead of Car silhouette. | F60: lpo | G60: Interior Accessories
A61: W2D | B61: Cargo net set | C61: 95 | D61: 1LT/LZ only | E61: 1LT 1LZ only | F61: lpo | G61: Interior Accessories
A62: PDA | B62: Jake C8.R Graphics Package | C62: 925 | D62: Includes SNE Jake hood graphic, LPO and VPW Jake C8.R rear hash graphic, LPO, Genuine Corvette Accessories | F62: lpo, stripes | G62: LPO Packages
A63: PDY | B63: Roadside Safety Package | C63: 195 | D63: Includes First Aid Kit RYT and Highway Safety Kit S08 | F63: lpo | G63: LPO Packages
A64: PEF | B64: Contoured Liner Protection Package | C64: 475 | D64: Includes RIA and CAV | E64: Not available with RIA or CAV | F64: lpo | G64: LPO Packages
A65: E60 | B65: Front lift adjustable height w/ memory | C65: 2595 | D65: 2LT/Z or 3LT/Z trim level only | E65: 2LT/Z or 3LT/Z trim level only | F65: mechanical | G65: Mechanical
A66: ERI | B66: Battery Protection Package | C66: 100 | D66: Battery tender used to keep the battery charged when vehicle is stored for long periods of time. | F66: mechanical | G66: Mechanical
A67: NGA | B67: Black Exhaust Tips | C67: 395 | F67: mechanical | G67: Mechanical
A68: ZER | B68: ZER Performance Package | C68: 500 | D68: XFR 275/30ZR20 front and 345/25ZR21 rear, blackwall, high performance tires, FED ZER suspension with Magnetic Selective Ride Control | F68: mechanical | G68: Mechanical
A69: G26 | B69: Sebring Orange Tintcoat | C69: 995 | D69: Premium Tintcoat Color new | F69: paint | G69: Paint Color
A70: G4Z | B70: Roswell Green Metallic exterior color (extra cost) | C70: 500 | D70: new Premium Color | F70: paint | G70: Paint Color
A71: G8G | B71: Arctic White | C71: 0 | F71: paint | G71: Paint Color
A72: GBA | B72: Black | C72: 0 | F72: paint | G72: Paint Color
A73: GBK | B73: Competition Yellow Tintcoat Metallic | C73: 995 | D73: Premium Tintcoat Color new | F73: paint | G73: Paint Color
A74: GJV | B74: Riptide Blue Metallic | C74: 0 | F74: paint | G74: Paint Color
A75: GKA | B75: Blade Silver Metallic exterior color | C75: 0 | D75: new | F75: paint | G75: Paint Color
A76: GKZ | B76: Torch Red | C76: 0 | F76: paint | G76: Paint Color
A77: GPH | B77: Red Mist Metallic Tintcoat | C77: 995 | D77: Premium Tintcoat Color | F77: paint | G77: Paint Color
A78: GXL | B78: Hysteria Purple Metallic | C78: 0 | F78: paint | G78: Paint Color
A79: 5V5-z | B79: Visible Carbon Fiber "low" spoiler | C79: 5995 | D79: Not available at this time. | E79: Not available with 5ZV | F79: spoilers, carbon_fiber | G79: Spoilers
A80: 5ZV | B80: NEW! LPO, Three-Stanchion high wing spoiler, Carbon Flash Metallic-painted | C80: WA | D80: Not available at this time. | E80: Not available with 5V5-z | F80: spoilers | G80: Spoilers
A81: T0E | B81: Low Rear Spoiler | C81: 0 | D81: Standard. Includes wicker end caps in 2 sizes | F81: spoilers | G81: Spoilers
A82: ZYC | B82: Carbon Flash Metallic painted outside mirrors and spoiler | C82: 195 | D82: Also paints Spoiler IF equipped with Z51, TVS, or T0E | F82: spoilers | G82: Spoilers
A83: DPB | B83: Carbon Flash with Blue accent Full Length Dual Racing Stripes | C83: 1195 | D83: Not available with exterior color GJV Riptide Blue Metallic, GMO Rapid Blue, or GXL Hysteria Purple. | E83: Not available with exterior color GJV Riptide Blue Metallic, GMO Rapid Blue, or GXL Hysteria Purple. | F83: stripes | G83: Stripes
A84: DPC | B84: Carbon Flash with Yellow accent Full Length Dual Racing Stripes | C84: 1195 | D84: Not available with exterior color GBK Competition Yellow Tintcoat Metallic. | E84: Not available with exterior color GBK Competition Yellow Tintcoat Metallic. | F84: stripes | G84: Stripes
A85: DPG | B85: Carbon Flash with Orange accent Full Length Dual Racing Stripes | C85: 1195 | D85: Not available with exterior color G26 Sebring Orange Tintcoat. | E85: Not available with exterior color G26 Sebring Orange Tintcoat. | F85: stripes | G85: Stripes
A86: DPL | B86: Carbon Flash with Red accent Full Length Dual Racing Stripes | C86: 1195 | D86: Not available with exterior color GKZ Torch Red or GPH Red Mist Metallic Tintcoat. | E86: Not available with exterior color GKZ Torch Red or GPH Red Mist Metallic Tintcoat. | F86: stripes | G86: Stripes
A87: DPT | B87: Carbon Flash with Silver accent Full Length Dual Racing Stripes | C87: 1195 | F87: stripes | G87: Stripes
A88: DSY | B88: Edge Orange Full Length Dual Racing Stripe | C88: 1195 | D88: Not available with exterior color G26 Sebring Orange Tintcoat. | E88: Not available with exterior color G26 Sebring Orange Tintcoat. | F88: stripes | G88: Stripes
A89: DSZ | B89: Edge Red Full Length Dual Racing Stripe | C89: 1195 | D89: Not available with exterior color GKZ Torch Red or GPH Red Mist Metallic Tintcoat. | E89: Not available with exterior color GKZ Torch Red or GPH Red Mist Metallic Tintcoat. | F89: stripes | G89: Stripes
A90: DT0 | B90: Competition Yellow Full Length Dual Racing Stripe | C90: 1195 | D90: Not available with exterior color GBK Competition Yellow Tintcoat Metallic. | E90: Not available with exterior color GBK Competition Yellow Tintcoat Metallic. | F90: stripes | G90: Stripes
A91: DTB | B91: Electric Blue Full Length Dual Racing Stripes | C91: 1195 | D91: Not available with exterior color GJV Riptide Blue Metallic, GMO Rapid Blue, or GXL Hysteria Purple. | E91: Not available with exterior color GJV Riptide Blue Metallic, GMO Rapid Blue, or GXL Hysteria Purple. | F91: stripes | G91: Stripes
A92: DTH | B92: Carbon Flash Full Length Dual Racing Stripe | C92: 1195 | F92: stripes | G92: Stripes
A93: DUB | B93: Sterling Silver Full Length Dual Racing Stripe | C93: 1195 | F93: stripes | G93: Stripes
A94: DUK | B94: Asymmetrical Adrenaline Red/Carbon Flash Full Length Dual Racing Stripes | C94: 1195 | D94: Not available with exterior color (GKZ) Torch Red or (GPH) Red Mist Metallic Tintcoat. | E94: Not available with exterior color (GKZ) Torch Red or (GPH) Red Mist Metallic Tintcoat. | F94: stripes | G94: Stripes
A95: DUW | B95: Edge Blue Full Length Dual Racing Stripe | C95: 1195 | D95: Not available with exterior color GJV Riptide Blue Metallic, GMO Rapid Blue, or GXL Hysteria Purple. | E95: Not available with exterior color GJV Riptide Blue Metallic, GMO Rapid Blue, or GXL Hysteria Purple. | F95: stripes | G95: Stripes
A96: DZU | B96: Stinger Stripe, Carbon Flash/ Competition Yellow | C96: 500 | D96: Not available with exterior color GBK Competition Yellow Tintcoat Metallic. | E96: Not available with exterior color GBK Competition Yellow Tintcoat Metallic. | F96: stripes | G96: Stripes
A97: DZV | B97: Stinger Stripe, Carbon Flash/ Midnight Silver | C97: 500 | F97: stripes | G97: Stripes
A98: DZX | B98: Stinger Stripe, Carbon Flash/ Edge Red | C98: 500 | D98: Not available with exterior color GKZ Torch Red or GPH Red Mist Metallic Tintcoat. | E98: Not available with exterior color GKZ Torch Red or GPH Red Mist Metallic Tintcoat. | F98: stripes | G98: Stripes
A99: SHT | B99: Jake Hood Graphic w/ Tech Bronze Accent | C99: 495 | D99: Dealer Installed | F99: stripes | G99: Stripes
A100: SNE | B100: Jake Hood Graphic | C100: 595 | D100: Dealer Installed | F100: stripes | G100: Stripes
...

Sheet Z06
A1: RPO Code | B1: Name | C1: Price | D1: Detail | E1: Compatibility | F1: Category | G1: Section
A2: 5DH | B2: Satin Graphite, Spider design Forged Aluminum Wheels with Red Stripe | C2: 4450 | D2: Includes Black lug nuts, LPO and Black wheel locks, LPO. Comes as a Second Set of Wheels | E2: Not available w/ R8C | F2: lpo, wheels | G2: Exterior Accessories
A3: 5DK | B3: Tech Bronze, Spider design Forged Aluminum Wheels | C3: 4150 | D3: Comes as a Second Set of Wheels. Includes Bronze center caps, Black wheel locks and Black Lugnuts | E3: Not available w/ R8C | F3: lpo, wheels | G3: Exterior Accessories
A4: 5JR | B4: Visible Carbon Fiber Mirror Covers | C4: 1250 | D4: 3LT/LZ only. Adds DRG carbon flash painted mirrors (N/C) | E4: 3LT/LZ only. Available with 1LZ on ZR1. | F4: carbon_fiber, lpo | G4: Carbon Fiber
A5: 5V5-z | B5: Visible Carbon Fiber "low" spoiler | C5: 5995 | D5: Not available at this time. | F5: spoilers, carbon_fiber | G5: Spoilers
A6: 5ZC | B6: Jake Logo wheel center caps | C6: 250 | F6: lpo, wheels | G6: Wheel Accessories
A7: 5ZD | B7: Carbon Flash Center Caps w/ Crossed Flags logo | C7: 250 | F7: lpo, wheels | G7: Wheel Accessories
A8: 5ZV | B8: NEW! LPO, Three-Stanchion high wing spoiler, Carbon Flash Metallic-painted | C8: WA | D8: Not available at this time. | E8: Not available with 5V5-z | F8: spoilers | G8: Spoilers
A9: B6P | B9: Coupe Engine Appearance Package | C9: 1695 | D9: Includes Carbon Fiber Trim, D3V Engine Bay Lights, and SL9 Engine Specification Plaque | F9: engine_bay, carbon_fiber | G9: Engine Appearance
A10: BCW | B10: Engine Intake, Edge red. | C10: 495 | D10: Requires B6P on Coupe. Requires ZZ3 Engine appearance package on Convertible. | E10: When equipped with B6P on Coupe. Requires ZZ3 Engine appearance package on Convertible. | F10: engine_bay | G10: Engine Appearance
A11: BCW-s | B11: Engine Intake, Edge red. | C11: 595 | D11: Without B6P. Includes D3V Engine Bay Lights on Coupe. Requires ZZ3 Engine appearance package on Convertible. | E11: Without B6P. Includes D3V Engine Bay Lights on Coupe. Requires ZZ3 Engine appearance package on Convertible. | F11: engine_bay | G11: Engine Appearance
A12: BV4 | B12: Plaque, personalized, custom-made with your name and VIN | C12: 295 | D12: Personalized plaque is included in museum delivery R8C, Plaque is located between the seats on the speaker grille. | F12: customdelivery | G12: Custom Delivery
A13: C2Z | B13: Visible Carbon Fiber weave w/body color border roof panel | C13: 2495 | F13: roof, carbon_fiber | G13: Coupe Roof Panel
A14: CAV | B14: Contoured Cargo Area Liners w/ Jake logo | C14: 195 | D14: Included w/PEF. Stingray and Z06 include both cargo areas. E-Ray and ZR1 rear trunk only | F14: lpo | G14: Interior Accessories
A15: CBF | B15: "NEW! Rockers and splitter, body-color | C15: 395 | D15: Not available with exterior color (GBA) Black or (CFV/CFZ) ground effects." | E15: Not available with exterior color (GBA) Black or (CFV/CFZ) ground effects." | F15: accents | G15: Accents
A16: CC3 | B16: Transparent Glass roof panel | C16: 995 | F16: roof | G16: Coupe Roof Panel
A17: CF7 | B17: Body-Color Carbon Roof panel | C17: 0 | D17: Standard | F17: roof | G17: Coupe Roof Panel
A18: CF8 | B18: Electrochromic Dimming Roof Panel | C18: 3000 | D18: Electrochromic dimming, removable. | E18: Not available on 1LT, 1LZ. Not available with any Full Length Dual Racing Stripes (DPB, DPC, DPG, DPL, DPT, DSY, DSZ, DT0, DTB, DTH, DUB, DUK, DUW). | F18: roof | G18: Coupe Roof Panel
A19: CFV | B19: Carbon Fiber Ground Effects- Visible Carbon weave | C19: 3995 | D19: Included with T0G | F19: carbon_fiber, lpo | G19: Carbon Fiber
A20: CFZ | B20: Carbon Fiber Ground Effects- Carbon Flash metallic Painted | C20: 2995 | D20: Included with T0F | F20: carbon_fiber, lpo | G20: Carbon Fiber
A21: CM9 | B21: Body-Color roof and nacelles | C21: 0 | D21: Standard | F21: roof | G21: Convertible Roof Panel
A22: D3V | B22: Engine Bay, Lights only | C22: 100 | D22: Coupe Only. Included with BCP, BCS, B6P, BCW. | F22: engine_bay | G22: Engine Appearance
A23: D84 | B23: Carbon Flash painted nacelles and roof | C23: 1295 | D23: Not available w/ GBA Black | E23: Not available w/ GBA Black | F23: roof | G23: Convertible Roof Panel
A24: D86 | B24: Carbon Flash painted nacelles and body color roof | C24: 1295 | D24: Not available w/ GBA Black | E24: Not available w/ GBA Black | F24: roof | G24: Convertible Roof Panel
A25: DPB | B25: Carbon Flash with Blue accent Full Length Dual Racing Stripes | C25: 1195 | D25: Not available with exterior color GJV Riptide Blue Metallic, GMO Rapid Blue, or GXL Hysteria Purple. | E25: Not available with exterior color GJV Riptide Blue Metallic, GMO Rapid Blue, or GXL Hysteria Purple. | F25: stripes | G25: Stripes
A26: DPC | B26: Carbon Flash with Yellow accent Full Length Dual Racing Stripes | C26: 1195 | D26: Not available with exterior color GBK Competition Yellow Tintcoat Metallic. | E26: Not available with exterior color GBK Competition Yellow Tintcoat Metallic. | F26: stripes | G26: Stripes
A27: DPG | B27: Carbon Flash with Orange accent Full Length Dual Racing Stripes | C27: 1195 | D27: Not available with exterior color G26 Sebring Orange Tintcoat. | E27: Not available with exterior color G26 Sebring Orange Tintcoat. | F27: stripes | G27: Stripes
A28: DPL | B28: Carbon Flash with Red accent Full Length Dual Racing Stripes | C28: 1195 | D28: Not available with exterior color GKZ Torch Red or GPH Red Mist Metallic Tintcoat. | E28: Not available with exterior color GKZ Torch Red or GPH Red Mist Metallic Tintcoat. | F28: stripes | G28: Stripes
A29: DPT | B29: Carbon Flash with Silver accent Full Length Dual Racing Stripes | C29: 1195 | F29: stripes | G29: Stripes
A30: DSY | B30: Edge Orange Full Length Dual Racing Stripe | C30: 1195 | D30: Not available with exterior color G26 Sebring Orange Tintcoat. | E30: Not available with exterior color G26 Sebring Orange Tintcoat. | F30: stripes | G30: Stripes
A31: DSZ | B31: Edge Red Full Length Dual Racing Stripe | C31: 1195 | D31: Not available with exterior color GKZ Torch Red or GPH Red Mist Metallic Tintcoat. | E31: Not available with exterior color GKZ Torch Red or GPH Red Mist Metallic Tintcoat. | F31: stripes | G31: Stripes
A32: DT0 | B32: Competition Yellow Full Length Dual Racing Stripe | C32: 1195 | D32: Not available with exterior color GBK Competition Yellow Tintcoat Metallic. | E32: Not available with exterior color GBK Competition Yellow Tintcoat Metallic. | F32: stripes | G32: Stripes
A33: DTH | B33: Carbon Flash Full Length Dual Racing Stripe | C33: 1195 | F33: stripes | G33: Stripes
A34: DUB | B34: Sterling Silver Full Length Dual Racing Stripe | C34: 1195 | F34: stripes | G34: Stripes
A35: DUK | B35: Asymmetrical Adrenaline Red/Carbon Flash Full Length Dual Racing Stripes | C35: 1195 | D35: Not available with exterior color (GKZ) Torch Red or (GPH) Red Mist Metallic Tintcoat. | E35: Not available with exterior color (GKZ) Torch Red or (GPH) Red Mist Metallic Tintcoat. | F35: stripes | G35: Stripes
A36: DUW | B36: Edge Blue Full Length Dual Racing Stripe | C36: 1195 | D36: Not available with exterior color GJV Riptide Blue Metallic, GMO Rapid Blue, or GXL Hysteria Purple. | E36: Not available with exterior color GJV Riptide Blue Metallic, GMO Rapid Blue, or GXL Hysteria Purple. | F36: stripes | G36: Stripes
A37: DZU | B37: Stinger Stripe, Carbon Flash/ Competition Yellow | C37: 500 | D37: Not available with exterior color GBK Competition Yellow Tintcoat Metallic. | E37: Not available with exterior color GBK Competition Yellow Tintcoat Metallic. | F37: stripes | G37: Stripes
A38: DZV | B38: Stinger Stripe, Carbon Flash/ Midnight Silver | C38: 500 | F38: stripes | G38: Stripes
A39: DZX | B39: Stinger Stripe, Carbon Flash/ Edge Red | C39: 500 | D39: Not available with exterior color GKZ Torch Red or GPH Red Mist Metallic Tintcoat. | E39: Not available with exterior color GKZ Torch Red or GPH Red Mist Metallic Tintcoat. | F39: stripes | G39: Stripes
A40: E60 | B40: Front lift adjustable height w/ memory | C40: 2595 | D40: 2LT/Z or 3LT/Z trim level only | E40: 2LT/Z or 3LT/Z trim level only | F40: mechanical | G40: Mechanical
A41: EFR | B41: Carbon Flash exterior accents | C41: 0 | D41: Standard Carbon Flash. Includes side vents and front/rear grille accents. Includes tonneau vent on convertible. Includes rockers on E-Ray and Z06 | F41: accents | G41: Accents
A42: EFY | B42: Body Color exterior accents | C42: 995 | D42: Includes side vents and front/rear grille accents. Includes tonneau vent on convertible. | E42: Not available with Black [GBA] | F42: accents | G42: Accents
A43: ERI | B43: Battery Protection Package | C43: 100 | D43: Battery tender used to keep the battery charged when vehicle is stored for long periods of time. | F43: mechanical | G43: Mechanical
A44: EYK | B44: Chrome Exterior Badge Package | C44: 295 | D44: Includes badges on the nose and decklid, "Corvette" script on rear, and lower rocker badge on wide-body models. | F44: badges | G44: Badges
A45: EYT | B45: Carbon Flash Exterior Badge Package | C45: 0 | D45: Standard. Includes badges on the nose and decklid, "Corvette" script on rear, and lower rocker badge on wide-body models. | F45: badges | G45: Badges
A46: G26 | B46: Sebring Orange Tintcoat | C46: 995 | D46: Premium Tintcoat Color new | F46: paint | G46: Paint Color
A47: G4Z | B47: Roswell Green Metallic exterior color (extra cost) | C47: 500 | D47: new Premium Color | F47: paint | G47: Paint Color
A48: G8G | B48: Arctic White | C48: 0 | F48: paint | G48: Paint Color
A49: GBA | B49: Black | C49: 0 | F49: paint | G49: Paint Color
A50: GBK | B50: Competition Yellow Tintcoat Metallic | C50: 995 | D50: Premium Tintcoat Color new | F50: paint | G50: Paint Color
A51: GJV | B51: Riptide Blue Metallic | C51: 0 | F51: paint | G51: Paint Color
A52: GKA | B52: Blade Silver Metallic exterior color | C52: 0 | D52: new | F52: paint | G52: Paint Color
A53: GKZ | B53: Torch Red | C53: 0 | F53: paint | G53: Paint Color
A54: GPH | B54: Red Mist Metallic Tintcoat | C54: 995 | D54: Premium Tintcoat Color | F54: paint | G54: Paint Color
A55: GXL | B55: Hysteria Purple Metallic | C55: 0 | F55: paint | G55: Paint Color
A56: J57 | B56: Carbon Ceramic Brakes | C56: 9000 | D56: Included with Z07 | F56: mechanical | G56: Mechanical
A57: J6A | B57: Black Painted Calipers | C57: 0 | D57: Standard, Gloss finish. Not available with J57 | E57: Not available with J57 ceramic brakes | F57: calipers | G57: Brake Calipers
A58: J6B | B58: Blue Painted Calipers | C58: 695 | D58: Requires J57 Ceramic brakes | E58: Requires J57 Ceramic brakes | F58: calipers | G58: Brake Calipers
A59: J6D | B59: Dark Gray metallic Painted Calipers | C59: 0 | D59: Standard with J57, Requires J57 Ceramic brakes | E59: Requires J57 Ceramic brakes | F59: calipers | G59: Brake Calipers
A60: J6E | B60: Velocity Yellow Painted Calipers | C60: 695 | D60: Gloss finish | F60: calipers | G60: Brake Calipers
A61: J6F | B61: Bright Red Painted Calipers | C61: 695 | D61: Gloss finish | F61: calipers | G61: Brake Calipers
A62: J6L | B62: Orange Painted Calipers | C62: 695 | D62: Requires J57 Ceramic brakes | E62: Requires J57 Ceramic brakes | F62: calipers | G62: Brake Calipers
A63: J6N | B63: Edge Red Painted Calipers | C63: 695 | D63: Darker shade of red, satin finish | F63: calipers | G63: Brake Calipers
A64: NGA | B64: Black Exhaust Tips | C64: 395 | F64: mechanical | G64: Mechanical
A65: PCZ | B65: Tech Bronze Accent Package | C65: 5050 | D65: Includes 5DK, SFZ, SHT, VPO | E65: Not available with EYK, PDA, SNE, DPB, DPC, DPG, DPL, DPT, DSY, DSZ, DT0, DTH, DUB, DUW, DZU, DZV, DZX | F65: lpo, wheels, stripes, badges | G65: LPO Packages
A66: PDA | B66: Jake C8.R Graphics Package | C66: 925 | D66: Includes SNE Jake hood graphic, LPO and VPW Jake C8.R rear hash graphic, LPO, Genuine Corvette Accessories | F66: lpo, stripes | G66: LPO Packages
A67: PDY | B67: Roadside Safety Package | C67: 195 | D67: Includes First Aid Kit RYT and Highway Safety Kit S08 | F67: lpo | G67: LPO Packages
A68: PEF | B68: Contoured Liner Protection Package | C68: 475 | D68: Includes CAV and RIA. ZR1 includes rear cargo liner only | F68: lpo | G68: LPO Packages
A69: PIN | B69: Customer selectable VIN ending* | C69: 5000 | D69: This option is subject to restrictions and approval. | F69: customdelivery | G69: Custom Delivery
A70: R88 | B70: NEW! LPO, Illuminated crossed flags emblem | C70: 475 | D70: Not available at the start of production | E70: Not available with (SFZ) Dark Stealth crossed flags emblems, LPO, (EYK) Chrome Exterior Badge Package or any Full Length Dual Racing Stripes (DPB, DPC, DPG, DPL, DPT, DSY, DSZ, DT0, DTB, DTH, DUB, DUK, DUK, DUW). | F70: lpo | G70: Exterior Accessories
A71: R8C | B71: Corvette Museum Delivery | C71: 1495 | D71: Guided VIP tour of the Corvette Assembly Plant (when available) for customer and 3 guests, Guided VIP tour of the NCM where the owner will see their Corvette on display, Quality, detailed orientation of the car by Delivery Team Guide, Celebratory drive out of the Museum (complimentary SD card to record for those with PDR), Unique gold RSC decal placed on the inside of the driver's door jamb, Custom interior dash plaque, Individual one-year NCM membership, Commemorative wall plaque with nameplate (customer's name, date of delivery, VIN#), Opportunity to purchase exclusive apparel, bricks and build sheet, Delivery can be viewed world-wide via our live webcams, Photos of the customer with the car (shared via email) | F71: customdelivery | G71: Custom Delivery
A72: R8E | B72: Gas guzzler tax, mandatory federal tax added to price of vehicle. | C72: 0 | D72: ALL Z06 and ZR1 | F72: mechanical | G72: Gas Guzzler Tax
A73: RIA | B73: All Weather floor liner w/ Jake logo | C73: 265 | D73: Included w/PEF | F73: lpo | G73: Interior Accessories
A74: RIK | B74: Rear Corvette Script, Torch Red | C74: 425 | D74: Not available with SL8, RIN | E74: Not available with SL8, RIN | F74: lpo | G74: Exterior Accessories
A75: RIN | B75: Rear Corvette Script, Arctic White | C75: 395 | D75: Not available with SL8, RIK | E75: Not available with SL8, RIK | F75: lpo | G75: Exterior Accessories
A76: ROY | B76: Carbon Flash metallic painted | C76: 11995 | D76: Requires J57 Ceramic brakes. (20"x10" Front / 21"x13" Rear) | F76: wheels, carbon_fiber | G76: Wheels
A77: ROZ | B77: Visible Carbon Fiber | C77: 13995 | D77: Requires J57 Ceramic brakes. (20"x10" Front / 21"x13" Rear) | F77: wheels, carbon_fiber | G77: Wheels
A78: RWH | B78: Premium Indoor car cover, Black with crossed flags logo | C78: 495 | F78: lpo | G78: Car Covers
A79: RWJ | B79: LPO, Premium outdoor car cover, Gray with crossed flags logo and Corvette silhouette | C79: 495 | F79: lpo | G79: Car Covers
A80: RWU | B80: Cargo Area Organizer, collapsible | C80: 175 | F80: lpo | G80: Interior Accessories
A81: RXI | B81: LT6 Engine Cover In Visible Carbon Fiber | C81: 2395 | D81: Coupe, 3LZ only | F81: engine_bay, carbon_fiber, lpo | G81: Carbon Fiber
A82: RYQ | B82: Visible Carbon Fiber Door Intake Trim | C82: 3995 | D82: Not available with (EFY) body-color exterior accents. | E82: Not available with (EFY) body-color exterior accents. | F82: carbon_fiber, lpo | G82: Carbon Fiber
A83: RYT | B83: First Aid Kit, Genuine Corvette Accessory | C83: 60 | D83: Included in PDY | F83: lpo | G83: Interior Accessories
A84: S08 | B84: Highway Safety Kit, Genuine Corvette Accessory | C84: 150 | D84: Included in PDY | F84: lpo | G84: Interior Accessories
A85: S2L | B85: Premium Leather weekend travel bags | C85: 1695 | D85: Set of 2 | F85: lpo | G85: Interior Accessories
A86: S47 | B86: Chrome lug nuts | C86: 275 | F86: lpo, wheels | G86: Wheel Accessories
A87: SBT | B87: LPO, Dual Roof, adds clear roof and storage bag. | C87: 2350 | D87: Adds Transparent glass panel CC3 and Roof panel storage bag SC7 | F87: roof, lpo | G87: Coupe Roof Panel
A88: SC7 | B88: Roof panel storage pouch | C88: 195 | D88: Included with Dual roof packages C2M, C2Q, SBT. Coupe Only | F88: lpo | G88: Exterior Accessories
A89: SDA | B89: Black recovery hook | C89: 125 | F89: lpo | G89: Exterior Accessories
A90: SFE | B90: Wheel locks | C90: 125 | F90: lpo, wheels | G90: Wheel Accessories
A91: SFZ | B91: Dark Stealth crossed flags emblem | C91: 275 | D91: Not available with EYK Chrome Exterior Badge Package or any Full Length Dual Racing Stripes DPB, DPC, DPG, DPL, DPT, DSY, DSZ, DT0, DTB, DTH, DUB, DUW, Included with PCX/PCZ Tech Bronze Accent Package, LPO. | E91: Not available with EYK Chrome Exterior Badge Package or any Full Length Dual Racing Stripes DPB, DPC, DPG, DPL, DPT, DSY, DSZ, DT0, DTB, DTH, DUB, DUW, Included with PCX/PCZ Tech Bronze Accent Package, LPO. | F91: lpo | G91: Exterior Accessories
A92: SG1 | B92: Z06 Badge in Edge Red | C92: 275 | F92: lpo | G92: Exterior Accessories
A93: SHT | B93: Jake Hood Graphic w/ Tech Bronze Accent | C93: 495 | D93: Dealer Installed | F93: stripes | G93: Stripes
A94: SIG | B94: LPO, Spoiler Extension, clear smoked center bridge w/ Jake Logo | C94: 425 | D94: Requires T0E rear spoiler (Standard spoiler) | E94: Requires T0E rear spoiler (Standard spoiler) | F94: spoilers, lpo | G94: Exterior Accessories
A95: SL8 | B95: Rear Corvette Script, Edge Red | C95: 395 | D95: Not available with RIK, RIN | E95: Not available with RIK, RIN | F95: lpo | G95: Exterior Accessories
A96: SL9 | B96: Engine Specification Plaque | C96: 95 | D96: Included with B6P/ZZ3 Engine Appearance Package new | F96: engine_bay | G96: Engine Appearance
A97: SLK | B97: Red Strut Bracket | C97: 1995 | D97: Coupe only. LPO | F97: engine_bay, lpo | G97: Engine Appearance
A98: SLN | B98: Visible Carbon Fiber Engine Cross Brace w/ Jake Logo | C98: 2895 | D98: Not available with RXI | E98: Not available with RXI | F98: carbon_fiber, engine_bay, lpo | G98: Carbon Fiber
A99: SNE | B99: Jake Hood Graphic | C99: 595 | D99: Dealer Installed | F99: stripes | G99: Stripes
A100: SOA | B100: Black, Spider Design Wheels | C100: 995 | D100: (20"x10" Front / 21"x13" Rear) Forged Aluminum Rims. | F100: wheels | G100: Wheels
...

Sheet ZR1
A1: RPO Code | B1: Name | C1: Price | D1: Detail | E1: Compatibility | F1: Category | G1: Section
A2: 5JR | B2: Visible Carbon Fiber Mirror Covers | C2: 1250 | D2: Adds DRG carbon flash painted mirrors (N/C) | E2: 3LT/LZ only. Available with 1LZ on ZR1. | F2: carbon_fiber, lpo | G2: Carbon Fiber
A3: 5ZC | B3: Jake Logo wheel center caps | C3: 250 | F3: lpo, wheels | G3: Wheel Accessories
A4: BV4 | B4: Plaque, personalized, custom-made with your name and VIN | C4: 295 | D4: Personalized plaque is included in museum delivery R8C, Plaque is located between the seats on the speaker grille. | F4: customdelivery | G4: Custom Delivery
A5: C2Z-z | B5: Visible Carbon Fiber weave w/body color border roof panel | C5: 0 | D5: Standard on ZR1 | F5: roof, carbon_fiber | G5: Coupe Roof Panel
A6: CAV | B6: Contoured Cargo Area Liners w/ Jake logo | C6: 195 | D6: ZR1 rear trunk only | F6: lpo | G6: Interior Accessories
A7: CF8 | B7: Electrochromic Dimming Roof Panel | C7: 3000 | D7: Electrochromic dimming, removable. | E7: Not available on 1LT, 1LZ. Not available with any Full Length Dual Racing Stripes (DPB, DPC, DPG, DPL, DPT, DSY, DSZ, DT0, DTB, DTH, DUB, DUK, DUW). | F7: roof | G7: Coupe Roof Panel
A8: CFC | B8: Convertible top | C8: 0 | D8: Standard. Retractable, power-folding hard top, visible carbon fiber, remote control (down only), includes power glass rear window with integral defogger | F8: roof | G8: Convertible Roof Panel
A9: DPB | B9: Carbon Flash with Blue accent Full Length Dual Racing Stripes | C9: 1195 | D9: Not available with exterior color GJV Riptide Blue Metallic, GMO Rapid Blue, or GXL Hysteria Purple. | E9: Not available with exterior color GJV Riptide Blue Metallic, GMO Rapid Blue, or GXL Hysteria Purple. | F9: stripes | G9: Stripes
A10: DPC | B10: Carbon Flash with Yellow accent Full Length Dual Racing Stripes | C10: 1195 | D10: Not available with exterior color GBK Competition Yellow Tintcoat Metallic. | E10: Not available with exterior color GBK Competition Yellow Tintcoat Metallic. | F10: stripes | G10: Stripes
A11: DPG | B11: Carbon Flash with Orange accent Full Length Dual Racing Stripes | C11: 1195 | D11: Not available with exterior color G26 Sebring Orange Tintcoat. | E11: Not available with exterior color G26 Sebring Orange Tintcoat. | F11: stripes | G11: Stripes
A12: DPL | B12: Carbon Flash with Red accent Full Length Dual Racing Stripes | C12: 1195 | D12: Not available with exterior color GKZ Torch Red or GPH Red Mist Metallic Tintcoat. | E12: Not available with exterior color GKZ Torch Red or GPH Red Mist Metallic Tintcoat. | F12: stripes | G12: Stripes
A13: DPT | B13: Carbon Flash with Silver accent Full Length Dual Racing Stripes | C13: 1195 | F13: stripes | G13: Stripes
A14: DSY | B14: Edge Orange Full Length Dual Racing Stripe | C14: 1195 | D14: Not available with exterior color G26 Sebring Orange Tintcoat. | E14: Not available with exterior color G26 Sebring Orange Tintcoat. | F14: stripes | G14: Stripes
A15: DSZ | B15: Edge Red Full Length Dual Racing Stripe | C15: 1195 | D15: Not available with exterior color GKZ Torch Red or GPH Red Mist Metallic Tintcoat. | E15: Not available with exterior color GKZ Torch Red or GPH Red Mist Metallic Tintcoat. | F15: stripes | G15: Stripes
A16: DT0 | B16: Competition Yellow Full Length Dual Racing Stripe | C16: 1195 | D16: Not available with exterior color GBK Competition Yellow Tintcoat Metallic. | E16: Not available with exterior color GBK Competition Yellow Tintcoat Metallic. | F16: stripes | G16: Stripes
A17: DTH | B17: Carbon Flash Full Length Dual Racing Stripe | C17: 1195 | F17: stripes | G17: Stripes
A18: DUB | B18: Sterling Silver Full Length Dual Racing Stripe | C18: 1195 | F18: stripes | G18: Stripes
A19: DUK | B19: Asymmetrical Adrenaline Red/Carbon Flash Full Length Dual Racing Stripes | C19: 1195 | D19: Not available with exterior color (GKZ) Torch Red or (GPH) Red Mist Metallic Tintcoat. | E19: Not available with exterior color (GKZ) Torch Red or (GPH) Red Mist Metallic Tintcoat. | F19: stripes | G19: Stripes
A20: DUW | B20: Edge Blue Full Length Dual Racing Stripe | C20: 1195 | D20: Not available with exterior color GJV Riptide Blue Metallic, GMO Rapid Blue, or GXL Hysteria Purple. | E20: Not available with exterior color GJV Riptide Blue Metallic, GMO Rapid Blue, or GXL Hysteria Purple. | F20: stripes | G20: Stripes
A21: E60 | B21: Front lift adjustable height w/ memory | C21: 2595 | E21: 3LZ trim level only | F21: mechanical | G21: Mechanical
A22: EFR | B22: Carbon Flash exterior accents | C22: 0 | D22: Standard Carbon Flash. Front grille and rear vents. | F22: accents | G22: Accents
A23: ERI | B23: Battery Protection Package | C23: 100 | D23: Battery tender used to keep the battery charged when vehicle is stored for long periods of time. | F23: mechanical | G23: Mechanical
A24: ETV | B24: Exterior trim, carbon fiber split window trim, painted body-color | C24: 995 | E24: Coupe Only | F24: accents
A25: EYK | B25: Chrome Exterior Badge Package | C25: 295 | D25: Includes badges on the nose and decklid, "Corvette" script on rear, and lower rocker badge on wide-body models. | F25: badges | G25: Badges
A26: EYT | B26: Carbon Flash Exterior Badge Package | C26: 0 | D26: Standard. Includes badges on the nose and decklid, "Corvette" script on rear, and lower rocker badge on wide-body models. | F26: badges | G26: Badges
A27: G26 | B27: Sebring Orange Tintcoat | C27: 995 | D27: Premium Tintcoat Color new | F27: paint | G27: Paint Color
A28: G4Z | B28: Roswell Green Metallic exterior color (extra cost) | C28: 500 | D28: new Premium Color | F28: paint | G28: Paint Color
A29: G8G | B29: Arctic White | C29: 0 | F29: paint | G29: Paint Color
A30: GBA | B30: Black | C30: 0 | F30: paint | G30: Paint Color
A31: GBK | B31: Competition Yellow Tintcoat Metallic | C31: 995 | D31: Premium Tintcoat Color new | F31: paint | G31: Paint Color
A32: GJV | B32: Riptide Blue Metallic | C32: 0 | F32: paint | G32: Paint Color
A33: GKA | B33: Blade Silver Metallic exterior color | C33: 0 | D33: new | F33: paint | G33: Paint Color
A34: GKZ | B34: Torch Red | C34: 0 | F34: paint | G34: Paint Color
A35: GPH | B35: Red Mist Metallic Tintcoat | C35: 995 | D35: Premium Tintcoat Color | F35: paint | G35: Paint Color
A36: GXL | B36: Hysteria Purple Metallic | C36: 0 | F36: paint | G36: Paint Color
A37: J6B | B37: Blue Painted Calipers | C37: 695 | D37: Requires J57 Ceramic brakes | E37: Requires J57 Ceramic brakes | F37: calipers | G37: Brake Calipers
A38: J6D | B38: Dark Gray metallic Painted Calipers | C38: 0 | D38: Standard with J57, Requires J57 Ceramic brakes | E38: Requires J57 Ceramic brakes | F38: calipers | G38: Brake Calipers
A39: J6E | B39: Velocity Yellow Painted Calipers | C39: 695 | D39: Gloss finish | F39: calipers | G39: Brake Calipers
A40: J6F | B40: Bright Red Painted Calipers | C40: 695 | D40: Gloss finish | F40: calipers | G40: Brake Calipers
A41: J6L | B41: Orange Painted Calipers | C41: 695 | D41: Requires J57 Ceramic brakes | E41: Requires J57 Ceramic brakes | F41: calipers | G41: Brake Calipers
A42: J6N | B42: Edge Red Painted Calipers | C42: 695 | D42: Darker shade of red, satin finish | F42: calipers | G42: Brake Calipers
A43: J6O | B43: Bronze Painted Calipers | C43: 695 | D43: ZR1 Only | F43: calipers | G43: Brake Calipers
A44: NGA | B44: Black Exhaust Tips | C44: 395 | F44: mechanical | G44: Mechanical
A45: PDY | B45: Roadside Safety Package | C45: 195 | D45: Includes First Aid Kit RYT and Highway Safety Kit S08 | F45: lpo | G45: LPO Packages
A46: PEF | B46: Contoured Liner Protection Package | C46: 475 | D46: Includes CAV and RIA. ZR1 includes rear cargo liner only | F46: lpo | G46: LPO Packages
A47: PIN | B47: Customer selectable VIN ending* | C47: 5000 | D47: This option is subject to restrictions and approval. | F47: customdelivery | G47: Custom Delivery
A48: R88 | B48: NEW! LPO, Illuminated crossed flags emblem | C48: 475 | D48: Not available at the start of production | E48: Not available with (SFZ) Dark Stealth crossed flags emblems, LPO, (EYK) Chrome Exterior Badge Package or any Full Length Dual Racing Stripes (DPB, DPC, DPG, DPL, DPT, DSY, DSZ, DT0, DTB, DTH, DUB, DUK, DUK, DUW). | F48: lpo | G48: Exterior Accessories
A49: R8C | B49: Corvette Museum Delivery | C49: 1495 | D49: Guided VIP tour of the Corvette Assembly Plant (when available) for customer and 3 guests, Guided VIP tour of the NCM where the owner will see their Corvette on display, Quality, detailed orientation of the car by Delivery Team Guide, Celebratory drive out of the Museum (complimentary SD card to record for those with PDR), Unique gold RSC decal placed on the inside of the driver's door jamb, Custom interior dash plaque, Individual one-year NCM membership, Commemorative wall plaque with nameplate (customer's name, date of delivery, VIN#), Opportunity to purchase exclusive apparel, bricks and build sheet, Delivery can be viewed world-wide via our live webcams, Photos of the customer with the car (shared via email) | F49: customdelivery | G49: Custom Delivery
A50: R8E | B50: Gas guzzler tax, mandatory federal tax added to price of vehicle. | C50: 0 | D50: ALL Z06 and ZR1 | F50: mechanical | G50: Gas Guzzler Tax
A51: RIA | B51: All Weather floor liner w/ Jake logo | C51: 265 | D51: Included w/PEF | F51: lpo | G51: Interior Accessories
A52: RIK | B52: Rear Corvette Script, Torch Red | C52: 425 | D52: Not available with SL8, RIN | E52: Not available with SL8, RIN | F52: lpo | G52: Exterior Accessories
A53: RIN | B53: Rear Corvette Script, Arctic White | C53: 395 | D53: Not available with SL8, RIK | E53: Not available with SL8, RIK | F53: lpo | G53: Exterior Accessories
A54: RWH | B54: Premium Indoor car cover, Black with crossed flags logo | C54: 495 | F54: lpo | G54: Car Covers
A55: RWJ | B55: LPO, Premium outdoor car cover, Gray with crossed flags logo and Corvette silhouette | C55: 495 | F55: lpo | G55: Car Covers
A56: RWU | B56: Cargo Area Organizer, collapsible | C56: 175 | F56: lpo | G56: Interior Accessories
A57: RYT | B57: First Aid Kit, Genuine Corvette Accessory | C57: 60 | D57: Included in PDY | F57: lpo | G57: Interior Accessories
A58: S08 | B58: Highway Safety Kit, Genuine Corvette Accessory | C58: 150 | D58: Included in PDY | F58: lpo | G58: Interior Accessories
A59: S2L | B59: Premium Leather weekend travel bags | C59: 1695 | D59: Set of 2 | F59: lpo | G59: Interior Accessories
A60: S47 | B60: Chrome lug nuts | C60: 275 | F60: lpo, wheels | G60: Wheel Accessories
A61: SBT | B61: LPO, Dual Roof, adds clear roof and storage bag. | C61: 2350 | D61: Adds Transparent glass panel CC3 and Roof panel storage bag SC7 | F61: roof, lpo | G61: Coupe Roof Panel
A62: SC7 | B62: Roof panel storage pouch | C62: 195 | D62: Included with Dual roof packages C2M, C2Q, SBT. Coupe Only | F62: lpo | G62: Exterior Accessories
A63: SDA | B63: Black recovery hook | C63: 125 | F63: lpo | G63: Exterior Accessories
A64: SFE | B64: Wheel locks | C64: 125 | F64: lpo, wheels | G64: Wheel Accessories
A65: SFZ | B65: Dark Stealth crossed flags emblem | C65: 275 | D65: Not available with EYK Chrome Exterior Badge Package or any Full Length Dual Racing Stripes DPB, DPC, DPG, DPL, DPT, DSY, DSZ, DT0, DTB, DTH, DUB, DUW, Included with PCX/PCZ Tech Bronze Accent Package, LPO. | E65: Not available with EYK Chrome Exterior Badge Package or any Full Length Dual Racing Stripes DPB, DPC, DPG, DPL, DPT, DSY, DSZ, DT0, DTB, DTH, DUB, DUW, Included with PCX/PCZ Tech Bronze Accent Package, LPO. | F65: lpo | G65: Exterior Accessories
A66: SIG | B66: LPO, Spoiler Extension, clear smoked center bridge w/ Jake Logo | C66: 425 | D66: Requires T0E rear spoiler (Standard spoiler) | E66: Requires T0E rear spoiler (Standard spoiler) | F66: spoilers, lpo | G66: Exterior Accessories
A67: SL8 | B67: Rear Corvette Script, Edge Red | C67: 395 | D67: Not available with RIK, RIN | E67: Not available with RIK, RIN | F67: lpo | G67: Exterior Accessories
A68: SLK | B68: Red Strut Bracket | C68: 1995 | D68: Coupe only. LPO | F68: engine_bay, lpo | G68: Engine Appearance
A69: SLN | B69: Visible Carbon Fiber Engine Cross Brace w/ Jake Logo | C69: 2895 | D69: Not available with RXI | E69: Not available with RXI | F69: carbon_fiber, engine_bay, lpo | G69: Carbon Fiber
A70: SOF | B70: Edge Blue-painted forged aluminum 20 Spoke Wheels | C70: 1495 | D70: (20"x10" Front / 21"x13" Rear) Forged Aluminum Rims. | F70: wheels | G70: Wheels
A71: SOG | B71: Carbon Flash-painted forged aluminum 20 Spoke Wheels | C71: 1495 | D71: (20"x10" Front / 21"x13" Rear) Forged Aluminum Rims. | F71: wheels | G71: Wheels
A72: SOH | B72: Bright machined forged aluminum 20 Spoke Wheels | C72: 1995 | D72: (20"x10" Front / 21"x13" Rear) Forged Aluminum Rims. | F72: wheels | G72: Wheels
A73: SOJ | B73: Sterling Silver-painted forged aluminum 20 Spoke Wheels | C73: 0 | D73: Standard (20"x10" Front / 21"x13" Rear) Forged Aluminum Rims. | F73: wheels | G73: Wheels
A74: SPY | B74: Black lug nuts | C74: 295 | F74: lpo, wheels | G74: Wheel Accessories
A75: SPZ | B75: Black wheel locks | C75: 175 | E75: Requires SPY Black lug nuts | F75: lpo, wheels | G75: Wheel Accessories
A76: SU1 | B76: Visible carbon fiber 10 Spoke Wheels | C76: 13995 | D76: (20"x10" Front / 21"x13" Rear) | F76: wheels, carbon_fiber | G76: Wheels
A77: SXB | B77: Suede Frunk and Trunk Liner, Black | C77: 1950 | F77: lpo | G77: Interior Accessories
A78: SXR | B78: Suede Frunk and Trunk Liner, Red | C78: 1950 | F78: lpo | G78: Interior Accessories
A79: SXT | B79: Suede Frunk and Trunk Liner, Tan | C79: 2295 | F79: lpo | G79: Interior Accessories
A80: T0E | B80: Low Rear Spoiler | C80: 0 | D80: Standard. Includes wicker end caps in 2 sizes | F80: spoilers | G80: Spoilers
A81: TOM | B81: ZR1 Carbon Fiber Aero Package | C81: 10495 | D81: Visible carbon fiber, includes carbon fiber high-wing spoiler, dive planes, and tall hood spoiler | F81: spoilers, carbon_fiber | G81: Spoilers
A82: V8X | B82: Visible Carbon Fiber Sill Plates | C82: 1995 | D82: Corvette Script and sillhouette logo | F82: carbon_fiber, lpo | G82: Carbon Fiber
A83: VK3 | B83: License Plate Bracket, Front | C83: 40 | D83: (Auto Shipped to Required States) | F83: lpo | G83: Exterior Accessories
A84: VTB | B84: Rear Fascia/roof storage protector Black w/ Crossed flags logo | C84: 150 | F84: lpo | G84: Interior Accessories
A85: VUP | B85: Engine Bay Closeout Graphics | C85: 570 | D85: Coupe only. LPO | F85: lpo, engine_bay | G85: Engine Appearance
A86: VYW | B86: Premium Floor mats, carpeted w/ Car silhouette logo | C86: 298 | D86: Z06 has Z06 logo instead of Car silhouette. | F86: lpo | G86: Interior Accessories
A87: W2D | B87: Cargo net set | C87: 95 | D87: 1LT/LZ only | E87: 1LT 1LZ only | F87: lpo | G87: Interior Accessories
A88: WKR | B88: NEW! LPO, Premium indoor car cover, GT3.R, fully rendered | C88: WA | F88: lpo | G88: Car Covers
A89: ZTK | B89: ZTK Track Performance Package | C89: 4395 | D89: Includes (J59) carbon ceramic, 10-piston front, 6-piston rear brakes, (FEJ) ZTK suspension with Magnetic Selective Ride Control and (XFS) 275/30ZR20 front and 345/25ZR21 rear Michelin Pilot Sport Cup 2 R ultra performance tires | E89: Requires (TOM) ZR1 Carbon Fiber Aero Package. | F89: mechanical, spoilers | G89: Mechanical
A90: ZYC | B90: Carbon Flash Metallic painted outside mirrors and spoiler | C90: 195 | D90: Also paints Spoiler IF equipped with T0E | E90: Requires T0E | F90: spoilers | G90: Spoilers

Sheet ZR1X
A1: RPO Code | B1: Name | C1: Price | D1: Detail | E1: Compatibility | F1: Category | G1: Section
A2: EFR | B2: Carbon Flash exterior accents | C2: 0 | D2: Standard Carbon Flash. Front grille and rear vents. | F2: accents | G2: Accents
A3: EYK | B3: Chrome Exterior Badge Package | C3: 295 | D3: Includes badges on the nose and decklid, "Corvette" script on rear, and lower rocker badge on wide-body models. | F3: badges | G3: Badges
A4: EYT | B4: Carbon Flash Exterior Badge Package | C4: 0 | D4: Standard. Includes badges on the nose and decklid, "Corvette" script on rear, and lower rocker badge on wide-body models. | F4: badges | G4: Badges
A5: J6B | B5: Blue Painted Calipers | C5: 695 | D5: Requires J57 Ceramic brakes | E5: Requires J57 Ceramic brakes | F5: calipers | G5: Brake Calipers
A6: J6D | B6: Dark Gray metallic Painted Calipers | C6: 0 | D6: Standard with J57, Requires J57 Ceramic brakes | E6: Requires J57 Ceramic brakes | F6: calipers | G6: Brake Calipers
A7: J6E | B7: Velocity Yellow Painted Calipers | C7: 695 | D7: Gloss finish | F7: calipers | G7: Brake Calipers
A8: J6F | B8: Bright Red Painted Calipers | C8: 695 | D8: Gloss finish | F8: calipers | G8: Brake Calipers
A9: J6L | B9: Orange Painted Calipers | C9: 695 | D9: Requires J57 Ceramic brakes | E9: Requires J57 Ceramic brakes | F9: calipers | G9: Brake Calipers
A10: J6N | B10: Edge Red Painted Calipers | C10: 695 | D10: Darker shade of red, satin finish | F10: calipers | G10: Brake Calipers
A11: J6O | B11: Bronze Painted Calipers | C11: 695 | D11: ZR1 Only | F11: calipers | G11: Brake Calipers
A12: RWH | B12: Premium Indoor car cover, Black with crossed flags logo | C12: 495 | F12: lpo | G12: Car Covers
A13: RWJ | B13: LPO, Premium outdoor car cover, Gray with crossed flags logo and Corvette silhouette | C13: 495 | F13: lpo | G13: Car Covers
A14: WKR | B14: NEW! LPO, Premium indoor car cover, GT3.R, fully rendered | C14: WA | F14: lpo | G14: Car Covers
A15: 5JR | B15: Visible Carbon Fiber Mirror Covers | C15: 1250 | D15: Adds DRG carbon flash painted mirrors (N/C) | E15: 3LT/LZ only. Available with 1LZ on ZR1. | F15: carbon_fiber, lpo | G15: Carbon Fiber
A16: SLN | B16: Visible Carbon Fiber Engine Cross Brace w/ Jake Logo | C16: 2895 | D16: Not available with RXI | E16: Not available with RXI | F16: carbon_fiber, engine_bay, lpo | G16: Carbon Fiber
A17: V8X | B17: Visible Carbon Fiber Sill Plates | C17: 1995 | D17: Corvette Script and sillhouette logo | F17: carbon_fiber, lpo | G17: Carbon Fiber
A18: CFC | B18: Convertible top | C18: 0 | D18: Standard. Retractable, power-folding hard top, visible carbon fiber, remote control (down only), includes power glass rear window with integral defogger | F18: roof | G18: Convertible Roof Panel
A19: C2Z-z | B19: Visible Carbon Fiber weave w/body color border roof panel | C19: 0 | D19: Standard on ZR1 | F19: roof, carbon_fiber | G19: Coupe Roof Panel
A20: CF8 | B20: Electrochromic Dimming Roof Panel | C20: 3000 | D20: Electrochromic dimming, removable. | E20: Not available on 1LT, 1LZ. Not available with any Full Length Dual Racing Stripes (DPB, DPC, DPG, DPL, DPT, DSY, DSZ, DT0, DTB, DTH, DUB, DUK, DUW). | F20: roof | G20: Coupe Roof Panel
A21: SBT | B21: LPO, Dual Roof, adds clear roof and storage bag. | C21: 2350 | D21: Adds Transparent glass panel CC3 and Roof panel storage bag SC7 | F21: roof, lpo | G21: Coupe Roof Panel
A22: BV4 | B22: Plaque, personalized, custom-made with your name and VIN | C22: 295 | D22: Personalized plaque is included in museum delivery R8C, Plaque is located between the seats on the speaker grille. | F22: customdelivery | G22: Custom Delivery
A23: PIN | B23: Customer selectable VIN ending* | C23: 5000 | D23: This option is subject to restrictions and approval. | F23: customdelivery | G23: Custom Delivery
A24: R8C | B24: Corvette Museum Delivery | C24: 1495 | D24: Guided VIP tour of the Corvette Assembly Plant (when available) for customer and 3 guests, Guided VIP tour of the NCM where the owner will see their Corvette on display, Quality, detailed orientation of the car by Delivery Team Guide, Celebratory drive out of the Museum (complimentary SD card to record for those with PDR), Unique gold RSC decal placed on the inside of the driver's door jamb, Custom interior dash plaque, Individual one-year NCM membership, Commemorative wall plaque with nameplate (customer's name, date of delivery, VIN#), Opportunity to purchase exclusive apparel, bricks and build sheet, Delivery can be viewed world-wide via our live webcams, Photos of the customer with the car (shared via email) | F24: customdelivery | G24: Custom Delivery
A25: SLK | B25: Red Strut Bracket | C25: 1995 | D25: Coupe only. LPO | F25: engine_bay, lpo | G25: Engine Appearance
A26: VUP | B26: Engine Bay Closeout Graphics | C26: 570 | D26: Coupe only. LPO | F26: lpo, engine_bay | G26: Engine Appearance
A27: R88 | B27: NEW! LPO, Illuminated crossed flags emblem | C27: 475 | D27: Not available at the start of production | E27: Not available with (SFZ) Dark Stealth crossed flags emblems, LPO, (EYK) Chrome Exterior Badge Package or any Full Length Dual Racing Stripes (DPB, DPC, DPG, DPL, DPT, DSY, DSZ, DT0, DTB, DTH, DUB, DUK, DUK, DUW). | F27: lpo | G27: Exterior Accessories
A28: RIK | B28: Rear Corvette Script, Torch Red | C28: 425 | D28: Not available with SL8, RIN | E28: Not available with SL8, RIN | F28: lpo | G28: Exterior Accessories
A29: RIN | B29: Rear Corvette Script, Arctic White | C29: 395 | D29: Not available with SL8, RIK | E29: Not available with SL8, RIK | F29: lpo | G29: Exterior Accessories
A30: SC7 | B30: Roof panel storage pouch | C30: 195 | D30: Included with Dual roof packages C2M, C2Q, SBT. Coupe Only | F30: lpo | G30: Exterior Accessories
A31: SDA | B31: Black recovery hook | C31: 125 | F31: lpo | G31: Exterior Accessories
A32: SFZ | B32: Dark Stealth crossed flags emblem | C32: 275 | D32: Not available with EYK Chrome Exterior Badge Package or any Full Length Dual Racing Stripes DPB, DPC, DPG, DPL, DPT, DSY, DSZ, DT0, DTB, DTH, DUB, DUW, Included with PCX/PCZ Tech Bronze Accent Package, LPO. | E32: Not available with EYK Chrome Exterior Badge Package or any Full Length Dual Racing Stripes DPB, DPC, DPG, DPL, DPT, DSY, DSZ, DT0, DTB, DTH, DUB, DUW, Included with PCX/PCZ Tech Bronze Accent Package, LPO. | F32: lpo | G32: Exterior Accessories
A33: SIG | B33: LPO, Spoiler Extension, clear smoked center bridge w/ Jake Logo | C33: 425 | D33: Requires T0E rear spoiler (Standard spoiler) | E33: Requires T0E rear spoiler (Standard spoiler) | F33: spoilers, lpo | G33: Exterior Accessories
A34: SL8 | B34: Rear Corvette Script, Edge Red | C34: 395 | D34: Not available with RIK, RIN | E34: Not available with RIK, RIN | F34: lpo | G34: Exterior Accessories
A35: VK3 | B35: License Plate Bracket, Front | C35: 40 | D35: (Auto Shipped to Required States) | F35: lpo | G35: Exterior Accessories
A36: R8E | B36: Gas guzzler tax, mandatory federal tax added to price of vehicle. | C36: 0 | D36: ALL Z06 and ZR1 | F36: mechanical | G36: Gas Guzzler Tax
A37: CAV | B37: Contoured Cargo Area Liners w/ Jake logo | C37: 195 | D37: ZR1 rear trunk only | F37: lpo | G37: Interior Accessories
A38: RIA | B38: All Weather floor liner w/ Jake logo | C38: 265 | D38: Included w/PEF | F38: lpo | G38: Interior Accessories
A39: RWU | B39: Cargo Area Organizer, collapsible | C39: 175 | F39: lpo | G39: Interior Accessories
A40: RYT | B40: First Aid Kit, Genuine Corvette Accessory | C40: 60 | D40: Included in PDY | F40: lpo | G40: Interior Accessories
A41: S08 | B41: Highway Safety Kit, Genuine Corvette Accessory | C41: 150 | D41: Included in PDY | F41: lpo | G41: Interior Accessories
A42: S2L | B42: Premium Leather weekend travel bags | C42: 1695 | D42: Set of 2 | F42: lpo | G42: Interior Accessories
A43: SXB | B43: Suede Frunk and Trunk Liner, Black | C43: 1950 | F43: lpo | G43: Interior Accessories
A44: SXR | B44: Suede Frunk and Trunk Liner, Red | C44: 1950 | F44: lpo | G44: Interior Accessories
A45: SXT | B45: Suede Frunk and Trunk Liner, Tan | C45: 2295 | F45: lpo | G45: Interior Accessories
A46: VTB | B46: Rear Fascia/roof storage protector Black w/ Crossed flags logo | C46: 150 | F46: lpo | G46: Interior Accessories
A47: VYW | B47: Premium Floor mats, carpeted w/ Car silhouette logo | C47: 298 | D47: Z06 has Z06 logo instead of Car silhouette. | F47: lpo | G47: Interior Accessories
A48: W2D | B48: Cargo net set | C48: 95 | D48: 1LT/LZ only | E48: 1LT 1LZ only | F48: lpo | G48: Interior Accessories
A49: PDY | B49: Roadside Safety Package | C49: 195 | D49: Includes First Aid Kit RYT and Highway Safety Kit S08 | F49: lpo | G49: LPO Packages
A50: PEF | B50: Contoured Liner Protection Package | C50: 475 | D50: Includes CAV and RIA. ZR1 includes rear cargo liner only | F50: lpo | G50: LPO Packages
A51: E60 | B51: Front lift adjustable height w/ memory | C51: 2595 | E51: 3LZ trim level only | F51: mechanical | G51: Mechanical
A52: ERI | B52: Battery Protection Package | C52: 100 | D52: Battery tender used to keep the battery charged when vehicle is stored for long periods of time. | F52: mechanical | G52: Mechanical
A53: NGA | B53: Black Exhaust Tips | C53: 395 | F53: mechanical | G53: Mechanical
A54: ZTK | B54: ZTK Track Performance Package | C54: 4395 | D54: Includes (J59) carbon ceramic, 10-piston front, 6-piston rear brakes, (FEJ) ZTK suspension with Magnetic Selective Ride Control and (XFS) 275/30ZR20 front and 345/25ZR21 rear Michelin Pilot Sport Cup 2 R ultra performance tires | E54: Requires (TOM) ZR1 Carbon Fiber Aero Package. | F54: mechanical, spoilers | G54: Mechanical
A55: G26 | B55: Sebring Orange Tintcoat | C55: 995 | D55: Premium Tintcoat Color new | F55: paint | G55: Paint Color
A56: G4Z | B56: Roswell Green Metallic exterior color (extra cost) | C56: 500 | D56: new Premium Color | F56: paint | G56: Paint Color
A57: G8G | B57: Arctic White | C57: 0 | F57: paint | G57: Paint Color
A58: GBA | B58: Black | C58: 0 | F58: paint | G58: Paint Color
A59: GBK | B59: Competition Yellow Tintcoat Metallic | C59: 995 | D59: Premium Tintcoat Color new | F59: paint | G59: Paint Color
A60: GJV | B60: Riptide Blue Metallic | C60: 0 | F60: paint | G60: Paint Color
A61: GKA | B61: Blade Silver Metallic exterior color | C61: 0 | D61: new | F61: paint | G61: Paint Color
A62: GKZ | B62: Torch Red | C62: 0 | F62: paint | G62: Paint Color
A63: GPH | B63: Red Mist Metallic Tintcoat | C63: 995 | D63: Premium Tintcoat Color | F63: paint | G63: Paint Color
A64: GXL | B64: Hysteria Purple Metallic | C64: 0 | F64: paint | G64: Paint Color
A65: T0E | B65: Low Rear Spoiler | C65: 0 | D65: Standard. Includes wicker end caps in 2 sizes | F65: spoilers | G65: Spoilers
A66: TOM | B66: ZR1 Carbon Fiber Aero Package | C66: 10495 | D66: Visible carbon fiber, includes carbon fiber high-wing spoiler, dive planes, and tall hood spoiler | F66: spoilers, carbon_fiber | G66: Spoilers
A67: ZYC | B67: Carbon Flash Metallic painted outside mirrors and spoiler | C67: 195 | D67: Also paints Spoiler IF equipped with T0E | E67: Requires T0E | F67: spoilers | G67: Spoilers
A68: DPB | B68: Carbon Flash with Blue accent Full Length Dual Racing Stripes | C68: 1195 | D68: Not available with exterior color GJV Riptide Blue Metallic, GMO Rapid Blue, or GXL Hysteria Purple. | E68: Not available with exterior color GJV Riptide Blue Metallic, GMO Rapid Blue, or GXL Hysteria Purple. | F68: stripes | G68: Stripes
A69: DPC | B69: Carbon Flash with Yellow accent Full Length Dual Racing Stripes | C69: 1195 | D69: Not available with exterior color GBK Competition Yellow Tintcoat Metallic. | E69: Not available with exterior color GBK Competition Yellow Tintcoat Metallic. | F69: stripes | G69: Stripes
A70: DPG | B70: Carbon Flash with Orange accent Full Length Dual Racing Stripes | C70: 1195 | D70: Not available with exterior color G26 Sebring Orange Tintcoat. | E70: Not available with exterior color G26 Sebring Orange Tintcoat. | F70: stripes | G70: Stripes
A71: DPL | B71: Carbon Flash with Red accent Full Length Dual Racing Stripes | C71: 1195 | D71: Not available with exterior color GKZ Torch Red or GPH Red Mist Metallic Tintcoat. | E71: Not available with exterior color GKZ Torch Red or GPH Red Mist Metallic Tintcoat. | F71: stripes | G71: Stripes
A72: DPT | B72: Carbon Flash with Silver accent Full Length Dual Racing Stripes | C72: 1195 | F72: stripes | G72: Stripes
A73: DSY | B73: Edge Orange Full Length Dual Racing Stripe | C73: 1195 | D73: Not available with exterior color G26 Sebring Orange Tintcoat. | E73: Not available with exterior color G26 Sebring Orange Tintcoat. | F73: stripes | G73: Stripes
A74: DSZ | B74: Edge Red Full Length Dual Racing Stripe | C74: 1195 | D74: Not available with exterior color GKZ Torch Red or GPH Red Mist Metallic Tintcoat. | E74: Not available with exterior color GKZ Torch Red or GPH Red Mist Metallic Tintcoat. | F74: stripes | G74: Stripes
A75: DT0 | B75: Competition Yellow Full Length Dual Racing Stripe | C75: 1195 | D75: Not available with exterior color GBK Competition Yellow Tintcoat Metallic. | E75: Not available with exterior color GBK Competition Yellow Tintcoat Metallic. | F75: stripes | G75: Stripes
A76: DTH | B76: Carbon Flash Full Length Dual Racing Stripe | C76: 1195 | F76: stripes | G76: Stripes
A77: DUB | B77: Sterling Silver Full Length Dual Racing Stripe | C77: 1195 | F77: stripes | G77: Stripes
A78: DUK | B78: Asymmetrical Adrenaline Red/Carbon Flash Full Length Dual Racing Stripes | C78: 1195 | D78: Not available with exterior color (GKZ) Torch Red or (GPH) Red Mist Metallic Tintcoat. | E78: Not available with exterior color (GKZ) Torch Red or (GPH) Red Mist Metallic Tintcoat. | F78: stripes | G78: Stripes
A79: DUW | B79: Edge Blue Full Length Dual Racing Stripe | C79: 1195 | D79: Not available with exterior color GJV Riptide Blue Metallic, GMO Rapid Blue, or GXL Hysteria Purple. | E79: Not available with exterior color GJV Riptide Blue Metallic, GMO Rapid Blue, or GXL Hysteria Purple. | F79: stripes | G79: Stripes
A80: 5ZC | B80: Jake Logo wheel center caps | C80: 250 | F80: lpo, wheels | G80: Wheel Accessories
A81: S47 | B81: Chrome lug nuts | C81: 275 | F81: lpo, wheels | G81: Wheel Accessories
A82: SFE | B82: Wheel locks | C82: 125 | F82: lpo, wheels | G82: Wheel Accessories
A83: SPY | B83: Black lug nuts | C83: 295 | F83: lpo, wheels | G83: Wheel Accessories
A84: SPZ | B84: Black wheel locks | C84: 175 | E84: Requires SPY Black lug nuts | F84: lpo, wheels | G84: Wheel Accessories
A85: SOF | B85: Edge Blue-painted forged aluminum 20 Spoke Wheels | C85: 1495 | D85: (20"x10" Front / 21"x13" Rear) Forged Aluminum Rims. | F85: wheels | G85: Wheels
A86: SOG | B86: Carbon Flash-painted forged aluminum 20 Spoke Wheels | C86: 1495 | D86: (20"x10" Front / 21"x13" Rear) Forged Aluminum Rims. | F86: wheels | G86: Wheels
A87: SOH | B87: Bright machined forged aluminum 20 Spoke Wheels | C87: 1995 | D87: (20"x10" Front / 21"x13" Rear) Forged Aluminum Rims. | F87: wheels | G87: Wheels
A88: SOJ | B88: Sterling Silver-painted forged aluminum 20 Spoke Wheels | C88: 0 | D88: Standard (20"x10" Front / 21"x13" Rear) Forged Aluminum Rims. | F88: wheels | G88: Wheels
A89: SU1 | B89: Visible carbon fiber 10 Spoke Wheels | C89: 13995 | D89: (20"x10" Front / 21"x13" Rear) | F89: wheels, carbon_fiber | G89: Wheels
A90: ETV | B90: Exterior trim, carbon fiber split window trim, painted body-color | C90: 995 | E90: Coupe Only | F90: accents

Sheet ERay.Z06_Int
A1: Section | B1: Trim | C1: Seat | D1: RPO | E1: Suede | F1: Stitching | G1: Two Tone | H1: Name | I1: Detail | J1: Category | K1: Codes | L1: Price
A2: 1LZ Colors | B2: 1LZ | C2: AQ9 | D2: HTA | H2: Jet Black Mulan | I2: AQ9 GT1 Seats . Interior color on seats only. Stitching will match int color. Jet Black has silver stitching. | J2: interior.1 | K2: =textjoin(" ",true,B2,C2,D2,F2,E2,G2) -> 1LZ AQ9 HTA | L2: =SUM( SUMIFS( PriceRef!$D$2:$D158, PriceRef!$A$2:$A158, "Seat", PriceRef!$B$2:$B158, $B2, PriceRef!$C$2:$C158, $C2 ), SUMIFS( PriceRef!$D$2:$D158, PriceRef!$A$2:$A158, "Stitching", PriceRef!$C$2:$C158, $F2 ), SUMIFS( PriceRef!$D$2:$D158, PriceRef!$A$2:$A158, "Suede", PriceRef!$C$2:$C158, $E2 ), SUMIFS( PriceRef!$D$2:$D158, PriceRef!$A$2:$A158, "TwoTone", PriceRef!$C$2:$C158, $G2 ) ) -> 0
A3: 1LZ Colors | B3: 1LZ | C3: AE4 | D3: HTJ | E3: N26 | H3: Jet Black Performance Textile | I3: AE4 Comp Seats. Adds N26 suede steering wheel. Seat back and bottom are all performance textile. Interior color on seats only. Jet Black has silver stitching. | J3: interior.1 | K3: =textjoin(" ",true,B3,C3,D3,F3,E3,G3) -> 1LZ AE4 HTJ N26 | L3: =SUM( SUMIFS( PriceRef!$D$2:$D158, PriceRef!$A$2:$A158, "Seat", PriceRef!$B$2:$B158, $B3, PriceRef!$C$2:$C158, $C3 ), SUMIFS( PriceRef!$D$2:$D158, PriceRef!$A$2:$A158, "Stitching", PriceRef!$C$2:$C158, $F3 ), SUMIFS( PriceRef!$D$2:$D158, PriceRef!$A$2:$A158, "Suede", PriceRef!$C$2:$C158, $E3 ), SUMIFS( PriceRef!$D$2:$D158, PriceRef!$A$2:$A158, "TwoTone", PriceRef!$C$2:$C158, $G3 ) ) -> 1690
A4: 1LZ Colors | B4: 1LZ | C4: AQ9 | D4: HUP | H4: Sky Cool Gray Mulan | I4: AQ9 GT1 Seats. Interior color on seats only. Stitching will match int color. | J4: interior.1 | K4: =textjoin(" ",true,B4,C4,D4,F4,E4,G4) -> 1LZ AQ9 HUP | L4: =SUM( SUMIFS( PriceRef!$D$2:$D158, PriceRef!$A$2:$A158, "Seat", PriceRef!$B$2:$B158, $B4, PriceRef!$C$2:$C158, $C4 ), SUMIFS( PriceRef!$D$2:$D158, PriceRef!$A$2:$A158, "Stitching", PriceRef!$C$2:$C158, $F4 ), SUMIFS( PriceRef!$D$2:$D158, PriceRef!$A$2:$A158, "Suede", PriceRef!$C$2:$C158, $E4 ), SUMIFS( PriceRef!$D$2:$D158, PriceRef!$A$2:$A158, "TwoTone", PriceRef!$C$2:$C158, $G4 ) ) -> 0
A5: 1LZ Colors | B5: 1LZ | C5: AQ9 | D5: HUQ | H5: Adrenaline Red Mulan | I5: AQ9 GT1 Seats. Interior color on seats only. Stitching will match int color. | J5: interior.1 | K5: =textjoin(" ",true,B5,C5,D5,F5,E5,G5) -> 1LZ AQ9 HUQ | L5: =SUM( SUMIFS( PriceRef!$D$2:$D158, PriceRef!$A$2:$A158, "Seat", PriceRef!$B$2:$B158, $B5, PriceRef!$C$2:$C158, $C5 ), SUMIFS( PriceRef!$D$2:$D158, PriceRef!$A$2:$A158, "Stitching", PriceRef!$C$2:$C158, $F5 ), SUMIFS( PriceRef!$D$2:$D158, PriceRef!$A$2:$A158, "Suede", PriceRef!$C$2:$C158, $E5 ), SUMIFS( PriceRef!$D$2:$D158, PriceRef!$A$2:$A158, "TwoTone", PriceRef!$C$2:$C158, $G5 ) ) -> 0
A6: 1LZ Seats | B6: 1LZ | C6: AE4 | D6: AE4 | H6: Competition Sport Bucket seats | I6: Performance textile seating surface. Requires N26 Suede wrapped steering wheel $695 | J6: interior.1s | K6: =textjoin(" ",true,B6,C6,D6,F6,E6,G6) -> 1LZ AE4 AE4 | L6: =SUM( SUMIFS( PriceRef!$D$2:$D158, PriceRef!$A$2:$A158, "Seat", PriceRef!$B$2:$B158, $B6, PriceRef!$C$2:$C158, $C6 ), SUMIFS( PriceRef!$D$2:$D158, PriceRef!$A$2:$A158, "Stitching", PriceRef!$C$2:$C158, $F6 ), SUMIFS( PriceRef!$D$2:$D158, PriceRef!$A$2:$A158, "Suede", PriceRef!$C$2:$C158, $E6 ), SUMIFS( PriceRef!$D$2:$D158, PriceRef!$A$2:$A158, "TwoTone", PriceRef!$C$2:$C158, $G6 ) ) -> 995
A7: 1LZ Seats | B7: 1LZ | C7: AQ9 | D7: AQ9 | H7: GT1 Bucket seats | I7: Mulan Leather | J7: interior.1s | K7: =textjoin(" ",true,B7,C7,D7,F7,E7,G7) -> 1LZ AQ9 AQ9 | L7: =SUM( SUMIFS( PriceRef!$D$2:$D158, PriceRef!$A$2:$A158, "Seat", PriceRef!$B$2:$B158, $B7, PriceRef!$C$2:$C158, $C7 ), SUMIFS( PriceRef!$D$2:$D158, PriceRef!$A$2:$A158, "Stitching", PriceRef!$C$2:$C158, $F7 ), SUMIFS( PriceRef!$D$2:$D158, PriceRef!$A$2:$A158, "Suede", PriceRef!$C$2:$C158, $E7 ), SUMIFS( PriceRef!$D$2:$D158, PriceRef!$A$2:$A158, "TwoTone", PriceRef!$C$2:$C158, $G7 ) ) -> 0
A8: 2LZ Colors | B8: 2LZ | C8: AQ9 | D8: H1Y | H8: Jet Black Mulan | I8: AQ9 GT1 Seats. Interior color is on seats, doors, and console trim. Jet Black has silver stitching. | J8: interior.2 | K8: =textjoin(" ",true,B8,C8,D8,F8,E8,G8) -> 2LZ AQ9 H1Y | L8: =SUM( SUMIFS( PriceRef!$D$2:$D158, PriceRef!$A$2:$A158, "Seat", PriceRef!$B$2:$B158, $B8, PriceRef!$C$2:$C158, $C8 ), SUMIFS( PriceRef!$D$2:$D158, PriceRef!$A$2:$A158, "Stitching", PriceRef!$C$2:$C158, $F8 ), SUMIFS( PriceRef!$D$2:$D158, PriceRef!$A$2:$A158, "Suede", PriceRef!$C$2:$C158, $E8 ), SUMIFS( PriceRef!$D$2:$D158, PriceRef!$A$2:$A158, "TwoTone", PriceRef!$C$2:$C158, $G8 ) ) -> 0
A9: 2LZ Colors | B9: 2LZ | C9: AQ9 | D9: H1Y | F9: 38S | H9: Jet Black Mulan with Red Stitching | I9: AQ9 GT1 Seats. Interior color is on seats, doors, and console trim. | J9: interior.2 | K9: =textjoin(" ",true,B9,C9,D9,F9,E9,G9) -> 2LZ AQ9 H1Y 38S | L9: =SUM( SUMIFS( PriceRef!$D$2:$D158, PriceRef!$A$2:$A158, "Seat", PriceRef!$B$2:$B158, $B9, PriceRef!$C$2:$C158, $C9 ), SUMIFS( PriceRef!$D$2:$D158, PriceRef!$A$2:$A158, "Stitching", PriceRef!$C$2:$C158, $F9 ), SUMIFS( PriceRef!$D$2:$D158, PriceRef!$A$2:$A158, "Suede", PriceRef!$C$2:$C158, $E9 ), SUMIFS( PriceRef!$D$2:$D158, PriceRef!$A$2:$A158, "TwoTone", PriceRef!$C$2:$C158, $G9 ) ) -> 495
A10: 2LZ Colors | B10: 2LZ | C10: AQ9 | D10: H1Y | F10: 36S | H10: Jet Black Mulan with Yellow Stitching | I10: AQ9 GT1 Seats. Interior color is on seats, doors, and console trim. | J10: interior.2 | K10: =textjoin(" ",true,B10,C10,D10,F10,E10,G10) -> 2LZ AQ9 H1Y 36S | L10: =SUM( SUMIFS( PriceRef!$D$2:$D158, PriceRef!$A$2:$A158, "Seat", PriceRef!$B$2:$B158, $B10, PriceRef!$C$2:$C158, $C10 ), SUMIFS( PriceRef!$D$2:$D158, PriceRef!$A$2:$A158, "Stitching", PriceRef!$C$2:$C158, $F10 ), SUMIFS( PriceRef!$D$2:$D158, PriceRef!$A$2:$A158, "Suede", PriceRef!$C$2:$C158, $E10 ), SUMIFS( PriceRef!$D$2:$D158, PriceRef!$A$2:$A158, "TwoTone", PriceRef!$C$2:$C158, $G10 ) ) -> 495
A11: 2LZ Colors | B11: 2LZ | C11: AQ9 | D11: H1Y | F11: 37S | H11: Jet Black Mulan with Blue Stitching | I11: AQ9 GT1 Seats. Interior color is on seats, doors, and console trim. | J11: interior.2 | K11: =textjoin(" ",true,B11,C11,D11,F11,E11,G11) -> 2LZ AQ9 H1Y 37S | L11: =SUM( SUMIFS( PriceRef!$D$2:$D158, PriceRef!$A$2:$A158, "Seat", PriceRef!$B$2:$B158, $B11, PriceRef!$C$2:$C158, $C11 ), SUMIFS( PriceRef!$D$2:$D158, PriceRef!$A$2:$A158, "Stitching", PriceRef!$C$2:$C158, $F11 ), SUMIFS( PriceRef!$D$2:$D158, PriceRef!$A$2:$A158, "Suede", PriceRef!$C$2:$C158, $E11 ), SUMIFS( PriceRef!$D$2:$D158, PriceRef!$A$2:$A158, "TwoTone", PriceRef!$C$2:$C158, $G11 ) ) -> 495
A12: 2LZ Colors | B12: 2LZ | C12: AH2 | D12: HTM | H12: Jet Black Napa | I12: AH2 GT2 seats. Interior color is on seats, doors, and console trim. Jet Black has silver stitching. | J12: interior.2 | K12: =textjoin(" ",true,B12,C12,D12,F12,E12,G12) -> 2LZ AH2 HTM | L12: =SUM( SUMIFS( PriceRef!$D$2:$D158, PriceRef!$A$2:$A158, "Seat", PriceRef!$B$2:$B158, $B12, PriceRef!$C$2:$C158, $C12 ), SUMIFS( PriceRef!$D$2:$D158, PriceRef!$A$2:$A158, "Stitching", PriceRef!$C$2:$C158, $F12 ), SUMIFS( PriceRef!$D$2:$D158, PriceRef!$A$2:$A158, "Suede", PriceRef!$C$2:$C158, $E12 ), SUMIFS( PriceRef!$D$2:$D158, PriceRef!$A$2:$A158, "TwoTone", PriceRef!$C$2:$C158, $G12 ) ) -> 1695
A13: 2LZ Colors | B13: 2LZ | C13: AH2 | D13: HTM | F13: 38S | H13: Jet Black Napa with Red Stitching | I13: AH2 GT2 seats. Interior color is on seats, doors, and console trim. | J13: interior.2 | K13: =textjoin(" ",true,B13,C13,D13,F13,E13,G13) -> 2LZ AH2 HTM 38S | L13: =SUM( SUMIFS( PriceRef!$D$2:$D158, PriceRef!$A$2:$A158, "Seat", PriceRef!$B$2:$B158, $B13, PriceRef!$C$2:$C158, $C13 ), SUMIFS( PriceRef!$D$2:$D158, PriceRef!$A$2:$A158, "Stitching", PriceRef!$C$2:$C158, $F13 ), SUMIFS( PriceRef!$D$2:$D158, PriceRef!$A$2:$A158, "Suede", PriceRef!$C$2:$C158, $E13 ), SUMIFS( PriceRef!$D$2:$D158, PriceRef!$A$2:$A158, "TwoTone", PriceRef!$C$2:$C158, $G13 ) ) -> 2190
